Workbook

Sheet Nikes Sales Dataset - Worked f
A1: Order_ID | B1: Unique Order ID | C1: Gender_Category | D1: Product_Line | E1: Product_Name | F1: Size | G1: Size Filled | H1: Units_Sold | I1: Units Sold Filled | J1: MRP | K1: MRP Final | L1: Discount_Applied | M1: Cleaned Discount | N1: Sales Price | O1: Revenue | P1: Calculated Revenue | Q1: Order_Date | R1: Cleaned Order Date | S1: Month | T1: Year | U1: Sales_Channel | V1: Region | W1: Region corrected | X1: Profit
A2: 2000 | B2: =Nikes_Sales_Dataset___Working_file[[#This Row],[Order_ID]]&"_"&TEXT(Nikes_Sales_Dataset___Working_file[[#This Row],[Cleaned Order Date]],"yyyymmdd") -> 2000_20240309 | C2: Kids | D2: Training | E2: SuperRep Go | F2: M | G2: M | I2: =IF(ISBLANK(Nikes_Sales_Dataset___Working_file[[#This Row],[Units_Sold]]),IF(Nikes_Sales_Dataset___Working_file[[#This Row],[Profit]]<0,0,1),Nikes_Sales_Dataset___Working_file[[#This Row],[Units_Sold]]) -> 0 | K2: =IF(ISBLANK(Nikes_Sales_Dataset___Working_file[[#This Row],[MRP]]),MEDIAN(Nikes_Sales_Dataset___Working_file[[#All],[MRP]]),Nikes_Sales_Dataset___Working_file[[#This Row],[MRP]]) -> 6110.03 | L2: 0.47 | M2: =IF(ISBLANK(Nikes_Sales_Dataset___Working_file[[#This Row],[Discount_Applied]]),0,Nikes_Sales_Dataset___Working_file[[#This Row],[Discount_Applied]]) -> 0.47 | N2: =Nikes_Sales_Dataset___Working_file[[#This Row],[MRP Final]]*(1-Nikes_Sales_Dataset___Working_file[[#This Row],[Cleaned Discount]]) -> 3238.3159 | O2: 0 | P2: =Nikes_Sales_Dataset___Working_file[[#This Row],[Sales Price]]*Nikes_Sales_Dataset___Working_file[[#This Row],[Units Sold Filled]] -> 0 | Q2: 45360 | R2: =IF(ISBLANK(Nikes_Sales_Dataset___Working_file[[#This Row],[Order_Date]]),"Unknown Date",Nikes_Sales_Dataset___Working_file[[#This Row],[Order_Date]]) -> 45360 | S2: =IF(ISNUMBER(Nikes_Sales_Dataset___Working_file[[#This Row],[Cleaned Order Date]]),TEXT(Nikes_Sales_Dataset___Working_file[[#This Row],[Cleaned Order Date]],"mmm"),"Unknown") -> Mar | T2: =IF(ISNUMBER(Nikes_Sales_Dataset___Working_file[[#This Row],[Cleaned Order Date]]),TEXT(Nikes_Sales_Dataset___Working_file[[#This Row],[Cleaned Order Date]],"yyyy"),"Unknown") -> 2024 | U2: Online | V2: bengaluru | W2: Bangalore | X2: -770.45 | AB2: Size
A3: 2001 | B3: =Nikes_Sales_Dataset___Working_file[[#This Row],[Order_ID]]&"_"&TEXT(Nikes_Sales_Dataset___Working_file[[#This Row],[Cleaned Order Date]],"yyyymmdd") -> 2001_20240709 | C3: Women | D3: Soccer | E3: Tiempo Legend | F3: M | G3: M | H3: 3 | I3: =IF(ISBLANK(Nikes_Sales_Dataset___Working_file[[#This Row],[Units_Sold]]),IF(Nikes_Sales_Dataset___Working_file[[#This Row],[Profit]]<0,0,1),Nikes_Sales_Dataset___Working_file[[#This Row],[Units_Sold]]) -> 3 | J3: 4957.93 | K3: =IF(ISBLANK(Nikes_Sales_Dataset___Working_file[[#This Row],[MRP]]),MEDIAN(Nikes_Sales_Dataset___Working_file[[#All],[MRP]]),Nikes_Sales_Dataset___Working_file[[#This Row],[MRP]]) -> 4957.93 | M3: =IF(ISBLANK(Nikes_Sales_Dataset___Working_file[[#This Row],[Discount_Applied]]),0,Nikes_Sales_Dataset___Working_file[[#This Row],[Discount_Applied]]) -> 0 | N3: =Nikes_Sales_Dataset___Working_file[[#This Row],[MRP Final]]*(1-Nikes_Sales_Dataset___Working_file[[#This Row],[Cleaned Discount]]) -> 4957.93 | O3: 0 | P3: =Nikes_Sales_Dataset___Working_file[[#This Row],[Sales Price]]*Nikes_Sales_Dataset___Working_file[[#This Row],[Units Sold Filled]] -> 14873.79 | Q3: 45482 | R3: =IF(ISBLANK(Nikes_Sales_Dataset___Working_file[[#This Row],[Order_Date]]),"Unknown Date",Nikes_Sales_Dataset___Working_file[[#This Row],[Order_Date]]) -> 45482 | S3: =IF(ISNUMBER(Nikes_Sales_Dataset___Working_file[[#This Row],[Cleaned Order Date]]),TEXT(Nikes_Sales_Dataset___Working_file[[#This Row],[Cleaned Order Date]],"mmm"),"Unknown") -> Jul | T3: =IF(ISNUMBER(Nikes_Sales_Dataset___Working_file[[#This Row],[Cleaned Order Date]]),TEXT(Nikes_Sales_Dataset___Working_file[[#This Row],[Cleaned Order Date]],"yyyy"),"Unknown") -> 2024 | U3: Retail | V3: Hyd | W3: Hyderabad | X3: -112.53 | AB3: M | AC3: =COUNTIF(G:G,AB3) -> 1261
A4: 2002 | B4: =Nikes_Sales_Dataset___Working_file[[#This Row],[Order_ID]]&"_"&TEXT(Nikes_Sales_Dataset___Working_file[[#This Row],[Cleaned Order Date]],"yyyymmdd") -> 2002_Unknown Date | C4: Women | D4: Soccer | E4: Premier III | F4: M | G4: M | H4: 4 | I4: =IF(ISBLANK(Nikes_Sales_Dataset___Working_file[[#This Row],[Units_Sold]]),IF(Nikes_Sales_Dataset___Working_file[[#This Row],[Profit]]<0,0,1),Nikes_Sales_Dataset___Working_file[[#This Row],[Units_Sold]]) -> 4 | K4: =IF(ISBLANK(Nikes_Sales_Dataset___Working_file[[#This Row],[MRP]]),MEDIAN(Nikes_Sales_Dataset___Working_file[[#All],[MRP]]),Nikes_Sales_Dataset___Working_file[[#This Row],[MRP]]) -> 6110.03 | M4: =IF(ISBLANK(Nikes_Sales_Dataset___Working_file[[#This Row],[Discount_Applied]]),0,Nikes_Sales_Dataset___Working_file[[#This Row],[Discount_Applied]]) -> 0 | N4: =Nikes_Sales_Dataset___Working_file[[#This Row],[MRP Final]]*(1-Nikes_Sales_Dataset___Working_file[[#This Row],[Cleaned Discount]]) -> 6110.03 | O4: 0 | P4: =Nikes_Sales_Dataset___Working_file[[#This Row],[Sales Price]]*Nikes_Sales_Dataset___Working_file[[#This Row],[Units Sold Filled]] -> 24440.12 | R4: =IF(ISBLANK(Nikes_Sales_Dataset___Working_file[[#This Row],[Order_Date]]),"Unknown Date",Nikes_Sales_Dataset___Working_file[[#This Row],[Order_Date]]) -> Unknown Date | S4: =IF(ISNUMBER(Nikes_Sales_Dataset___Working_file[[#This Row],[Cleaned Order Date]]),TEXT(Nikes_Sales_Dataset___Working_file[[#This Row],[Cleaned Order Date]],"mmm"),"Unknown") -> Unknown | T4: =IF(ISNUMBER(Nikes_Sales_Dataset___Working_file[[#This Row],[Cleaned Order Date]]),TEXT(Nikes_Sales_Dataset___Working_file[[#This Row],[Cleaned Order Date]],"yyyy"),"Unknown") -> Unknown | U4: Retail | V4: Mumbai | W4: Mumbai | X4: 3337.34 | AB4: L | AC4: =COUNTIF(G:G,AB4) -> 666
A5: 2003 | B5: =Nikes_Sales_Dataset___Working_file[[#This Row],[Order_ID]]&"_"&TEXT(Nikes_Sales_Dataset___Working_file[[#This Row],[Cleaned Order Date]],"yyyymmdd") -> 2003_20241004 | C5: Kids | D5: Lifestyle | E5: Blazer Mid | F5: L | G5: L | I5: =IF(ISBLANK(Nikes_Sales_Dataset___Working_file[[#This Row],[Units_Sold]]),IF(Nikes_Sales_Dataset___Working_file[[#This Row],[Profit]]<0,0,1),Nikes_Sales_Dataset___Working_file[[#This Row],[Units_Sold]]) -> 1 | J5: 9673.57 | K5: =IF(ISBLANK(Nikes_Sales_Dataset___Working_file[[#This Row],[MRP]]),MEDIAN(Nikes_Sales_Dataset___Working_file[[#All],[MRP]]),Nikes_Sales_Dataset___Working_file[[#This Row],[MRP]]) -> 9673.57 | M5: =IF(ISBLANK(Nikes_Sales_Dataset___Working_file[[#This Row],[Discount_Applied]]),0,Nikes_Sales_Dataset___Working_file[[#This Row],[Discount_Applied]]) -> 0 | N5: =Nikes_Sales_Dataset___Working_file[[#This Row],[MRP Final]]*(1-Nikes_Sales_Dataset___Working_file[[#This Row],[Cleaned Discount]]) -> 9673.57 | O5: 0 | P5: =Nikes_Sales_Dataset___Working_file[[#This Row],[Sales Price]]*Nikes_Sales_Dataset___Working_file[[#This Row],[Units Sold Filled]] -> 9673.57 | Q5: 45569 | R5: =IF(ISBLANK(Nikes_Sales_Dataset___Working_file[[#This Row],[Order_Date]]),"Unknown Date",Nikes_Sales_Dataset___Working_file[[#This Row],[Order_Date]]) -> 45569 | S5: =IF(ISNUMBER(Nikes_Sales_Dataset___Working_file[[#This Row],[Cleaned Order Date]]),TEXT(Nikes_Sales_Dataset___Working_file[[#This Row],[Cleaned Order Date]],"mmm"),"Unknown") -> Oct | T5: =IF(ISNUMBER(Nikes_Sales_Dataset___Working_file[[#This Row],[Cleaned Order Date]]),TEXT(Nikes_Sales_Dataset___Working_file[[#This Row],[Cleaned Order Date]],"yyyy"),"Unknown") -> 2024 | U5: Online | V5: Pune | W5: Pune | X5: 3376.85 | AB5: XL | AC5: =COUNTIF(G:G,AB5) -> 573
A6: 2004 | B6: =Nikes_Sales_Dataset___Working_file[[#This Row],[Order_ID]]&"_"&TEXT(Nikes_Sales_Dataset___Working_file[[#This Row],[Cleaned Order Date]],"yyyymmdd") -> 2004_20240912 | C6: Kids | D6: Running | E6: React Infinity | F6: XL | G6: XL | I6: =IF(ISBLANK(Nikes_Sales_Dataset___Working_file[[#This Row],[Units_Sold]]),IF(Nikes_Sales_Dataset___Working_file[[#This Row],[Profit]]<0,0,1),Nikes_Sales_Dataset___Working_file[[#This Row],[Units_Sold]]) -> 1 | K6: =IF(ISBLANK(Nikes_Sales_Dataset___Working_file[[#This Row],[MRP]]),MEDIAN(Nikes_Sales_Dataset___Working_file[[#All],[MRP]]),Nikes_Sales_Dataset___Working_file[[#This Row],[MRP]]) -> 6110.03 | M6: =IF(ISBLANK(Nikes_Sales_Dataset___Working_file[[#This Row],[Discount_Applied]]),0,Nikes_Sales_Dataset___Working_file[[#This Row],[Discount_Applied]]) -> 0 | N6: =Nikes_Sales_Dataset___Working_file[[#This Row],[MRP Final]]*(1-Nikes_Sales_Dataset___Working_file[[#This Row],[Cleaned Discount]]) -> 6110.03 | O6: 0 | P6: =Nikes_Sales_Dataset___Working_file[[#This Row],[Sales Price]]*Nikes_Sales_Dataset___Working_file[[#This Row],[Units Sold Filled]] -> 6110.03 | Q6: 45547 | R6: =IF(ISBLANK(Nikes_Sales_Dataset___Working_file[[#This Row],[Order_Date]]),"Unknown Date",Nikes_Sales_Dataset___Working_file[[#This Row],[Order_Date]]) -> 45547 | S6: =IF(ISNUMBER(Nikes_Sales_Dataset___Working_file[[#This Row],[Cleaned Order Date]]),TEXT(Nikes_Sales_Dataset___Working_file[[#This Row],[Cleaned Order Date]],"mmm"),"Unknown") -> Sep | T6: =IF(ISNUMBER(Nikes_Sales_Dataset___Working_file[[#This Row],[Cleaned Order Date]]),TEXT(Nikes_Sales_Dataset___Working_file[[#This Row],[Cleaned Order Date]],"yyyy"),"Unknown") -> 2024 | U6: Retail | V6: Delhi | W6: Delhi | X6: 187.89 | AB6: Mode="M"
A7: 2005 | B7: =Nikes_Sales_Dataset___Working_file[[#This Row],[Order_ID]]&"_"&TEXT(Nikes_Sales_Dataset___Working_file[[#This Row],[Cleaned Order Date]],"yyyymmdd") -> 2005_Unknown Date | C7: Women | D7: Training | E7: Flex Trainer | F7: M | G7: M | H7: 1 | I7: =IF(ISBLANK(Nikes_Sales_Dataset___Working_file[[#This Row],[Units_Sold]]),IF(Nikes_Sales_Dataset___Working_file[[#This Row],[Profit]]<0,0,1),Nikes_Sales_Dataset___Working_file[[#This Row],[Units_Sold]]) -> 1 | J7: 7363.96 | K7: =IF(ISBLANK(Nikes_Sales_Dataset___Working_file[[#This Row],[MRP]]),MEDIAN(Nikes_Sales_Dataset___Working_file[[#All],[MRP]]),Nikes_Sales_Dataset___Working_file[[#This Row],[MRP]]) -> 7363.96 | M7: =IF(ISBLANK(Nikes_Sales_Dataset___Working_file[[#This Row],[Discount_Applied]]),0,Nikes_Sales_Dataset___Working_file[[#This Row],[Discount_Applied]]) -> 0 | N7: =Nikes_Sales_Dataset___Working_file[[#This Row],[MRP Final]]*(1-Nikes_Sales_Dataset___Working_file[[#This Row],[Cleaned Discount]]) -> 7363.96 | O7: 0 | P7: =Nikes_Sales_Dataset___Working_file[[#This Row],[Sales Price]]*Nikes_Sales_Dataset___Working_file[[#This Row],[Units Sold Filled]] -> 7363.96 | R7: =IF(ISBLANK(Nikes_Sales_Dataset___Working_file[[#This Row],[Order_Date]]),"Unknown Date",Nikes_Sales_Dataset___Working_file[[#This Row],[Order_Date]]) -> Unknown Date | S7: =IF(ISNUMBER(Nikes_Sales_Dataset___Working_file[[#This Row],[Cleaned Order Date]]),TEXT(Nikes_Sales_Dataset___Working_file[[#This Row],[Cleaned Order Date]],"mmm"),"Unknown") -> Unknown | T7: =IF(ISNUMBER(Nikes_Sales_Dataset___Working_file[[#This Row],[Cleaned Order Date]]),TEXT(Nikes_Sales_Dataset___Working_file[[#This Row],[Cleaned Order Date]],"yyyy"),"Unknown") -> Unknown | U7: Retail | V7: Delhi | W7: Delhi | X7: 1415.98
A8: 2006 | B8: =Nikes_Sales_Dataset___Working_file[[#This Row],[Order_ID]]&"_"&TEXT(Nikes_Sales_Dataset___Working_file[[#This Row],[Cleaned Order Date]],"yyyymmdd") -> 2006_20250604 | C8: Men | D8: Training | E8: SuperRep Go | F8: M | G8: M | I8: =IF(ISBLANK(Nikes_Sales_Dataset___Working_file[[#This Row],[Units_Sold]]),IF(Nikes_Sales_Dataset___Working_file[[#This Row],[Profit]]<0,0,1),Nikes_Sales_Dataset___Working_file[[#This Row],[Units_Sold]]) -> 1 | J8: 6819.78 | K8: =IF(ISBLANK(Nikes_Sales_Dataset___Working_file[[#This Row],[MRP]]),MEDIAN(Nikes_Sales_Dataset___Working_file[[#All],[MRP]]),Nikes_Sales_Dataset___Working_file[[#This Row],[MRP]]) -> 6819.78 | M8: =IF(ISBLANK(Nikes_Sales_Dataset___Working_file[[#This Row],[Discount_Applied]]),0,Nikes_Sales_Dataset___Working_file[[#This Row],[Discount_Applied]]) -> 0 | N8: =Nikes_Sales_Dataset___Working_file[[#This Row],[MRP Final]]*(1-Nikes_Sales_Dataset___Working_file[[#This Row],[Cleaned Discount]]) -> 6819.78 | O8: 0 | P8: =Nikes_Sales_Dataset___Working_file[[#This Row],[Sales Price]]*Nikes_Sales_Dataset___Working_file[[#This Row],[Units Sold Filled]] -> 6819.78 | Q8: 45812 | R8: =IF(ISBLANK(Nikes_Sales_Dataset___Working_file[[#This Row],[Order_Date]]),"Unknown Date",Nikes_Sales_Dataset___Working_file[[#This Row],[Order_Date]]) -> 45812 | S8: =IF(ISNUMBER(Nikes_Sales_Dataset___Working_file[[#This Row],[Cleaned Order Date]]),TEXT(Nikes_Sales_Dataset___Working_file[[#This Row],[Cleaned Order Date]],"mmm"),"Unknown") -> Jun | T8: =IF(ISNUMBER(Nikes_Sales_Dataset___Working_file[[#This Row],[Cleaned Order Date]]),TEXT(Nikes_Sales_Dataset___Working_file[[#This Row],[Cleaned Order Date]],"yyyy"),"Unknown") -> 2025 | U8: Online | V8: Bangalore | W8: Bangalore | X8: 1802.09
A9: 2007 | B9: =Nikes_Sales_Dataset___Working_file[[#This Row],[Order_ID]]&"_"&TEXT(Nikes_Sales_Dataset___Working_file[[#This Row],[Cleaned Order Date]],"yyyymmdd") -> 2007_Unknown Date | C9: Kids | D9: Training | E9: SuperRep Go | F9: M | G9: M | H9: 1 | I9: =IF(ISBLANK(Nikes_Sales_Dataset___Working_file[[#This Row],[Units_Sold]]),IF(Nikes_Sales_Dataset___Working_file[[#This Row],[Profit]]<0,0,1),Nikes_Sales_Dataset___Working_file[[#This Row],[Units_Sold]]) -> 1 | K9: =IF(ISBLANK(Nikes_Sales_Dataset___Working_file[[#This Row],[MRP]]),MEDIAN(Nikes_Sales_Dataset___Working_file[[#All],[MRP]]),Nikes_Sales_Dataset___Working_file[[#This Row],[MRP]]) -> 6110.03 | L9: 0.32 | M9: =IF(ISBLANK(Nikes_Sales_Dataset___Working_file[[#This Row],[Discount_Applied]]),0,Nikes_Sales_Dataset___Working_file[[#This Row],[Discount_Applied]]) -> 0.32 | N9: =Nikes_Sales_Dataset___Working_file[[#This Row],[MRP Final]]*(1-Nikes_Sales_Dataset___Working_file[[#This Row],[Cleaned Discount]]) -> 4154.8204 | O9: 0 | P9: =Nikes_Sales_Dataset___Working_file[[#This Row],[Sales Price]]*Nikes_Sales_Dataset___Working_file[[#This Row],[Units Sold Filled]] -> 4154.8204 | R9: =IF(ISBLANK(Nikes_Sales_Dataset___Working_file[[#This Row],[Order_Date]]),"Unknown Date",Nikes_Sales_Dataset___Working_file[[#This Row],[Order_Date]]) -> Unknown Date | S9: =IF(ISNUMBER(Nikes_Sales_Dataset___Working_file[[#This Row],[Cleaned Order Date]]),TEXT(Nikes_Sales_Dataset___Working_file[[#This Row],[Cleaned Order Date]],"mmm"),"Unknown") -> Unknown | T9: =IF(ISNUMBER(Nikes_Sales_Dataset___Working_file[[#This Row],[Cleaned Order Date]]),TEXT(Nikes_Sales_Dataset___Working_file[[#This Row],[Cleaned Order Date]],"yyyy"),"Unknown") -> Unknown | U9: Retail | V9: Bangalore | W9: Bangalore | X9: 2928.36
A10: 2008 | B10: =Nikes_Sales_Dataset___Working_file[[#This Row],[Order_ID]]&"_"&TEXT(Nikes_Sales_Dataset___Working_file[[#This Row],[Cleaned Order Date]],"yyyymmdd") -> 2008_20241011 | C10: Women | D10: Soccer | E10: Premier III | F10: 11 | G10: L | H10: -1 | I10: =IF(ISBLANK(Nikes_Sales_Dataset___Working_file[[#This Row],[Units_Sold]]),IF(Nikes_Sales_Dataset___Working_file[[#This Row],[Profit]]<0,0,1),Nikes_Sales_Dataset___Working_file[[#This Row],[Units_Sold]]) -> -1 | K10: =IF(ISBLANK(Nikes_Sales_Dataset___Working_file[[#This Row],[MRP]]),MEDIAN(Nikes_Sales_Dataset___Working_file[[#All],[MRP]]),Nikes_Sales_Dataset___Working_file[[#This Row],[MRP]]) -> 6110.03 | M10: =IF(ISBLANK(Nikes_Sales_Dataset___Working_file[[#This Row],[Discount_Applied]]),0,Nikes_Sales_Dataset___Working_file[[#This Row],[Discount_Applied]]) -> 0 | N10: =Nikes_Sales_Dataset___Working_file[[#This Row],[MRP Final]]*(1-Nikes_Sales_Dataset___Working_file[[#This Row],[Cleaned Discount]]) -> 6110.03 | O10: 0 | P10: =Nikes_Sales_Dataset___Working_file[[#This Row],[Sales Price]]*Nikes_Sales_Dataset___Working_file[[#This Row],[Units Sold Filled]] -> -6110.03 | Q10: 45576 | R10: =IF(ISBLANK(Nikes_Sales_Dataset___Working_file[[#This Row],[Order_Date]]),"Unknown Date",Nikes_Sales_Dataset___Working_file[[#This Row],[Order_Date]]) -> 45576 | S10: =IF(ISNUMBER(Nikes_Sales_Dataset___Working_file[[#This Row],[Cleaned Order Date]]),TEXT(Nikes_Sales_Dataset___Working_file[[#This Row],[Cleaned Order Date]],"mmm"),"Unknown") -> Oct | T10: =IF(ISNUMBER(Nikes_Sales_Dataset___Working_file[[#This Row],[Cleaned Order Date]]),TEXT(Nikes_Sales_Dataset___Working_file[[#This Row],[Cleaned Order Date]],"yyyy"),"Unknown") -> 2024 | U10: Online | V10: Hyderabad | W10: Hyderabad | X10: -731.18
A11: 2009 | B11: =Nikes_Sales_Dataset___Working_file[[#This Row],[Order_ID]]&"_"&TEXT(Nikes_Sales_Dataset___Working_file[[#This Row],[Cleaned Order Date]],"yyyymmdd") -> 2009_Unknown Date | C11: Men | D11: Soccer | E11: Mercurial Superfly | F11: M | G11: M | H11: 4 | I11: =IF(ISBLANK(Nikes_Sales_Dataset___Working_file[[#This Row],[Units_Sold]]),IF(Nikes_Sales_Dataset___Working_file[[#This Row],[Profit]]<0,0,1),Nikes_Sales_Dataset___Working_file[[#This Row],[Units_Sold]]) -> 4 | K11: =IF(ISBLANK(Nikes_Sales_Dataset___Working_file[[#This Row],[MRP]]),MEDIAN(Nikes_Sales_Dataset___Working_file[[#All],[MRP]]),Nikes_Sales_Dataset___Working_file[[#This Row],[MRP]]) -> 6110.03 | M11: =IF(ISBLANK(Nikes_Sales_Dataset___Working_file[[#This Row],[Discount_Applied]]),0,Nikes_Sales_Dataset___Working_file[[#This Row],[Discount_Applied]]) -> 0 | N11: =Nikes_Sales_Dataset___Working_file[[#This Row],[MRP Final]]*(1-Nikes_Sales_Dataset___Working_file[[#This Row],[Cleaned Discount]]) -> 6110.03 | O11: 0 | P11: =Nikes_Sales_Dataset___Working_file[[#This Row],[Sales Price]]*Nikes_Sales_Dataset___Working_file[[#This Row],[Units Sold Filled]] -> 24440.12 | R11: =IF(ISBLANK(Nikes_Sales_Dataset___Working_file[[#This Row],[Order_Date]]),"Unknown Date",Nikes_Sales_Dataset___Working_file[[#This Row],[Order_Date]]) -> Unknown Date | S11: =IF(ISNUMBER(Nikes_Sales_Dataset___Working_file[[#This Row],[Cleaned Order Date]]),TEXT(Nikes_Sales_Dataset___Working_file[[#This Row],[Cleaned Order Date]],"mmm"),"Unknown") -> Unknown | T11: =IF(ISNUMBER(Nikes_Sales_Dataset___Working_file[[#This Row],[Cleaned Order Date]]),TEXT(Nikes_Sales_Dataset___Working_file[[#This Row],[Cleaned Order Date]],"yyyy"),"Unknown") -> Unknown | U11: Online | V11: Pune | W11: Pune | X11: 3929.61
A12: 2010 | B12: =Nikes_Sales_Dataset___Working_file[[#This Row],[Order_ID]]&"_"&TEXT(Nikes_Sales_Dataset___Working_file[[#This Row],[Cleaned Order Date]],"yyyymmdd") -> 2010_20250116 | C12: Kids | D12: Lifestyle | E12: Waffle One | F12: L | G12: L | H12: 1 | I12: =IF(ISBLANK(Nikes_Sales_Dataset___Working_file[[#This Row],[Units_Sold]]),IF(Nikes_Sales_Dataset___Working_file[[#This Row],[Profit]]<0,0,1),Nikes_Sales_Dataset___Working_file[[#This Row],[Units_Sold]]) -> 1 | J12: 7949.83 | K12: =IF(ISBLANK(Nikes_Sales_Dataset___Working_file[[#This Row],[MRP]]),MEDIAN(Nikes_Sales_Dataset___Working_file[[#All],[MRP]]),Nikes_Sales_Dataset___Working_file[[#This Row],[MRP]]) -> 7949.83 | M12: =IF(ISBLANK(Nikes_Sales_Dataset___Working_file[[#This Row],[Discount_Applied]]),0,Nikes_Sales_Dataset___Working_file[[#This Row],[Discount_Applied]]) -> 0 | N12: =Nikes_Sales_Dataset___Working_file[[#This Row],[MRP Final]]*(1-Nikes_Sales_Dataset___Working_file[[#This Row],[Cleaned Discount]]) -> 7949.83 | O12: 0 | P12: =Nikes_Sales_Dataset___Working_file[[#This Row],[Sales Price]]*Nikes_Sales_Dataset___Working_file[[#This Row],[Units Sold Filled]] -> 7949.83 | Q12: 45673 | R12: =IF(ISBLANK(Nikes_Sales_Dataset___Working_file[[#This Row],[Order_Date]]),"Unknown Date",Nikes_Sales_Dataset___Working_file[[#This Row],[Order_Date]]) -> 45673 | S12: =IF(ISNUMBER(Nikes_Sales_Dataset___Working_file[[#This Row],[Cleaned Order Date]]),TEXT(Nikes_Sales_Dataset___Working_file[[#This Row],[Cleaned Order Date]],"mmm"),"Unknown") -> Jan | T12: =IF(ISNUMBER(Nikes_Sales_Dataset___Working_file[[#This Row],[Cleaned Order Date]]),TEXT(Nikes_Sales_Dataset___Working_file[[#This Row],[Cleaned Order Date]],"yyyy"),"Unknown") -> 2025 | U12: Online | V12: Pune | W12: Pune | X12: 1965.56
A13: 2011 | B13: =Nikes_Sales_Dataset___Working_file[[#This Row],[Order_ID]]&"_"&TEXT(Nikes_Sales_Dataset___Working_file[[#This Row],[Cleaned Order Date]],"yyyymmdd") -> 2011_Unknown Date | C13: Women | D13: Training | E13: Flex Trainer | F13: L | G13: L | H13: -1 | I13: =IF(ISBLANK(Nikes_Sales_Dataset___Working_file[[#This Row],[Units_Sold]]),IF(Nikes_Sales_Dataset___Working_file[[#This Row],[Profit]]<0,0,1),Nikes_Sales_Dataset___Working_file[[#This Row],[Units_Sold]]) -> -1 | J13: 9586.08 | K13: =IF(ISBLANK(Nikes_Sales_Dataset___Working_file[[#This Row],[MRP]]),MEDIAN(Nikes_Sales_Dataset___Working_file[[#All],[MRP]]),Nikes_Sales_Dataset___Working_file[[#This Row],[MRP]]) -> 9586.08 | M13: =IF(ISBLANK(Nikes_Sales_Dataset___Working_file[[#This Row],[Discount_Applied]]),0,Nikes_Sales_Dataset___Working_file[[#This Row],[Discount_Applied]]) -> 0 | N13: =Nikes_Sales_Dataset___Working_file[[#This Row],[MRP Final]]*(1-Nikes_Sales_Dataset___Working_file[[#This Row],[Cleaned Discount]]) -> 9586.08 | O13: 0 | P13: =Nikes_Sales_Dataset___Working_file[[#This Row],[Sales Price]]*Nikes_Sales_Dataset___Working_file[[#This Row],[Units Sold Filled]] -> -9586.08 | R13: =IF(ISBLANK(Nikes_Sales_Dataset___Working_file[[#This Row],[Order_Date]]),"Unknown Date",Nikes_Sales_Dataset___Working_file[[#This Row],[Order_Date]]) -> Unknown Date | S13: =IF(ISNUMBER(Nikes_Sales_Dataset___Working_file[[#This Row],[Cleaned Order Date]]),TEXT(Nikes_Sales_Dataset___Working_file[[#This Row],[Cleaned Order Date]],"mmm"),"Unknown") -> Unknown | T13: =IF(ISNUMBER(Nikes_Sales_Dataset___Working_file[[#This Row],[Cleaned Order Date]]),TEXT(Nikes_Sales_Dataset___Working_file[[#This Row],[Cleaned Order Date]],"yyyy"),"Unknown") -> Unknown | U13: Retail | V13: Hyd | W13: Hyderabad | X13: 1667.08
A14: 2018 | B14: =Nikes_Sales_Dataset___Working_file[[#This Row],[Order_ID]]&"_"&TEXT(Nikes_Sales_Dataset___Working_file[[#This Row],[Cleaned Order Date]],"yyyymmdd") -> 2018_20241113 | C14: Kids | D14: Lifestyle | E14: Blazer Mid | G14: M | H14: -1 | I14: =IF(ISBLANK(Nikes_Sales_Dataset___Working_file[[#This Row],[Units_Sold]]),IF(Nikes_Sales_Dataset___Working_file[[#This Row],[Profit]]<0,0,1),Nikes_Sales_Dataset___Working_file[[#This Row],[Units_Sold]]) -> -1 | K14: =IF(ISBLANK(Nikes_Sales_Dataset___Working_file[[#This Row],[MRP]]),MEDIAN(Nikes_Sales_Dataset___Working_file[[#All],[MRP]]),Nikes_Sales_Dataset___Working_file[[#This Row],[MRP]]) -> 6110.03 | L14: 0.86 | M14: =IF(ISBLANK(Nikes_Sales_Dataset___Working_file[[#This Row],[Discount_Applied]]),0,Nikes_Sales_Dataset___Working_file[[#This Row],[Discount_Applied]]) -> 0.86 | N14: =Nikes_Sales_Dataset___Working_file[[#This Row],[MRP Final]]*(1-Nikes_Sales_Dataset___Working_file[[#This Row],[Cleaned Discount]]) -> 855.4042 | O14: 0 | P14: =Nikes_Sales_Dataset___Working_file[[#This Row],[Sales Price]]*Nikes_Sales_Dataset___Working_file[[#This Row],[Units Sold Filled]] -> -855.4042 | Q14: 45609 | R14: =IF(ISBLANK(Nikes_Sales_Dataset___Working_file[[#This Row],[Order_Date]]),"Unknown Date",Nikes_Sales_Dataset___Working_file[[#This Row],[Order_Date]]) -> 45609 | S14: =IF(ISNUMBER(Nikes_Sales_Dataset___Working_file[[#This Row],[Cleaned Order Date]]),TEXT(Nikes_Sales_Dataset___Working_file[[#This Row],[Cleaned Order Date]],"mmm"),"Unknown") -> Nov | T14: =IF(ISNUMBER(Nikes_Sales_Dataset___Working_file[[#This Row],[Cleaned Order Date]]),TEXT(Nikes_Sales_Dataset___Working_file[[#This Row],[Cleaned Order Date]],"yyyy"),"Unknown") -> 2024 | U14: Online | V14: Delhi | W14: Delhi | X14: 2109.48
A15: 2013 | B15: =Nikes_Sales_Dataset___Working_file[[#This Row],[Order_ID]]&"_"&TEXT(Nikes_Sales_Dataset___Working_file[[#This Row],[Cleaned Order Date]],"yyyymmdd") -> 2013_20240919 | C15: Kids | D15: Training | E15: SuperRep Go | G15: M | I15: =IF(ISBLANK(Nikes_Sales_Dataset___Working_file[[#This Row],[Units_Sold]]),IF(Nikes_Sales_Dataset___Working_file[[#This Row],[Profit]]<0,0,1),Nikes_Sales_Dataset___Working_file[[#This Row],[Units_Sold]]) -> 1 | J15: 9671.05 | K15: =IF(ISBLANK(Nikes_Sales_Dataset___Working_file[[#This Row],[MRP]]),MEDIAN(Nikes_Sales_Dataset___Working_file[[#All],[MRP]]),Nikes_Sales_Dataset___Working_file[[#This Row],[MRP]]) -> 9671.05 | M15: =IF(ISBLANK(Nikes_Sales_Dataset___Working_file[[#This Row],[Discount_Applied]]),0,Nikes_Sales_Dataset___Working_file[[#This Row],[Discount_Applied]]) -> 0 | N15: =Nikes_Sales_Dataset___Working_file[[#This Row],[MRP Final]]*(1-Nikes_Sales_Dataset___Working_file[[#This Row],[Cleaned Discount]]) -> 9671.05 | O15: 0 | P15: =Nikes_Sales_Dataset___Working_file[[#This Row],[Sales Price]]*Nikes_Sales_Dataset___Working_file[[#This Row],[Units Sold Filled]] -> 9671.05 | Q15: 45554 | R15: =IF(ISBLANK(Nikes_Sales_Dataset___Working_file[[#This Row],[Order_Date]]),"Unknown Date",Nikes_Sales_Dataset___Working_file[[#This Row],[Order_Date]]) -> 45554 | S15: =IF(ISNUMBER(Nikes_Sales_Dataset___Working_file[[#This Row],[Cleaned Order Date]]),TEXT(Nikes_Sales_Dataset___Working_file[[#This Row],[Cleaned Order Date]],"mmm"),"Unknown") -> Sep | T15: =IF(ISNUMBER(Nikes_Sales_Dataset___Working_file[[#This Row],[Cleaned Order Date]]),TEXT(Nikes_Sales_Dataset___Working_file[[#This Row],[Cleaned Order Date]],"yyyy"),"Unknown") -> 2024 | U15: Online | V15: hyderbad | W15: Hyderabad | X15: 299.34
A16: 2014 | B16: =Nikes_Sales_Dataset___Working_file[[#This Row],[Order_ID]]&"_"&TEXT(Nikes_Sales_Dataset___Working_file[[#This Row],[Cleaned Order Date]],"yyyymmdd") -> 2014_20250412 | C16: Women | D16: Running | E16: React Infinity | F16: 11 | G16: L | I16: =IF(ISBLANK(Nikes_Sales_Dataset___Working_file[[#This Row],[Units_Sold]]),IF(Nikes_Sales_Dataset___Working_file[[#This Row],[Profit]]<0,0,1),Nikes_Sales_Dataset___Working_file[[#This Row],[Units_Sold]]) -> 0 | K16: =IF(ISBLANK(Nikes_Sales_Dataset___Working_file[[#This Row],[MRP]]),MEDIAN(Nikes_Sales_Dataset___Working_file[[#All],[MRP]]),Nikes_Sales_Dataset___Working_file[[#This Row],[MRP]]) -> 6110.03 | M16: =IF(ISBLANK(Nikes_Sales_Dataset___Working_file[[#This Row],[Discount_Applied]]),0,Nikes_Sales_Dataset___Working_file[[#This Row],[Discount_Applied]]) -> 0 | N16: =Nikes_Sales_Dataset___Working_file[[#This Row],[MRP Final]]*(1-Nikes_Sales_Dataset___Working_file[[#This Row],[Cleaned Discount]]) -> 6110.03 | O16: 0 | P16: =Nikes_Sales_Dataset___Working_file[[#This Row],[Sales Price]]*Nikes_Sales_Dataset___Working_file[[#This Row],[Units Sold Filled]] -> 0 | Q16: 45759 | R16: =IF(ISBLANK(Nikes_Sales_Dataset___Working_file[[#This Row],[Order_Date]]),"Unknown Date",Nikes_Sales_Dataset___Working_file[[#This Row],[Order_Date]]) -> 45759 | S16: =IF(ISNUMBER(Nikes_Sales_Dataset___Working_file[[#This Row],[Cleaned Order Date]]),TEXT(Nikes_Sales_Dataset___Working_file[[#This Row],[Cleaned Order Date]],"mmm"),"Unknown") -> Apr | T16: =IF(ISNUMBER(Nikes_Sales_Dataset___Working_file[[#This Row],[Cleaned Order Date]]),TEXT(Nikes_Sales_Dataset___Working_file[[#This Row],[Cleaned Order Date]],"yyyy"),"Unknown") -> 2025 | U16: Online | V16: Bangalore | W16: Bangalore | X16: -1044.4
A17: 2015 | B17: =Nikes_Sales_Dataset___Working_file[[#This Row],[Order_ID]]&"_"&TEXT(Nikes_Sales_Dataset___Working_file[[#This Row],[Cleaned Order Date]],"yyyymmdd") -> 2015_20250531 | C17: Kids | D17: Basketball | E17: Air Jordan | G17: M | I17: =IF(ISBLANK(Nikes_Sales_Dataset___Working_file[[#This Row],[Units_Sold]]),IF(Nikes_Sales_Dataset___Working_file[[#This Row],[Profit]]<0,0,1),Nikes_Sales_Dataset___Working_file[[#This Row],[Units_Sold]]) -> 1 | J17: 3285.52 | K17: =IF(ISBLANK(Nikes_Sales_Dataset___Working_file[[#This Row],[MRP]]),MEDIAN(Nikes_Sales_Dataset___Working_file[[#All],[MRP]]),Nikes_Sales_Dataset___Working_file[[#This Row],[MRP]]) -> 3285.52 | M17: =IF(ISBLANK(Nikes_Sales_Dataset___Working_file[[#This Row],[Discount_Applied]]),0,Nikes_Sales_Dataset___Working_file[[#This Row],[Discount_Applied]]) -> 0 | N17: =Nikes_Sales_Dataset___Working_file[[#This Row],[MRP Final]]*(1-Nikes_Sales_Dataset___Working_file[[#This Row],[Cleaned Discount]]) -> 3285.52 | O17: 0 | P17: =Nikes_Sales_Dataset___Working_file[[#This Row],[Sales Price]]*Nikes_Sales_Dataset___Working_file[[#This Row],[Units Sold Filled]] -> 3285.52 | Q17: 45808 | R17: =IF(ISBLANK(Nikes_Sales_Dataset___Working_file[[#This Row],[Order_Date]]),"Unknown Date",Nikes_Sales_Dataset___Working_file[[#This Row],[Order_Date]]) -> 45808 | S17: =IF(ISNUMBER(Nikes_Sales_Dataset___Working_file[[#This Row],[Cleaned Order Date]]),TEXT(Nikes_Sales_Dataset___Working_file[[#This Row],[Cleaned Order Date]],"mmm"),"Unknown") -> May | T17: =IF(ISNUMBER(Nikes_Sales_Dataset___Working_file[[#This Row],[Cleaned Order Date]]),TEXT(Nikes_Sales_Dataset___Working_file[[#This Row],[Cleaned Order Date]],"yyyy"),"Unknown") -> 2025 | U17: Retail | V17: Kolkata | W17: Kolkata | X17: 1193.21
A18: 2016 | B18: =Nikes_Sales_Dataset___Working_file[[#This Row],[Order_ID]]&"_"&TEXT(Nikes_Sales_Dataset___Working_file[[#This Row],[Cleaned Order Date]],"yyyymmdd") -> 2016_Unknown Date | C18: Women | D18: Basketball | E18: Air Jordan | F18: M | G18: M | H18: 1 | I18: =IF(ISBLANK(Nikes_Sales_Dataset___Working_file[[#This Row],[Units_Sold]]),IF(Nikes_Sales_Dataset___Working_file[[#This Row],[Profit]]<0,0,1),Nikes_Sales_Dataset___Working_file[[#This Row],[Units_Sold]]) -> 1 | J18: 9871.75 | K18: =IF(ISBLANK(Nikes_Sales_Dataset___Working_file[[#This Row],[MRP]]),MEDIAN(Nikes_Sales_Dataset___Working_file[[#All],[MRP]]),Nikes_Sales_Dataset___Working_file[[#This Row],[MRP]]) -> 9871.75 | L18: 0.3 | M18: =IF(ISBLANK(Nikes_Sales_Dataset___Working_file[[#This Row],[Discount_Applied]]),0,Nikes_Sales_Dataset___Working_file[[#This Row],[Discount_Applied]]) -> 0.3 | N18: =Nikes_Sales_Dataset___Working_file[[#This Row],[MRP Final]]*(1-Nikes_Sales_Dataset___Working_file[[#This Row],[Cleaned Discount]]) -> 6910.225 | O18: 6910.22 | P18: =Nikes_Sales_Dataset___Working_file[[#This Row],[Sales Price]]*Nikes_Sales_Dataset___Working_file[[#This Row],[Units Sold Filled]] -> 6910.225 | R18: =IF(ISBLANK(Nikes_Sales_Dataset___Working_file[[#This Row],[Order_Date]]),"Unknown Date",Nikes_Sales_Dataset___Working_file[[#This Row],[Order_Date]]) -> Unknown Date | S18: =IF(ISNUMBER(Nikes_Sales_Dataset___Working_file[[#This Row],[Cleaned Order Date]]),TEXT(Nikes_Sales_Dataset___Working_file[[#This Row],[Cleaned Order Date]],"mmm"),"Unknown") -> Unknown | T18: =IF(ISNUMBER(Nikes_Sales_Dataset___Working_file[[#This Row],[Cleaned Order Date]]),TEXT(Nikes_Sales_Dataset___Working_file[[#This Row],[Cleaned Order Date]],"yyyy"),"Unknown") -> Unknown | U18: Retail | V18: hyderbad | W18: Hyderabad | X18: 2452.69
A19: 2017 | B19: =Nikes_Sales_Dataset___Working_file[[#This Row],[Order_ID]]&"_"&TEXT(Nikes_Sales_Dataset___Working_file[[#This Row],[Cleaned Order Date]],"yyyymmdd") -> 2017_20250317 | C19: Women | D19: Basketball | E19: Air Jordan | F19: 9 | G19: M | H19: 4 | I19: =IF(ISBLANK(Nikes_Sales_Dataset___Working_file[[#This Row],[Units_Sold]]),IF(Nikes_Sales_Dataset___Working_file[[#This Row],[Profit]]<0,0,1),Nikes_Sales_Dataset___Working_file[[#This Row],[Units_Sold]]) -> 4 | K19: =IF(ISBLANK(Nikes_Sales_Dataset___Working_file[[#This Row],[MRP]]),MEDIAN(Nikes_Sales_Dataset___Working_file[[#All],[MRP]]),Nikes_Sales_Dataset___Working_file[[#This Row],[MRP]]) -> 6110.03 | M19: =IF(ISBLANK(Nikes_Sales_Dataset___Working_file[[#This Row],[Discount_Applied]]),0,Nikes_Sales_Dataset___Working_file[[#This Row],[Discount_Applied]]) -> 0 | N19: =Nikes_Sales_Dataset___Working_file[[#This Row],[MRP Final]]*(1-Nikes_Sales_Dataset___Working_file[[#This Row],[Cleaned Discount]]) -> 6110.03 | O19: 0 | P19: =Nikes_Sales_Dataset___Working_file[[#This Row],[Sales Price]]*Nikes_Sales_Dataset___Working_file[[#This Row],[Units Sold Filled]] -> 24440.12 | Q19: 45733 | R19: =IF(ISBLANK(Nikes_Sales_Dataset___Working_file[[#This Row],[Order_Date]]),"Unknown Date",Nikes_Sales_Dataset___Working_file[[#This Row],[Order_Date]]) -> 45733 | S19: =IF(ISNUMBER(Nikes_Sales_Dataset___Working_file[[#This Row],[Cleaned Order Date]]),TEXT(Nikes_Sales_Dataset___Working_file[[#This Row],[Cleaned Order Date]],"mmm"),"Unknown") -> Mar | T19: =IF(ISNUMBER(Nikes_Sales_Dataset___Working_file[[#This Row],[Cleaned Order Date]]),TEXT(Nikes_Sales_Dataset___Working_file[[#This Row],[Cleaned Order Date]],"yyyy"),"Unknown") -> 2025 | U19: Retail | V19: Delhi | W19: Delhi | X19: 1946.24
A20: 2018 | B20: =Nikes_Sales_Dataset___Working_file[[#This Row],[Order_ID]]&"_"&TEXT(Nikes_Sales_Dataset___Working_file[[#This Row],[Cleaned Order Date]],"yyyymmdd") -> 2018_Unknown Date | C20: Men | D20: Training | E20: Metcon 7 | F20: XL | G20: XL | H20: 0 | I20: =IF(ISBLANK(Nikes_Sales_Dataset___Working_file[[#This Row],[Units_Sold]]),IF(Nikes_Sales_Dataset___Working_file[[#This Row],[Profit]]<0,0,1),Nikes_Sales_Dataset___Working_file[[#This Row],[Units_Sold]]) -> 0 | K20: =IF(ISBLANK(Nikes_Sales_Dataset___Working_file[[#This Row],[MRP]]),MEDIAN(Nikes_Sales_Dataset___Working_file[[#All],[MRP]]),Nikes_Sales_Dataset___Working_file[[#This Row],[MRP]]) -> 6110.03 | L20: 1.17 | M20: =IF(ISBLANK(Nikes_Sales_Dataset___Working_file[[#This Row],[Discount_Applied]]),0,Nikes_Sales_Dataset___Working_file[[#This Row],[Discount_Applied]]) -> 1.17 | N20: =Nikes_Sales_Dataset___Working_file[[#This Row],[MRP Final]]*(1-Nikes_Sales_Dataset___Working_file[[#This Row],[Cleaned Discount]]) -> -1038.7051 | O20: 0 | P20: =Nikes_Sales_Dataset___Working_file[[#This Row],[Sales Price]]*Nikes_Sales_Dataset___Working_file[[#This Row],[Units Sold Filled]] -> 0 | R20: =IF(ISBLANK(Nikes_Sales_Dataset___Working_file[[#This Row],[Order_Date]]),"Unknown Date",Nikes_Sales_Dataset___Working_file[[#This Row],[Order_Date]]) -> Unknown Date | S20: =IF(ISNUMBER(Nikes_Sales_Dataset___Working_file[[#This Row],[Cleaned Order Date]]),TEXT(Nikes_Sales_Dataset___Working_file[[#This Row],[Cleaned Order Date]],"mmm"),"Unknown") -> Unknown | T20: =IF(ISNUMBER(Nikes_Sales_Dataset___Working_file[[#This Row],[Cleaned Order Date]]),TEXT(Nikes_Sales_Dataset___Working_file[[#This Row],[Cleaned Order Date]],"yyyy"),"Unknown") -> Unknown | U20: Online | V20: bengaluru | W20: Bangalore | X20: -966.89
A21: 2019 | B21: =Nikes_Sales_Dataset___Working_file[[#This Row],[Order_ID]]&"_"&TEXT(Nikes_Sales_Dataset___Working_file[[#This Row],[Cleaned Order Date]],"yyyymmdd") -> 2019_20250117 | C21: Kids | D21: Running | E21: Air Zoom | F21: 6 | G21: M | H21: 0 | I21: =IF(ISBLANK(Nikes_Sales_Dataset___Working_file[[#This Row],[Units_Sold]]),IF(Nikes_Sales_Dataset___Working_file[[#This Row],[Profit]]<0,0,1),Nikes_Sales_Dataset___Working_file[[#This Row],[Units_Sold]]) -> 0 | J21: 3424.06 | K21: =IF(ISBLANK(Nikes_Sales_Dataset___Working_file[[#This Row],[MRP]]),MEDIAN(Nikes_Sales_Dataset___Working_file[[#All],[MRP]]),Nikes_Sales_Dataset___Working_file[[#This Row],[MRP]]) -> 3424.06 | L21: 0.32 | M21: =IF(ISBLANK(Nikes_Sales_Dataset___Working_file[[#This Row],[Discount_Applied]]),0,Nikes_Sales_Dataset___Working_file[[#This Row],[Discount_Applied]]) -> 0.32 | N21: =Nikes_Sales_Dataset___Working_file[[#This Row],[MRP Final]]*(1-Nikes_Sales_Dataset___Working_file[[#This Row],[Cleaned Discount]]) -> 2328.3608 | O21: 0 | P21: =Nikes_Sales_Dataset___Working_file[[#This Row],[Sales Price]]*Nikes_Sales_Dataset___Working_file[[#This Row],[Units Sold Filled]] -> 0 | Q21: 45674 | R21: =IF(ISBLANK(Nikes_Sales_Dataset___Working_file[[#This Row],[Order_Date]]),"Unknown Date",Nikes_Sales_Dataset___Working_file[[#This Row],[Order_Date]]) -> 45674 | S21: =IF(ISNUMBER(Nikes_Sales_Dataset___Working_file[[#This Row],[Cleaned Order Date]]),TEXT(Nikes_Sales_Dataset___Working_file[[#This Row],[Cleaned Order Date]],"mmm"),"Unknown") -> Jan | T21: =IF(ISNUMBER(Nikes_Sales_Dataset___Working_file[[#This Row],[Cleaned Order Date]]),TEXT(Nikes_Sales_Dataset___Working_file[[#This Row],[Cleaned Order Date]],"yyyy"),"Unknown") -> 2025 | U21: Online | V21: Hyderabad | W21: Hyderabad | X21: 1915.24
A22: 2020 | B22: =Nikes_Sales_Dataset___Working_file[[#This Row],[Order_ID]]&"_"&TEXT(Nikes_Sales_Dataset___Working_file[[#This Row],[Cleaned Order Date]],"yyyymmdd") -> 2020_20250328 | C22: Kids | D22: Soccer | E22: Tiempo Legend | F22: L | G22: L | H22: -1 | I22: =IF(ISBLANK(Nikes_Sales_Dataset___Working_file[[#This Row],[Units_Sold]]),IF(Nikes_Sales_Dataset___Working_file[[#This Row],[Profit]]<0,0,1),Nikes_Sales_Dataset___Working_file[[#This Row],[Units_Sold]]) -> -1 | K22: =IF(ISBLANK(Nikes_Sales_Dataset___Working_file[[#This Row],[MRP]]),MEDIAN(Nikes_Sales_Dataset___Working_file[[#All],[MRP]]),Nikes_Sales_Dataset___Working_file[[#This Row],[MRP]]) -> 6110.03 | L22: 0.67 | M22: =IF(ISBLANK(Nikes_Sales_Dataset___Working_file[[#This Row],[Discount_Applied]]),0,Nikes_Sales_Dataset___Working_file[[#This Row],[Discount_Applied]]) -> 0.67 | N22: =Nikes_Sales_Dataset___Working_file[[#This Row],[MRP Final]]*(1-Nikes_Sales_Dataset___Working_file[[#This Row],[Cleaned Discount]]) -> 2016.3099 | O22: 0 | P22: =Nikes_Sales_Dataset___Working_file[[#This Row],[Sales Price]]*Nikes_Sales_Dataset___Working_file[[#This Row],[Units Sold Filled]] -> -2016.3099 | Q22: 45744 | R22: =IF(ISBLANK(Nikes_Sales_Dataset___Working_file[[#This Row],[Order_Date]]),"Unknown Date",Nikes_Sales_Dataset___Working_file[[#This Row],[Order_Date]]) -> 45744 | S22: =IF(ISNUMBER(Nikes_Sales_Dataset___Working_file[[#This Row],[Cleaned Order Date]]),TEXT(Nikes_Sales_Dataset___Working_file[[#This Row],[Cleaned Order Date]],"mmm"),"Unknown") -> Mar | T22: =IF(ISNUMBER(Nikes_Sales_Dataset___Working_file[[#This Row],[Cleaned Order Date]]),TEXT(Nikes_Sales_Dataset___Working_file[[#This Row],[Cleaned Order Date]],"yyyy"),"Unknown") -> 2025 | U22: Retail | V22: Mumbai | W22: Mumbai | X22: 439.96
A23: 2021 | B23: =Nikes_Sales_Dataset___Working_file[[#This Row],[Order_ID]]&"_"&TEXT(Nikes_Sales_Dataset___Working_file[[#This Row],[Cleaned Order Date]],"yyyymmdd") -> 2021_20241119 | C23: Men | D23: Running | E23: Free RN | F23: L | G23: L | H23: -1 | I23: =IF(ISBLANK(Nikes_Sales_Dataset___Working_file[[#This Row],[Units_Sold]]),IF(Nikes_Sales_Dataset___Working_file[[#This Row],[Profit]]<0,0,1),Nikes_Sales_Dataset___Working_file[[#This Row],[Units_Sold]]) -> -1 | J23: 7086.7 | K23: =IF(ISBLANK(Nikes_Sales_Dataset___Working_file[[#This Row],[MRP]]),MEDIAN(Nikes_Sales_Dataset___Working_file[[#All],[MRP]]),Nikes_Sales_Dataset___Working_file[[#This Row],[MRP]]) -> 7086.7 | L23: 0.66 | M23: =IF(ISBLANK(Nikes_Sales_Dataset___Working_file[[#This Row],[Discount_Applied]]),0,Nikes_Sales_Dataset___Working_file[[#This Row],[Discount_Applied]]) -> 0.66 | N23: =Nikes_Sales_Dataset___Working_file[[#This Row],[MRP Final]]*(1-Nikes_Sales_Dataset___Working_file[[#This Row],[Cleaned Discount]]) -> 2409.478 | O23: -2409.48 | P23: =Nikes_Sales_Dataset___Working_file[[#This Row],[Sales Price]]*Nikes_Sales_Dataset___Working_file[[#This Row],[Units Sold Filled]] -> -2409.478 | Q23: 45615 | R23: =IF(ISBLANK(Nikes_Sales_Dataset___Working_file[[#This Row],[Order_Date]]),"Unknown Date",Nikes_Sales_Dataset___Working_file[[#This Row],[Order_Date]]) -> 45615 | S23: =IF(ISNUMBER(Nikes_Sales_Dataset___Working_file[[#This Row],[Cleaned Order Date]]),TEXT(Nikes_Sales_Dataset___Working_file[[#This Row],[Cleaned Order Date]],"mmm"),"Unknown") -> Nov | T23: =IF(ISNUMBER(Nikes_Sales_Dataset___Working_file[[#This Row],[Cleaned Order Date]]),TEXT(Nikes_Sales_Dataset___Working_file[[#This Row],[Cleaned Order Date]],"yyyy"),"Unknown") -> 2024 | U23: Retail | V23: Hyd | W23: Hyderabad | X23: -1120.49
A24: 2022 | B24: =Nikes_Sales_Dataset___Working_file[[#This Row],[Order_ID]]&"_"&TEXT(Nikes_Sales_Dataset___Working_file[[#This Row],[Cleaned Order Date]],"yyyymmdd") -> 2022_20240924 | C24: Women | D24: Soccer | E24: Premier III | F24: M | G24: M | I24: =IF(ISBLANK(Nikes_Sales_Dataset___Working_file[[#This Row],[Units_Sold]]),IF(Nikes_Sales_Dataset___Working_file[[#This Row],[Profit]]<0,0,1),Nikes_Sales_Dataset___Working_file[[#This Row],[Units_Sold]]) -> 1 | K24: =IF(ISBLANK(Nikes_Sales_Dataset___Working_file[[#This Row],[MRP]]),MEDIAN(Nikes_Sales_Dataset___Working_file[[#All],[MRP]]),Nikes_Sales_Dataset___Working_file[[#This Row],[MRP]]) -> 6110.03 | M24: =IF(ISBLANK(Nikes_Sales_Dataset___Working_file[[#This Row],[Discount_Applied]]),0,Nikes_Sales_Dataset___Working_file[[#This Row],[Discount_Applied]]) -> 0 | N24: =Nikes_Sales_Dataset___Working_file[[#This Row],[MRP Final]]*(1-Nikes_Sales_Dataset___Working_file[[#This Row],[Cleaned Discount]]) -> 6110.03 | O24: 0 | P24: =Nikes_Sales_Dataset___Working_file[[#This Row],[Sales Price]]*Nikes_Sales_Dataset___Working_file[[#This Row],[Units Sold Filled]] -> 6110.03 | Q24: 45559 | R24: =IF(ISBLANK(Nikes_Sales_Dataset___Working_file[[#This Row],[Order_Date]]),"Unknown Date",Nikes_Sales_Dataset___Working_file[[#This Row],[Order_Date]]) -> 45559 | S24: =IF(ISNUMBER(Nikes_Sales_Dataset___Working_file[[#This Row],[Cleaned Order Date]]),TEXT(Nikes_Sales_Dataset___Working_file[[#This Row],[Cleaned Order Date]],"mmm"),"Unknown") -> Sep | T24: =IF(ISNUMBER(Nikes_Sales_Dataset___Working_file[[#This Row],[Cleaned Order Date]]),TEXT(Nikes_Sales_Dataset___Working_file[[#This Row],[Cleaned Order Date]],"yyyy"),"Unknown") -> 2024 | U24: Online | V24: Pune | W24: Pune | X24: 3427.16
A25: 2023 | B25: =Nikes_Sales_Dataset___Working_file[[#This Row],[Order_ID]]&"_"&TEXT(Nikes_Sales_Dataset___Working_file[[#This Row],[Cleaned Order Date]],"yyyymmdd") -> 2023_20250110 | C25: Men | D25: Lifestyle | E25: Waffle One | F25: M | G25: M | I25: =IF(ISBLANK(Nikes_Sales_Dataset___Working_file[[#This Row],[Units_Sold]]),IF(Nikes_Sales_Dataset___Working_file[[#This Row],[Profit]]<0,0,1),Nikes_Sales_Dataset___Working_file[[#This Row],[Units_Sold]]) -> 1 | J25: 5003.95 | K25: =IF(ISBLANK(Nikes_Sales_Dataset___Working_file[[#This Row],[MRP]]),MEDIAN(Nikes_Sales_Dataset___Working_file[[#All],[MRP]]),Nikes_Sales_Dataset___Working_file[[#This Row],[MRP]]) -> 5003.95 | M25: =IF(ISBLANK(Nikes_Sales_Dataset___Working_file[[#This Row],[Discount_Applied]]),0,Nikes_Sales_Dataset___Working_file[[#This Row],[Discount_Applied]]) -> 0 | N25: =Nikes_Sales_Dataset___Working_file[[#This Row],[MRP Final]]*(1-Nikes_Sales_Dataset___Working_file[[#This Row],[Cleaned Discount]]) -> 5003.95 | O25: 0 | P25: =Nikes_Sales_Dataset___Working_file[[#This Row],[Sales Price]]*Nikes_Sales_Dataset___Working_file[[#This Row],[Units Sold Filled]] -> 5003.95 | Q25: 45667 | R25: =IF(ISBLANK(Nikes_Sales_Dataset___Working_file[[#This Row],[Order_Date]]),"Unknown Date",Nikes_Sales_Dataset___Working_file[[#This Row],[Order_Date]]) -> 45667 | S25: =IF(ISNUMBER(Nikes_Sales_Dataset___Working_file[[#This Row],[Cleaned Order Date]]),TEXT(Nikes_Sales_Dataset___Working_file[[#This Row],[Cleaned Order Date]],"mmm"),"Unknown") -> Jan | T25: =IF(ISNUMBER(Nikes_Sales_Dataset___Working_file[[#This Row],[Cleaned Order Date]]),TEXT(Nikes_Sales_Dataset___Working_file[[#This Row],[Cleaned Order Date]],"yyyy"),"Unknown") -> 2025 | U25: Online | V25: Mumbai | W25: Mumbai | X25: 1498.37
A26: 2024 | B26: =Nikes_Sales_Dataset___Working_file[[#This Row],[Order_ID]]&"_"&TEXT(Nikes_Sales_Dataset___Working_file[[#This Row],[Cleaned Order Date]],"yyyymmdd") -> 2024_20241228 | C26: Kids | D26: Training | E26: SuperRep Go | F26: XL | G26: XL | H26: 0 | I26: =IF(ISBLANK(Nikes_Sales_Dataset___Working_file[[#This Row],[Units_Sold]]),IF(Nikes_Sales_Dataset___Working_file[[#This Row],[Profit]]<0,0,1),Nikes_Sales_Dataset___Working_file[[#This Row],[Units_Sold]]) -> 0 | K26: =IF(ISBLANK(Nikes_Sales_Dataset___Working_file[[#This Row],[MRP]]),MEDIAN(Nikes_Sales_Dataset___Working_file[[#All],[MRP]]),Nikes_Sales_Dataset___Working_file[[#This Row],[MRP]]) -> 6110.03 | L26: 0.5 | M26: =IF(ISBLANK(Nikes_Sales_Dataset___Working_file[[#This Row],[Discount_Applied]]),0,Nikes_Sales_Dataset___Working_file[[#This Row],[Discount_Applied]]) -> 0.5 | N26: =Nikes_Sales_Dataset___Working_file[[#This Row],[MRP Final]]*(1-Nikes_Sales_Dataset___Working_file[[#This Row],[Cleaned Discount]]) -> 3055.015 | O26: 0 | P26: =Nikes_Sales_Dataset___Working_file[[#This Row],[Sales Price]]*Nikes_Sales_Dataset___Working_file[[#This Row],[Units Sold Filled]] -> 0 | Q26: 45654 | R26: =IF(ISBLANK(Nikes_Sales_Dataset___Working_file[[#This Row],[Order_Date]]),"Unknown Date",Nikes_Sales_Dataset___Working_file[[#This Row],[Order_Date]]) -> 45654 | S26: =IF(ISNUMBER(Nikes_Sales_Dataset___Working_file[[#This Row],[Cleaned Order Date]]),TEXT(Nikes_Sales_Dataset___Working_file[[#This Row],[Cleaned Order Date]],"mmm"),"Unknown") -> Dec | T26: =IF(ISNUMBER(Nikes_Sales_Dataset___Working_file[[#This Row],[Cleaned Order Date]]),TEXT(Nikes_Sales_Dataset___Working_file[[#This Row],[Cleaned Order Date]],"yyyy"),"Unknown") -> 2024 | U26: Retail | V26: Bangalore | W26: Bangalore | X26: 1842.35
A27: 2025 | B27: =Nikes_Sales_Dataset___Working_file[[#This Row],[Order_ID]]&"_"&TEXT(Nikes_Sales_Dataset___Working_file[[#This Row],[Cleaned Order Date]],"yyyymmdd") -> 2025_Unknown Date | C27: Women | D27: Basketball | E27: Kyrie Flytrap | F27: M | G27: M | H27: 3 | I27: =IF(ISBLANK(Nikes_Sales_Dataset___Working_file[[#This Row],[Units_Sold]]),IF(Nikes_Sales_Dataset___Working_file[[#This Row],[Profit]]<0,0,1),Nikes_Sales_Dataset___Working_file[[#This Row],[Units_Sold]]) -> 3 | J27: 9820.5 | K27: =IF(ISBLANK(Nikes_Sales_Dataset___Working_file[[#This Row],[MRP]]),MEDIAN(Nikes_Sales_Dataset___Working_file[[#All],[MRP]]),Nikes_Sales_Dataset___Working_file[[#This Row],[MRP]]) -> 9820.5 | M27: =IF(ISBLANK(Nikes_Sales_Dataset___Working_file[[#This Row],[Discount_Applied]]),0,Nikes_Sales_Dataset___Working_file[[#This Row],[Discount_Applied]]) -> 0 | N27: =Nikes_Sales_Dataset___Working_file[[#This Row],[MRP Final]]*(1-Nikes_Sales_Dataset___Working_file[[#This Row],[Cleaned Discount]]) -> 9820.5 | O27: 0 | P27: =Nikes_Sales_Dataset___Working_file[[#This Row],[Sales Price]]*Nikes_Sales_Dataset___Working_file[[#This Row],[Units Sold Filled]] -> 29461.5 | R27: =IF(ISBLANK(Nikes_Sales_Dataset___Working_file[[#This Row],[Order_Date]]),"Unknown Date",Nikes_Sales_Dataset___Working_file[[#This Row],[Order_Date]]) -> Unknown Date | S27: =IF(ISNUMBER(Nikes_Sales_Dataset___Working_file[[#This Row],[Cleaned Order Date]]),TEXT(Nikes_Sales_Dataset___Working_file[[#This Row],[Cleaned Order Date]],"mmm"),"Unknown") -> Unknown | T27: =IF(ISNUMBER(Nikes_Sales_Dataset___Working_file[[#This Row],[Cleaned Order Date]]),TEXT(Nikes_Sales_Dataset___Working_file[[#This Row],[Cleaned Order Date]],"yyyy"),"Unknown") -> Unknown | U27: Retail | V27: Mumbai | W27: Mumbai | X27: 1900.15
A28: 2026 | B28: =Nikes_Sales_Dataset___Working_file[[#This Row],[Order_ID]]&"_"&TEXT(Nikes_Sales_Dataset___Working_file[[#This Row],[Cleaned Order Date]],"yyyymmdd") -> 2026_20240810 | C28: Kids | D28: Lifestyle | E28: Blazer Mid | F28: XL | G28: XL | H28: 1 | I28: =IF(ISBLANK(Nikes_Sales_Dataset___Working_file[[#This Row],[Units_Sold]]),IF(Nikes_Sales_Dataset___Working_file[[#This Row],[Profit]]<0,0,1),Nikes_Sales_Dataset___Working_file[[#This Row],[Units_Sold]]) -> 1 | K28: =IF(ISBLANK(Nikes_Sales_Dataset___Working_file[[#This Row],[MRP]]),MEDIAN(Nikes_Sales_Dataset___Working_file[[#All],[MRP]]),Nikes_Sales_Dataset___Working_file[[#This Row],[MRP]]) -> 6110.03 | L28: 0.16 | M28: =IF(ISBLANK(Nikes_Sales_Dataset___Working_file[[#This Row],[Discount_Applied]]),0,Nikes_Sales_Dataset___Working_file[[#This Row],[Discount_Applied]]) -> 0.16 | N28: =Nikes_Sales_Dataset___Working_file[[#This Row],[MRP Final]]*(1-Nikes_Sales_Dataset___Working_file[[#This Row],[Cleaned Discount]]) -> 5132.4252 | O28: 0 | P28: =Nikes_Sales_Dataset___Working_file[[#This Row],[Sales Price]]*Nikes_Sales_Dataset___Working_file[[#This Row],[Units Sold Filled]] -> 5132.4252 | Q28: 45514 | R28: =IF(ISBLANK(Nikes_Sales_Dataset___Working_file[[#This Row],[Order_Date]]),"Unknown Date",Nikes_Sales_Dataset___Working_file[[#This Row],[Order_Date]]) -> 45514 | S28: =IF(ISNUMBER(Nikes_Sales_Dataset___Working_file[[#This Row],[Cleaned Order Date]]),TEXT(Nikes_Sales_Dataset___Working_file[[#This Row],[Cleaned Order Date]],"mmm"),"Unknown") -> Aug | T28: =IF(ISNUMBER(Nikes_Sales_Dataset___Working_file[[#This Row],[Cleaned Order Date]]),TEXT(Nikes_Sales_Dataset___Working_file[[#This Row],[Cleaned Order Date]],"yyyy"),"Unknown") -> 2024 | U28: Retail | V28: Kolkata | W28: Kolkata | X28: 2301.64
A29: 2027 | B29: =Nikes_Sales_Dataset___Working_file[[#This Row],[Order_ID]]&"_"&TEXT(Nikes_Sales_Dataset___Working_file[[#This Row],[Cleaned Order Date]],"yyyymmdd") -> 2027_Unknown Date | C29: Men | D29: Basketball | E29: Zoom Freak | F29: XL | G29: XL | I29: =IF(ISBLANK(Nikes_Sales_Dataset___Working_file[[#This Row],[Units_Sold]]),IF(Nikes_Sales_Dataset___Working_file[[#This Row],[Profit]]<0,0,1),Nikes_Sales_Dataset___Working_file[[#This Row],[Units_Sold]]) -> 0 | K29: =IF(ISBLANK(Nikes_Sales_Dataset___Working_file[[#This Row],[MRP]]),MEDIAN(Nikes_Sales_Dataset___Working_file[[#All],[MRP]]),Nikes_Sales_Dataset___Working_file[[#This Row],[MRP]]) -> 6110.03 | L29: 0.22 | M29: =IF(ISBLANK(Nikes_Sales_Dataset___Working_file[[#This Row],[Discount_Applied]]),0,Nikes_Sales_Dataset___Working_file[[#This Row],[Discount_Applied]]) -> 0.22 | N29: =Nikes_Sales_Dataset___Working_file[[#This Row],[MRP Final]]*(1-Nikes_Sales_Dataset___Working_file[[#This Row],[Cleaned Discount]]) -> 4765.8234 | O29: 0 | P29: =Nikes_Sales_Dataset___Working_file[[#This Row],[Sales Price]]*Nikes_Sales_Dataset___Working_file[[#This Row],[Units Sold Filled]] -> 0 | R29: =IF(ISBLANK(Nikes_Sales_Dataset___Working_file[[#This Row],[Order_Date]]),"Unknown Date",Nikes_Sales_Dataset___Working_file[[#This Row],[Order_Date]]) -> Unknown Date | S29: =IF(ISNUMBER(Nikes_Sales_Dataset___Working_file[[#This Row],[Cleaned Order Date]]),TEXT(Nikes_Sales_Dataset___Working_file[[#This Row],[Cleaned Order Date]],"mmm"),"Unknown") -> Unknown | T29: =IF(ISNUMBER(Nikes_Sales_Dataset___Working_file[[#This Row],[Cleaned Order Date]]),TEXT(Nikes_Sales_Dataset___Working_file[[#This Row],[Cleaned Order Date]],"yyyy"),"Unknown") -> Unknown | U29: Online | V29: Pune | W29: Pune | X29: -138.74
A30: 2028 | B30: =Nikes_Sales_Dataset___Working_file[[#This Row],[Order_ID]]&"_"&TEXT(Nikes_Sales_Dataset___Working_file[[#This Row],[Cleaned Order Date]],"yyyymmdd") -> 2028_Unknown Date | C30: Men | D30: Training | E30: Flex Trainer | F30: 12 | G30: XL | I30: =IF(ISBLANK(Nikes_Sales_Dataset___Working_file[[#This Row],[Units_Sold]]),IF(Nikes_Sales_Dataset___Working_file[[#This Row],[Profit]]<0,0,1),Nikes_Sales_Dataset___Working_file[[#This Row],[Units_Sold]]) -> 0 | J30: 3270.23 | K30: =IF(ISBLANK(Nikes_Sales_Dataset___Working_file[[#This Row],[MRP]]),MEDIAN(Nikes_Sales_Dataset___Working_file[[#All],[MRP]]),Nikes_Sales_Dataset___Working_file[[#This Row],[MRP]]) -> 3270.23 | M30: =IF(ISBLANK(Nikes_Sales_Dataset___Working_file[[#This Row],[Discount_Applied]]),0,Nikes_Sales_Dataset___Working_file[[#This Row],[Discount_Applied]]) -> 0 | N30: =Nikes_Sales_Dataset___Working_file[[#This Row],[MRP Final]]*(1-Nikes_Sales_Dataset___Working_file[[#This Row],[Cleaned Discount]]) -> 3270.23 | O30: 0 | P30: =Nikes_Sales_Dataset___Working_file[[#This Row],[Sales Price]]*Nikes_Sales_Dataset___Working_file[[#This Row],[Units Sold Filled]] -> 0 | R30: =IF(ISBLANK(Nikes_Sales_Dataset___Working_file[[#This Row],[Order_Date]]),"Unknown Date",Nikes_Sales_Dataset___Working_file[[#This Row],[Order_Date]]) -> Unknown Date | S30: =IF(ISNUMBER(Nikes_Sales_Dataset___Working_file[[#This Row],[Cleaned Order Date]]),TEXT(Nikes_Sales_Dataset___Working_file[[#This Row],[Cleaned Order Date]],"mmm"),"Unknown") -> Unknown | T30: =IF(ISNUMBER(Nikes_Sales_Dataset___Working_file[[#This Row],[Cleaned Order Date]]),TEXT(Nikes_Sales_Dataset___Working_file[[#This Row],[Cleaned Order Date]],"yyyy"),"Unknown") -> Unknown | U30: Retail | V30: Delhi | W30: Delhi | X30: -946.86
A31: 2029 | B31: =Nikes_Sales_Dataset___Working_file[[#This Row],[Order_ID]]&"_"&TEXT(Nikes_Sales_Dataset___Working_file[[#This Row],[Cleaned Order Date]],"yyyymmdd") -> 2029_20231028 | C31: Men | D31: Training | E31: ZoomX Invincible | F31: 12 | G31: XL | H31: 0 | I31: =IF(ISBLANK(Nikes_Sales_Dataset___Working_file[[#This Row],[Units_Sold]]),IF(Nikes_Sales_Dataset___Working_file[[#This Row],[Profit]]<0,0,1),Nikes_Sales_Dataset___Working_file[[#This Row],[Units_Sold]]) -> 0 | K31: =IF(ISBLANK(Nikes_Sales_Dataset___Working_file[[#This Row],[MRP]]),MEDIAN(Nikes_Sales_Dataset___Working_file[[#All],[MRP]]),Nikes_Sales_Dataset___Working_file[[#This Row],[MRP]]) -> 6110.03 | M31: =IF(ISBLANK(Nikes_Sales_Dataset___Working_file[[#This Row],[Discount_Applied]]),0,Nikes_Sales_Dataset___Working_file[[#This Row],[Discount_Applied]]) -> 0 | N31: =Nikes_Sales_Dataset___Working_file[[#This Row],[MRP Final]]*(1-Nikes_Sales_Dataset___Working_file[[#This Row],[Cleaned Discount]]) -> 6110.03 | O31: 0 | P31: =Nikes_Sales_Dataset___Working_file[[#This Row],[Sales Price]]*Nikes_Sales_Dataset___Working_file[[#This Row],[Units Sold Filled]] -> 0 | Q31: 45227 | R31: =IF(ISBLANK(Nikes_Sales_Dataset___Working_file[[#This Row],[Order_Date]]),"Unknown Date",Nikes_Sales_Dataset___Working_file[[#This Row],[Order_Date]]) -> 45227 | S31: =IF(ISNUMBER(Nikes_Sales_Dataset___Working_file[[#This Row],[Cleaned Order Date]]),TEXT(Nikes_Sales_Dataset___Working_file[[#This Row],[Cleaned Order Date]],"mmm"),"Unknown") -> Oct | T31: =IF(ISNUMBER(Nikes_Sales_Dataset___Working_file[[#This Row],[Cleaned Order Date]]),TEXT(Nikes_Sales_Dataset___Working_file[[#This Row],[Cleaned Order Date]],"yyyy"),"Unknown") -> 2023 | U31: Online | V31: Bangalore | W31: Bangalore | X31: -185.67
A32: 2030 | B32: =Nikes_Sales_Dataset___Working_file[[#This Row],[Order_ID]]&"_"&TEXT(Nikes_Sales_Dataset___Working_file[[#This Row],[Cleaned Order Date]],"yyyymmdd") -> 2030_20250714 | C32: Men | D32: Soccer | E32: Phantom GT | F32: XL | G32: XL | I32: =IF(ISBLANK(Nikes_Sales_Dataset___Working_file[[#This Row],[Units_Sold]]),IF(Nikes_Sales_Dataset___Working_file[[#This Row],[Profit]]<0,0,1),Nikes_Sales_Dataset___Working_file[[#This Row],[Units_Sold]]) -> 0 | K32: =IF(ISBLANK(Nikes_Sales_Dataset___Working_file[[#This Row],[MRP]]),MEDIAN(Nikes_Sales_Dataset___Working_file[[#All],[MRP]]),Nikes_Sales_Dataset___Working_file[[#This Row],[MRP]]) -> 6110.03 | L32: 1.05 | M32: =IF(ISBLANK(Nikes_Sales_Dataset___Working_file[[#This Row],[Discount_Applied]]),0,Nikes_Sales_Dataset___Working_file[[#This Row],[Discount_Applied]]) -> 1.05 | N32: =Nikes_Sales_Dataset___Working_file[[#This Row],[MRP Final]]*(1-Nikes_Sales_Dataset___Working_file[[#This Row],[Cleaned Discount]]) -> -305.5015 | O32: 0 | P32: =Nikes_Sales_Dataset___Working_file[[#This Row],[Sales Price]]*Nikes_Sales_Dataset___Working_file[[#This Row],[Units Sold Filled]] -> 0 | Q32: 45852 | R32: =IF(ISBLANK(Nikes_Sales_Dataset___Working_file[[#This Row],[Order_Date]]),"Unknown Date",Nikes_Sales_Dataset___Working_file[[#This Row],[Order_Date]]) -> 45852 | S32: =IF(ISNUMBER(Nikes_Sales_Dataset___Working_file[[#This Row],[Cleaned Order Date]]),TEXT(Nikes_Sales_Dataset___Working_file[[#This Row],[Cleaned Order Date]],"mmm"),"Unknown") -> Jul | T32: =IF(ISNUMBER(Nikes_Sales_Dataset___Working_file[[#This Row],[Cleaned Order Date]]),TEXT(Nikes_Sales_Dataset___Working_file[[#This Row],[Cleaned Order Date]],"yyyy"),"Unknown") -> 2025 | U32: Retail | V32: Hyd | W32: Hyderabad | X32: -122.93
A33: 2031 | B33: =Nikes_Sales_Dataset___Working_file[[#This Row],[Order_ID]]&"_"&TEXT(Nikes_Sales_Dataset___Working_file[[#This Row],[Cleaned Order Date]],"yyyymmdd") -> 2031_20240509 | C33: Men | D33: Soccer | E33: Premier III | G33: M | H33: 4 | I33: =IF(ISBLANK(Nikes_Sales_Dataset___Working_file[[#This Row],[Units_Sold]]),IF(Nikes_Sales_Dataset___Working_file[[#This Row],[Profit]]<0,0,1),Nikes_Sales_Dataset___Working_file[[#This Row],[Units_Sold]]) -> 4 | J33: 3493.04 | K33: =IF(ISBLANK(Nikes_Sales_Dataset___Working_file[[#This Row],[MRP]]),MEDIAN(Nikes_Sales_Dataset___Working_file[[#All],[MRP]]),Nikes_Sales_Dataset___Working_file[[#This Row],[MRP]]) -> 3493.04 | L33: 0.82 | M33: =IF(ISBLANK(Nikes_Sales_Dataset___Working_file[[#This Row],[Discount_Applied]]),0,Nikes_Sales_Dataset___Working_file[[#This Row],[Discount_Applied]]) -> 0.82 | N33: =Nikes_Sales_Dataset___Working_file[[#This Row],[MRP Final]]*(1-Nikes_Sales_Dataset___Working_file[[#This Row],[Cleaned Discount]]) -> 628.7472 | O33: 2514.99 | P33: =Nikes_Sales_Dataset___Working_file[[#This Row],[Sales Price]]*Nikes_Sales_Dataset___Working_file[[#This Row],[Units Sold Filled]] -> 2514.9888 | Q33: 45421 | R33: =IF(ISBLANK(Nikes_Sales_Dataset___Working_file[[#This Row],[Order_Date]]),"Unknown Date",Nikes_Sales_Dataset___Working_file[[#This Row],[Order_Date]]) -> 45421 | S33: =IF(ISNUMBER(Nikes_Sales_Dataset___Working_file[[#This Row],[Cleaned Order Date]]),TEXT(Nikes_Sales_Dataset___Working_file[[#This Row],[Cleaned Order Date]],"mmm"),"Unknown") -> May | T33: =IF(ISNUMBER(Nikes_Sales_Dataset___Working_file[[#This Row],[Cleaned Order Date]]),TEXT(Nikes_Sales_Dataset___Working_file[[#This Row],[Cleaned Order Date]],"yyyy"),"Unknown") -> 2024 | U33: Online | V33: Delhi | W33: Delhi | X33: 350.7
A34: 2032 | B34: =Nikes_Sales_Dataset___Working_file[[#This Row],[Order_ID]]&"_"&TEXT(Nikes_Sales_Dataset___Working_file[[#This Row],[Cleaned Order Date]],"yyyymmdd") -> 2032_20250411 | C34: Women | D34: Lifestyle | E34: Blazer Mid | F34: XL | G34: XL | H34: 1 | I34: =IF(ISBLANK(Nikes_Sales_Dataset___Working_file[[#This Row],[Units_Sold]]),IF(Nikes_Sales_Dataset___Working_file[[#This Row],[Profit]]<0,0,1),Nikes_Sales_Dataset___Working_file[[#This Row],[Units_Sold]]) -> 1 | K34: =IF(ISBLANK(Nikes_Sales_Dataset___Working_file[[#This Row],[MRP]]),MEDIAN(Nikes_Sales_Dataset___Working_file[[#All],[MRP]]),Nikes_Sales_Dataset___Working_file[[#This Row],[MRP]]) -> 6110.03 | L34: 1.07 | M34: =IF(ISBLANK(Nikes_Sales_Dataset___Working_file[[#This Row],[Discount_Applied]]),0,Nikes_Sales_Dataset___Working_file[[#This Row],[Discount_Applied]]) -> 1.07 | N34: =Nikes_Sales_Dataset___Working_file[[#This Row],[MRP Final]]*(1-Nikes_Sales_Dataset___Working_file[[#This Row],[Cleaned Discount]]) -> -427.7021 | O34: 0 | P34: =Nikes_Sales_Dataset___Working_file[[#This Row],[Sales Price]]*Nikes_Sales_Dataset___Working_file[[#This Row],[Units Sold Filled]] -> -427.7021 | Q34: 45758 | R34: =IF(ISBLANK(Nikes_Sales_Dataset___Working_file[[#This Row],[Order_Date]]),"Unknown Date",Nikes_Sales_Dataset___Working_file[[#This Row],[Order_Date]]) -> 45758 | S34: =IF(ISNUMBER(Nikes_Sales_Dataset___Working_file[[#This Row],[Cleaned Order Date]]),TEXT(Nikes_Sales_Dataset___Working_file[[#This Row],[Cleaned Order Date]],"mmm"),"Unknown") -> Apr | T34: =IF(ISNUMBER(Nikes_Sales_Dataset___Working_file[[#This Row],[Cleaned Order Date]]),TEXT(Nikes_Sales_Dataset___Working_file[[#This Row],[Cleaned Order Date]],"yyyy"),"Unknown") -> 2025 | U34: Retail | V34: Mumbai | W34: Mumbai | X34: -555.16
A35: 2033 | B35: =Nikes_Sales_Dataset___Working_file[[#This Row],[Order_ID]]&"_"&TEXT(Nikes_Sales_Dataset___Working_file[[#This Row],[Cleaned Order Date]],"yyyymmdd") -> 2033_Unknown Date | C35: Men | D35: Soccer | E35: Mercurial Superfly | F35: XL | G35: XL | H35: -1 | I35: =IF(ISBLANK(Nikes_Sales_Dataset___Working_file[[#This Row],[Units_Sold]]),IF(Nikes_Sales_Dataset___Working_file[[#This Row],[Profit]]<0,0,1),Nikes_Sales_Dataset___Working_file[[#This Row],[Units_Sold]]) -> -1 | K35: =IF(ISBLANK(Nikes_Sales_Dataset___Working_file[[#This Row],[MRP]]),MEDIAN(Nikes_Sales_Dataset___Working_file[[#All],[MRP]]),Nikes_Sales_Dataset___Working_file[[#This Row],[MRP]]) -> 6110.03 | M35: =IF(ISBLANK(Nikes_Sales_Dataset___Working_file[[#This Row],[Discount_Applied]]),0,Nikes_Sales_Dataset___Working_file[[#This Row],[Discount_Applied]]) -> 0 | N35: =Nikes_Sales_Dataset___Working_file[[#This Row],[MRP Final]]*(1-Nikes_Sales_Dataset___Working_file[[#This Row],[Cleaned Discount]]) -> 6110.03 | O35: 0 | P35: =Nikes_Sales_Dataset___Working_file[[#This Row],[Sales Price]]*Nikes_Sales_Dataset___Working_file[[#This Row],[Units Sold Filled]] -> -6110.03 | R35: =IF(ISBLANK(Nikes_Sales_Dataset___Working_file[[#This Row],[Order_Date]]),"Unknown Date",Nikes_Sales_Dataset___Working_file[[#This Row],[Order_Date]]) -> Unknown Date | S35: =IF(ISNUMBER(Nikes_Sales_Dataset___Working_file[[#This Row],[Cleaned Order Date]]),TEXT(Nikes_Sales_Dataset___Working_file[[#This Row],[Cleaned Order Date]],"mmm"),"Unknown") -> Unknown | T35: =IF(ISNUMBER(Nikes_Sales_Dataset___Working_file[[#This Row],[Cleaned Order Date]]),TEXT(Nikes_Sales_Dataset___Working_file[[#This Row],[Cleaned Order Date]],"yyyy"),"Unknown") -> Unknown | U35: Retail | V35: Kolkata | W35: Kolkata | X35: -1005.71
A36: 2034 | B36: =Nikes_Sales_Dataset___Working_file[[#This Row],[Order_ID]]&"_"&TEXT(Nikes_Sales_Dataset___Working_file[[#This Row],[Cleaned Order Date]],"yyyymmdd") -> 2034_20250430 | C36: Men | D36: Basketball | E36: Air Jordan | F36: 6 | G36: M | I36: =IF(ISBLANK(Nikes_Sales_Dataset___Working_file[[#This Row],[Units_Sold]]),IF(Nikes_Sales_Dataset___Working_file[[#This Row],[Profit]]<0,0,1),Nikes_Sales_Dataset___Working_file[[#This Row],[Units_Sold]]) -> 0 | J36: 6235.71 | K36: =IF(ISBLANK(Nikes_Sales_Dataset___Working_file[[#This Row],[MRP]]),MEDIAN(Nikes_Sales_Dataset___Working_file[[#All],[MRP]]),Nikes_Sales_Dataset___Working_file[[#This Row],[MRP]]) -> 6235.71 | M36: =IF(ISBLANK(Nikes_Sales_Dataset___Working_file[[#This Row],[Discount_Applied]]),0,Nikes_Sales_Dataset___Working_file[[#This Row],[Discount_Applied]]) -> 0 | N36: =Nikes_Sales_Dataset___Working_file[[#This Row],[MRP Final]]*(1-Nikes_Sales_Dataset___Working_file[[#This Row],[Cleaned Discount]]) -> 6235.71 | O36: 0 | P36: =Nikes_Sales_Dataset___Working_file[[#This Row],[Sales Price]]*Nikes_Sales_Dataset___Working_file[[#This Row],[Units Sold Filled]] -> 0 | Q36: 45777 | R36: =IF(ISBLANK(Nikes_Sales_Dataset___Working_file[[#This Row],[Order_Date]]),"Unknown Date",Nikes_Sales_Dataset___Working_file[[#This Row],[Order_Date]]) -> 45777 | S36: =IF(ISNUMBER(Nikes_Sales_Dataset___Working_file[[#This Row],[Cleaned Order Date]]),TEXT(Nikes_Sales_Dataset___Working_file[[#This Row],[Cleaned Order Date]],"mmm"),"Unknown") -> Apr | T36: =IF(ISNUMBER(Nikes_Sales_Dataset___Working_file[[#This Row],[Cleaned Order Date]]),TEXT(Nikes_Sales_Dataset___Working_file[[#This Row],[Cleaned Order Date]],"yyyy"),"Unknown") -> 2025 | U36: Retail | V36: Delhi | W36: Delhi | X36: -267.37
A37: 2035 | B37: =Nikes_Sales_Dataset___Working_file[[#This Row],[Order_ID]]&"_"&TEXT(Nikes_Sales_Dataset___Working_file[[#This Row],[Cleaned Order Date]],"yyyymmdd") -> 2035_20241117 | C37: Kids | D37: Basketball | E37: Zoom Freak | G37: M | H37: 4 | I37: =IF(ISBLANK(Nikes_Sales_Dataset___Working_file[[#This Row],[Units_Sold]]),IF(Nikes_Sales_Dataset___Working_file[[#This Row],[Profit]]<0,0,1),Nikes_Sales_Dataset___Working_file[[#This Row],[Units_Sold]]) -> 4 | K37: =IF(ISBLANK(Nikes_Sales_Dataset___Working_file[[#This Row],[MRP]]),MEDIAN(Nikes_Sales_Dataset___Working_file[[#All],[MRP]]),Nikes_Sales_Dataset___Working_file[[#This Row],[MRP]]) -> 6110.03 | L37: 0.38 | M37: =IF(ISBLANK(Nikes_Sales_Dataset___Working_file[[#This Row],[Discount_Applied]]),0,Nikes_Sales_Dataset___Working_file[[#This Row],[Discount_Applied]]) -> 0.38 | N37: =Nikes_Sales_Dataset___Working_file[[#This Row],[MRP Final]]*(1-Nikes_Sales_Dataset___Working_file[[#This Row],[Cleaned Discount]]) -> 3788.2186 | O37: 0 | P37: =Nikes_Sales_Dataset___Working_file[[#This Row],[Sales Price]]*Nikes_Sales_Dataset___Working_file[[#This Row],[Units Sold Filled]] -> 15152.874 | Q37: 45613 | R37: =IF(ISBLANK(Nikes_Sales_Dataset___Working_file[[#This Row],[Order_Date]]),"Unknown Date",Nikes_Sales_Dataset___Working_file[[#This Row],[Order_Date]]) -> 45613 | S37: =IF(ISNUMBER(Nikes_Sales_Dataset___Working_file[[#This Row],[Cleaned Order Date]]),TEXT(Nikes_Sales_Dataset___Working_file[[#This Row],[Cleaned Order Date]],"mmm"),"Unknown") -> Nov | T37: =IF(ISNUMBER(Nikes_Sales_Dataset___Working_file[[#This Row],[Cleaned Order Date]]),TEXT(Nikes_Sales_Dataset___Working_file[[#This Row],[Cleaned Order Date]],"yyyy"),"Unknown") -> 2024 | U37: Online | V37: Bangalore | W37: Bangalore | X37: 2914.83
A38: 2036 | B38: =Nikes_Sales_Dataset___Working_file[[#This Row],[Order_ID]]&"_"&TEXT(Nikes_Sales_Dataset___Working_file[[#This Row],[Cleaned Order Date]],"yyyymmdd") -> 2036_20250215 | C38: Men | D38: Training | E38: Metcon 7 | G38: M | H38: 3 | I38: =IF(ISBLANK(Nikes_Sales_Dataset___Working_file[[#This Row],[Units_Sold]]),IF(Nikes_Sales_Dataset___Working_file[[#This Row],[Profit]]<0,0,1),Nikes_Sales_Dataset___Working_file[[#This Row],[Units_Sold]]) -> 3 | K38: =IF(ISBLANK(Nikes_Sales_Dataset___Working_file[[#This Row],[MRP]]),MEDIAN(Nikes_Sales_Dataset___Working_file[[#All],[MRP]]),Nikes_Sales_Dataset___Working_file[[#This Row],[MRP]]) -> 6110.03 | M38: =IF(ISBLANK(Nikes_Sales_Dataset___Working_file[[#This Row],[Discount_Applied]]),0,Nikes_Sales_Dataset___Working_file[[#This Row],[Discount_Applied]]) -> 0 | N38: =Nikes_Sales_Dataset___Working_file[[#This Row],[MRP Final]]*(1-Nikes_Sales_Dataset___Working_file[[#This Row],[Cleaned Discount]]) -> 6110.03 | O38: 0 | P38: =Nikes_Sales_Dataset___Working_file[[#This Row],[Sales Price]]*Nikes_Sales_Dataset___Working_file[[#This Row],[Units Sold Filled]] -> 18330.09 | Q38: 45703 | R38: =IF(ISBLANK(Nikes_Sales_Dataset___Working_file[[#This Row],[Order_Date]]),"Unknown Date",Nikes_Sales_Dataset___Working_file[[#This Row],[Order_Date]]) -> 45703 | S38: =IF(ISNUMBER(Nikes_Sales_Dataset___Working_file[[#This Row],[Cleaned Order Date]]),TEXT(Nikes_Sales_Dataset___Working_file[[#This Row],[Cleaned Order Date]],"mmm"),"Unknown") -> Feb | T38: =IF(ISNUMBER(Nikes_Sales_Dataset___Working_file[[#This Row],[Cleaned Order Date]]),TEXT(Nikes_Sales_Dataset___Working_file[[#This Row],[Cleaned Order Date]],"yyyy"),"Unknown") -> 2025 | U38: Retail | V38: Bangalore | W38: Bangalore | X38: -143.8
A39: 2037 | B39: =Nikes_Sales_Dataset___Working_file[[#This Row],[Order_ID]]&"_"&TEXT(Nikes_Sales_Dataset___Working_file[[#This Row],[Cleaned Order Date]],"yyyymmdd") -> 2037_Unknown Date | C39: Kids | D39: Running | E39: Pegasus Turbo | F39: 7 | G39: M | H39: 3 | I39: =IF(ISBLANK(Nikes_Sales_Dataset___Working_file[[#This Row],[Units_Sold]]),IF(Nikes_Sales_Dataset___Working_file[[#This Row],[Profit]]<0,0,1),Nikes_Sales_Dataset___Working_file[[#This Row],[Units_Sold]]) -> 3 | J39: 5653.14 | K39: =IF(ISBLANK(Nikes_Sales_Dataset___Working_file[[#This Row],[MRP]]),MEDIAN(Nikes_Sales_Dataset___Working_file[[#All],[MRP]]),Nikes_Sales_Dataset___Working_file[[#This Row],[MRP]]) -> 5653.14 | L39: 1.01 | M39: =IF(ISBLANK(Nikes_Sales_Dataset___Working_file[[#This Row],[Discount_Applied]]),0,Nikes_Sales_Dataset___Working_file[[#This Row],[Discount_Applied]]) -> 1.01 | N39: =Nikes_Sales_Dataset___Working_file[[#This Row],[MRP Final]]*(1-Nikes_Sales_Dataset___Working_file[[#This Row],[Cleaned Discount]]) -> -56.5314 | O39: -169.59 | P39: =Nikes_Sales_Dataset___Working_file[[#This Row],[Sales Price]]*Nikes_Sales_Dataset___Working_file[[#This Row],[Units Sold Filled]] -> -169.5942 | R39: =IF(ISBLANK(Nikes_Sales_Dataset___Working_file[[#This Row],[Order_Date]]),"Unknown Date",Nikes_Sales_Dataset___Working_file[[#This Row],[Order_Date]]) -> Unknown Date | S39: =IF(ISNUMBER(Nikes_Sales_Dataset___Working_file[[#This Row],[Cleaned Order Date]]),TEXT(Nikes_Sales_Dataset___Working_file[[#This Row],[Cleaned Order Date]],"mmm"),"Unknown") -> Unknown | T39: =IF(ISNUMBER(Nikes_Sales_Dataset___Working_file[[#This Row],[Cleaned Order Date]]),TEXT(Nikes_Sales_Dataset___Working_file[[#This Row],[Cleaned Order Date]],"yyyy"),"Unknown") -> Unknown | U39: Retail | V39: Pune | W39: Pune | X39: 2776.96
A40: 2038 | B40: =Nikes_Sales_Dataset___Working_file[[#This Row],[Order_ID]]&"_"&TEXT(Nikes_Sales_Dataset___Working_file[[#This Row],[Cleaned Order Date]],"yyyymmdd") -> 2038_Unknown Date | C40: Kids | D40: Running | E40: Free RN | G40: M | H40: 0 | I40: =IF(ISBLANK(Nikes_Sales_Dataset___Working_file[[#This Row],[Units_Sold]]),IF(Nikes_Sales_Dataset___Working_file[[#This Row],[Profit]]<0,0,1),Nikes_Sales_Dataset___Working_file[[#This Row],[Units_Sold]]) -> 0 | K40: =IF(ISBLANK(Nikes_Sales_Dataset___Working_file[[#This Row],[MRP]]),MEDIAN(Nikes_Sales_Dataset___Working_file[[#All],[MRP]]),Nikes_Sales_Dataset___Working_file[[#This Row],[MRP]]) -> 6110.03 | L40: 0.83 | M40: =IF(ISBLANK(Nikes_Sales_Dataset___Working_file[[#This Row],[Discount_Applied]]),0,Nikes_Sales_Dataset___Working_file[[#This Row],[Discount_Applied]]) -> 0.83 | N40: =Nikes_Sales_Dataset___Working_file[[#This Row],[MRP Final]]*(1-Nikes_Sales_Dataset___Working_file[[#This Row],[Cleaned Discount]]) -> 1038.7051 | O40: 0 | P40: =Nikes_Sales_Dataset___Working_file[[#This Row],[Sales Price]]*Nikes_Sales_Dataset___Working_file[[#This Row],[Units Sold Filled]] -> 0 | R40: =IF(ISBLANK(Nikes_Sales_Dataset___Working_file[[#This Row],[Order_Date]]),"Unknown Date",Nikes_Sales_Dataset___Working_file[[#This Row],[Order_Date]]) -> Unknown Date | S40: =IF(ISNUMBER(Nikes_Sales_Dataset___Working_file[[#This Row],[Cleaned Order Date]]),TEXT(Nikes_Sales_Dataset___Working_file[[#This Row],[Cleaned Order Date]],"mmm"),"Unknown") -> Unknown | T40: =IF(ISNUMBER(Nikes_Sales_Dataset___Working_file[[#This Row],[Cleaned Order Date]]),TEXT(Nikes_Sales_Dataset___Working_file[[#This Row],[Cleaned Order Date]],"yyyy"),"Unknown") -> Unknown | U40: Online | V40: Delhi | W40: Delhi | X40: 1163.21
A41: 2039 | B41: =Nikes_Sales_Dataset___Working_file[[#This Row],[Order_ID]]&"_"&TEXT(Nikes_Sales_Dataset___Working_file[[#This Row],[Cleaned Order Date]],"yyyymmdd") -> 2039_20250422 | C41: Women | D41: Training | E41: Flex Trainer | F41: M | G41: M | I41: =IF(ISBLANK(Nikes_Sales_Dataset___Working_file[[#This Row],[Units_Sold]]),IF(Nikes_Sales_Dataset___Working_file[[#This Row],[Profit]]<0,0,1),Nikes_Sales_Dataset___Working_file[[#This Row],[Units_Sold]]) -> 0 | J41: 2767.7 | K41: =IF(ISBLANK(Nikes_Sales_Dataset___Working_file[[#This Row],[MRP]]),MEDIAN(Nikes_Sales_Dataset___Working_file[[#All],[MRP]]),Nikes_Sales_Dataset___Working_file[[#This Row],[MRP]]) -> 2767.7 | L41: 0.63 | M41: =IF(ISBLANK(Nikes_Sales_Dataset___Working_file[[#This Row],[Discount_Applied]]),0,Nikes_Sales_Dataset___Working_file[[#This Row],[Discount_Applied]]) -> 0.63 | N41: =Nikes_Sales_Dataset___Working_file[[#This Row],[MRP Final]]*(1-Nikes_Sales_Dataset___Working_file[[#This Row],[Cleaned Discount]]) -> 1024.049 | O41: 0 | P41: =Nikes_Sales_Dataset___Working_file[[#This Row],[Sales Price]]*Nikes_Sales_Dataset___Working_file[[#This Row],[Units Sold Filled]] -> 0 | Q41: 45769 | R41: =IF(ISBLANK(Nikes_Sales_Dataset___Working_file[[#This Row],[Order_Date]]),"Unknown Date",Nikes_Sales_Dataset___Working_file[[#This Row],[Order_Date]]) -> 45769 | S41: =IF(ISNUMBER(Nikes_Sales_Dataset___Working_file[[#This Row],[Cleaned Order Date]]),TEXT(Nikes_Sales_Dataset___Working_file[[#This Row],[Cleaned Order Date]],"mmm"),"Unknown") -> Apr | T41: =IF(ISNUMBER(Nikes_Sales_Dataset___Working_file[[#This Row],[Cleaned Order Date]]),TEXT(Nikes_Sales_Dataset___Working_file[[#This Row],[Cleaned Order Date]],"yyyy"),"Unknown") -> 2025 | U41: Retail | V41: hyderbad | W41: Hyderabad | X41: -336.3
A42: 2002 | B42: =Nikes_Sales_Dataset___Working_file[[#This Row],[Order_ID]]&"_"&TEXT(Nikes_Sales_Dataset___Working_file[[#This Row],[Cleaned Order Date]],"yyyymmdd") -> 2002_20250307 | C42: Women | D42: Basketball | E42: Zoom Freak | F42: XL | G42: XL | H42: 3 | I42: =IF(ISBLANK(Nikes_Sales_Dataset___Working_file[[#This Row],[Units_Sold]]),IF(Nikes_Sales_Dataset___Working_file[[#This Row],[Profit]]<0,0,1),Nikes_Sales_Dataset___Working_file[[#This Row],[Units_Sold]]) -> 3 | J42: 5075.22 | K42: =IF(ISBLANK(Nikes_Sales_Dataset___Working_file[[#This Row],[MRP]]),MEDIAN(Nikes_Sales_Dataset___Working_file[[#All],[MRP]]),Nikes_Sales_Dataset___Working_file[[#This Row],[MRP]]) -> 5075.22 | M42: =IF(ISBLANK(Nikes_Sales_Dataset___Working_file[[#This Row],[Discount_Applied]]),0,Nikes_Sales_Dataset___Working_file[[#This Row],[Discount_Applied]]) -> 0 | N42: =Nikes_Sales_Dataset___Working_file[[#This Row],[MRP Final]]*(1-Nikes_Sales_Dataset___Working_file[[#This Row],[Cleaned Discount]]) -> 5075.22 | O42: 0 | P42: =Nikes_Sales_Dataset___Working_file[[#This Row],[Sales Price]]*Nikes_Sales_Dataset___Working_file[[#This Row],[Units Sold Filled]] -> 15225.66 | Q42: 45723 | R42: =IF(ISBLANK(Nikes_Sales_Dataset___Working_file[[#This Row],[Order_Date]]),"Unknown Date",Nikes_Sales_Dataset___Working_file[[#This Row],[Order_Date]]) -> 45723 | S42: =IF(ISNUMBER(Nikes_Sales_Dataset___Working_file[[#This Row],[Cleaned Order Date]]),TEXT(Nikes_Sales_Dataset___Working_file[[#This Row],[Cleaned Order Date]],"mmm"),"Unknown") -> Mar | T42: =IF(ISNUMBER(Nikes_Sales_Dataset___Working_file[[#This Row],[Cleaned Order Date]]),TEXT(Nikes_Sales_Dataset___Working_file[[#This Row],[Cleaned Order Date]],"yyyy"),"Unknown") -> 2025 | U42: Retail | V42: Delhi | W42: Delhi | X42: 145.08
A43: 2041 | B43: =Nikes_Sales_Dataset___Working_file[[#This Row],[Order_ID]]&"_"&TEXT(Nikes_Sales_Dataset___Working_file[[#This Row],[Cleaned Order Date]],"yyyymmdd") -> 2041_20250305 | C43: Kids | D43: Soccer | E43: Tiempo Legend | F43: 12 | G43: XL | I43: =IF(ISBLANK(Nikes_Sales_Dataset___Working_file[[#This Row],[Units_Sold]]),IF(Nikes_Sales_Dataset___Working_file[[#This Row],[Profit]]<0,0,1),Nikes_Sales_Dataset___Working_file[[#This Row],[Units_Sold]]) -> 1 | J43: 5553.88 | K43: =IF(ISBLANK(Nikes_Sales_Dataset___Working_file[[#This Row],[MRP]]),MEDIAN(Nikes_Sales_Dataset___Working_file[[#All],[MRP]]),Nikes_Sales_Dataset___Working_file[[#This Row],[MRP]]) -> 5553.88 | M43: =IF(ISBLANK(Nikes_Sales_Dataset___Working_file[[#This Row],[Discount_Applied]]),0,Nikes_Sales_Dataset___Working_file[[#This Row],[Discount_Applied]]) -> 0 | N43: =Nikes_Sales_Dataset___Working_file[[#This Row],[MRP Final]]*(1-Nikes_Sales_Dataset___Working_file[[#This Row],[Cleaned Discount]]) -> 5553.88 | O43: 0 | P43: =Nikes_Sales_Dataset___Working_file[[#This Row],[Sales Price]]*Nikes_Sales_Dataset___Working_file[[#This Row],[Units Sold Filled]] -> 5553.88 | Q43: 45721 | R43: =IF(ISBLANK(Nikes_Sales_Dataset___Working_file[[#This Row],[Order_Date]]),"Unknown Date",Nikes_Sales_Dataset___Working_file[[#This Row],[Order_Date]]) -> 45721 | S43: =IF(ISNUMBER(Nikes_Sales_Dataset___Working_file[[#This Row],[Cleaned Order Date]]),TEXT(Nikes_Sales_Dataset___Working_file[[#This Row],[Cleaned Order Date]],"mmm"),"Unknown") -> Mar | T43: =IF(ISNUMBER(Nikes_Sales_Dataset___Working_file[[#This Row],[Cleaned Order Date]]),TEXT(Nikes_Sales_Dataset___Working_file[[#This Row],[Cleaned Order Date]],"yyyy"),"Unknown") -> 2025 | U43: Online | V43: Hyd | W43: Hyderabad | X43: 2371.66
A44: 2042 | B44: =Nikes_Sales_Dataset___Working_file[[#This Row],[Order_ID]]&"_"&TEXT(Nikes_Sales_Dataset___Working_file[[#This Row],[Cleaned Order Date]],"yyyymmdd") -> 2042_20250419 | C44: Women | D44: Basketball | E44: Kyrie Flytrap | F44: L | G44: L | I44: =IF(ISBLANK(Nikes_Sales_Dataset___Working_file[[#This Row],[Units_Sold]]),IF(Nikes_Sales_Dataset___Working_file[[#This Row],[Profit]]<0,0,1),Nikes_Sales_Dataset___Working_file[[#This Row],[Units_Sold]]) -> 0 | K44: =IF(ISBLANK(Nikes_Sales_Dataset___Working_file[[#This Row],[MRP]]),MEDIAN(Nikes_Sales_Dataset___Working_file[[#All],[MRP]]),Nikes_Sales_Dataset___Working_file[[#This Row],[MRP]]) -> 6110.03 | M44: =IF(ISBLANK(Nikes_Sales_Dataset___Working_file[[#This Row],[Discount_Applied]]),0,Nikes_Sales_Dataset___Working_file[[#This Row],[Discount_Applied]]) -> 0 | N44: =Nikes_Sales_Dataset___Working_file[[#This Row],[MRP Final]]*(1-Nikes_Sales_Dataset___Working_file[[#This Row],[Cleaned Discount]]) -> 6110.03 | O44: 0 | P44: =Nikes_Sales_Dataset___Working_file[[#This Row],[Sales Price]]*Nikes_Sales_Dataset___Working_file[[#This Row],[Units Sold Filled]] -> 0 | Q44: 45766 | R44: =IF(ISBLANK(Nikes_Sales_Dataset___Working_file[[#This Row],[Order_Date]]),"Unknown Date",Nikes_Sales_Dataset___Working_file[[#This Row],[Order_Date]]) -> 45766 | S44: =IF(ISNUMBER(Nikes_Sales_Dataset___Working_file[[#This Row],[Cleaned Order Date]]),TEXT(Nikes_Sales_Dataset___Working_file[[#This Row],[Cleaned Order Date]],"mmm"),"Unknown") -> Apr | T44: =IF(ISNUMBER(Nikes_Sales_Dataset___Working_file[[#This Row],[Cleaned Order Date]]),TEXT(Nikes_Sales_Dataset___Working_file[[#This Row],[Cleaned Order Date]],"yyyy"),"Unknown") -> 2025 | U44: Online | V44: hyderbad | W44: Hyderabad | X44: -862.16
A45: 2043 | B45: =Nikes_Sales_Dataset___Working_file[[#This Row],[Order_ID]]&"_"&TEXT(Nikes_Sales_Dataset___Working_file[[#This Row],[Cleaned Order Date]],"yyyymmdd") -> 2043_20240502 | C45: Men | D45: Soccer | E45: Premier III | F45: XL | G45: XL | I45: =IF(ISBLANK(Nikes_Sales_Dataset___Working_file[[#This Row],[Units_Sold]]),IF(Nikes_Sales_Dataset___Working_file[[#This Row],[Profit]]<0,0,1),Nikes_Sales_Dataset___Working_file[[#This Row],[Units_Sold]]) -> 1 | J45: 3492.89 | K45: =IF(ISBLANK(Nikes_Sales_Dataset___Working_file[[#This Row],[MRP]]),MEDIAN(Nikes_Sales_Dataset___Working_file[[#All],[MRP]]),Nikes_Sales_Dataset___Working_file[[#This Row],[MRP]]) -> 3492.89 | L45: 0.77 | M45: =IF(ISBLANK(Nikes_Sales_Dataset___Working_file[[#This Row],[Discount_Applied]]),0,Nikes_Sales_Dataset___Working_file[[#This Row],[Discount_Applied]]) -> 0.77 | N45: =Nikes_Sales_Dataset___Working_file[[#This Row],[MRP Final]]*(1-Nikes_Sales_Dataset___Working_file[[#This Row],[Cleaned Discount]]) -> 803.3647 | O45: 0 | P45: =Nikes_Sales_Dataset___Working_file[[#This Row],[Sales Price]]*Nikes_Sales_Dataset___Working_file[[#This Row],[Units Sold Filled]] -> 803.3647 | Q45: 45414 | R45: =IF(ISBLANK(Nikes_Sales_Dataset___Working_file[[#This Row],[Order_Date]]),"Unknown Date",Nikes_Sales_Dataset___Working_file[[#This Row],[Order_Date]]) -> 45414 | S45: =IF(ISNUMBER(Nikes_Sales_Dataset___Working_file[[#This Row],[Cleaned Order Date]]),TEXT(Nikes_Sales_Dataset___Working_file[[#This Row],[Cleaned Order Date]],"mmm"),"Unknown") -> May | T45: =IF(ISNUMBER(Nikes_Sales_Dataset___Working_file[[#This Row],[Cleaned Order Date]]),TEXT(Nikes_Sales_Dataset___Working_file[[#This Row],[Cleaned Order Date]],"yyyy"),"Unknown") -> 2024 | U45: Retail | V45: Delhi | W45: Delhi | X45: 3770.75
A46: 2044 | B46: =Nikes_Sales_Dataset___Working_file[[#This Row],[Order_ID]]&"_"&TEXT(Nikes_Sales_Dataset___Working_file[[#This Row],[Cleaned Order Date]],"yyyymmdd") -> 2044_20230906 | C46: Kids | D46: Training | E46: SuperRep Go | G46: M | I46: =IF(ISBLANK(Nikes_Sales_Dataset___Working_file[[#This Row],[Units_Sold]]),IF(Nikes_Sales_Dataset___Working_file[[#This Row],[Profit]]<0,0,1),Nikes_Sales_Dataset___Working_file[[#This Row],[Units_Sold]]) -> 1 | K46: =IF(ISBLANK(Nikes_Sales_Dataset___Working_file[[#This Row],[MRP]]),MEDIAN(Nikes_Sales_Dataset___Working_file[[#All],[MRP]]),Nikes_Sales_Dataset___Working_file[[#This Row],[MRP]]) -> 6110.03 | M46: =IF(ISBLANK(Nikes_Sales_Dataset___Working_file[[#This Row],[Discount_Applied]]),0,Nikes_Sales_Dataset___Working_file[[#This Row],[Discount_Applied]]) -> 0 | N46: =Nikes_Sales_Dataset___Working_file[[#This Row],[MRP Final]]*(1-Nikes_Sales_Dataset___Working_file[[#This Row],[Cleaned Discount]]) -> 6110.03 | O46: 0 | P46: =Nikes_Sales_Dataset___Working_file[[#This Row],[Sales Price]]*Nikes_Sales_Dataset___Working_file[[#This Row],[Units Sold Filled]] -> 6110.03 | Q46: 45175 | R46: =IF(ISBLANK(Nikes_Sales_Dataset___Working_file[[#This Row],[Order_Date]]),"Unknown Date",Nikes_Sales_Dataset___Working_file[[#This Row],[Order_Date]]) -> 45175 | S46: =IF(ISNUMBER(Nikes_Sales_Dataset___Working_file[[#This Row],[Cleaned Order Date]]),TEXT(Nikes_Sales_Dataset___Working_file[[#This Row],[Cleaned Order Date]],"mmm"),"Unknown") -> Sep | T46: =IF(ISNUMBER(Nikes_Sales_Dataset___Working_file[[#This Row],[Cleaned Order Date]]),TEXT(Nikes_Sales_Dataset___Working_file[[#This Row],[Cleaned Order Date]],"yyyy"),"Unknown") -> 2023 | U46: Online | V46: Delhi | W46: Delhi | X46: 2174.71
A47: 2045 | B47: =Nikes_Sales_Dataset___Working_file[[#This Row],[Order_ID]]&"_"&TEXT(Nikes_Sales_Dataset___Working_file[[#This Row],[Cleaned Order Date]],"yyyymmdd") -> 2045_20250406 | C47: Kids | D47: Lifestyle | E47: Dunk Low | F47: XL | G47: XL | H47: 4 | I47: =IF(ISBLANK(Nikes_Sales_Dataset___Working_file[[#This Row],[Units_Sold]]),IF(Nikes_Sales_Dataset___Working_file[[#This Row],[Profit]]<0,0,1),Nikes_Sales_Dataset___Working_file[[#This Row],[Units_Sold]]) -> 4 | K47: =IF(ISBLANK(Nikes_Sales_Dataset___Working_file[[#This Row],[MRP]]),MEDIAN(Nikes_Sales_Dataset___Working_file[[#All],[MRP]]),Nikes_Sales_Dataset___Working_file[[#This Row],[MRP]]) -> 6110.03 | M47: =IF(ISBLANK(Nikes_Sales_Dataset___Working_file[[#This Row],[Discount_Applied]]),0,Nikes_Sales_Dataset___Working_file[[#This Row],[Discount_Applied]]) -> 0 | N47: =Nikes_Sales_Dataset___Working_file[[#This Row],[MRP Final]]*(1-Nikes_Sales_Dataset___Working_file[[#This Row],[Cleaned Discount]]) -> 6110.03 | O47: 0 | P47: =Nikes_Sales_Dataset___Working_file[[#This Row],[Sales Price]]*Nikes_Sales_Dataset___Working_file[[#This Row],[Units Sold Filled]] -> 24440.12 | Q47: 45753 | R47: =IF(ISBLANK(Nikes_Sales_Dataset___Working_file[[#This Row],[Order_Date]]),"Unknown Date",Nikes_Sales_Dataset___Working_file[[#This Row],[Order_Date]]) -> 45753 | S47: =IF(ISNUMBER(Nikes_Sales_Dataset___Working_file[[#This Row],[Cleaned Order Date]]),TEXT(Nikes_Sales_Dataset___Working_file[[#This Row],[Cleaned Order Date]],"mmm"),"Unknown") -> Apr | T47: =IF(ISNUMBER(Nikes_Sales_Dataset___Working_file[[#This Row],[Cleaned Order Date]]),TEXT(Nikes_Sales_Dataset___Working_file[[#This Row],[Cleaned Order Date]],"yyyy"),"Unknown") -> 2025 | U47: Retail | V47: Delhi | W47: Delhi | X47: 1833.94
A48: 2046 | B48: =Nikes_Sales_Dataset___Working_file[[#This Row],[Order_ID]]&"_"&TEXT(Nikes_Sales_Dataset___Working_file[[#This Row],[Cleaned Order Date]],"yyyymmdd") -> 2046_Unknown Date | C48: Kids | D48: Running | E48: Air Zoom | F48: 12 | G48: XL | I48: =IF(ISBLANK(Nikes_Sales_Dataset___Working_file[[#This Row],[Units_Sold]]),IF(Nikes_Sales_Dataset___Working_file[[#This Row],[Profit]]<0,0,1),Nikes_Sales_Dataset___Working_file[[#This Row],[Units_Sold]]) -> 1 | K48: =IF(ISBLANK(Nikes_Sales_Dataset___Working_file[[#This Row],[MRP]]),MEDIAN(Nikes_Sales_Dataset___Working_file[[#All],[MRP]]),Nikes_Sales_Dataset___Working_file[[#This Row],[MRP]]) -> 6110.03 | L48: 1.04 | M48: =IF(ISBLANK(Nikes_Sales_Dataset___Working_file[[#This Row],[Discount_Applied]]),0,Nikes_Sales_Dataset___Working_file[[#This Row],[Discount_Applied]]) -> 1.04 | N48: =Nikes_Sales_Dataset___Working_file[[#This Row],[MRP Final]]*(1-Nikes_Sales_Dataset___Working_file[[#This Row],[Cleaned Discount]]) -> -244.4012 | O48: 0 | P48: =Nikes_Sales_Dataset___Working_file[[#This Row],[Sales Price]]*Nikes_Sales_Dataset___Working_file[[#This Row],[Units Sold Filled]] -> -244.4012 | R48: =IF(ISBLANK(Nikes_Sales_Dataset___Working_file[[#This Row],[Order_Date]]),"Unknown Date",Nikes_Sales_Dataset___Working_file[[#This Row],[Order_Date]]) -> Unknown Date | S48: =IF(ISNUMBER(Nikes_Sales_Dataset___Working_file[[#This Row],[Cleaned Order Date]]),TEXT(Nikes_Sales_Dataset___Working_file[[#This Row],[Cleaned Order Date]],"mmm"),"Unknown") -> Unknown | T48: =IF(ISNUMBER(Nikes_Sales_Dataset___Working_file[[#This Row],[Cleaned Order Date]]),TEXT(Nikes_Sales_Dataset___Working_file[[#This Row],[Cleaned Order Date]],"yyyy"),"Unknown") -> Unknown | U48: Online | V48: Kolkata | W48: Kolkata | X48: 1284.33
A49: 2047 | B49: =Nikes_Sales_Dataset___Working_file[[#This Row],[Order_ID]]&"_"&TEXT(Nikes_Sales_Dataset___Working_file[[#This Row],[Cleaned Order Date]],"yyyymmdd") -> 2047_20240613 | C49: Women | D49: Training | E49: SuperRep Go | F49: 10 | G49: L | H49: 1 | I49: =IF(ISBLANK(Nikes_Sales_Dataset___Working_file[[#This Row],[Units_Sold]]),IF(Nikes_Sales_Dataset___Working_file[[#This Row],[Profit]]<0,0,1),Nikes_Sales_Dataset___Working_file[[#This Row],[Units_Sold]]) -> 1 | J49: 8577.75 | K49: =IF(ISBLANK(Nikes_Sales_Dataset___Working_file[[#This Row],[MRP]]),MEDIAN(Nikes_Sales_Dataset___Working_file[[#All],[MRP]]),Nikes_Sales_Dataset___Working_file[[#This Row],[MRP]]) -> 8577.75 | M49: =IF(ISBLANK(Nikes_Sales_Dataset___Working_file[[#This Row],[Discount_Applied]]),0,Nikes_Sales_Dataset___Working_file[[#This Row],[Discount_Applied]]) -> 0 | N49: =Nikes_Sales_Dataset___Working_file[[#This Row],[MRP Final]]*(1-Nikes_Sales_Dataset___Working_file[[#This Row],[Cleaned Discount]]) -> 8577.75 | O49: 0 | P49: =Nikes_Sales_Dataset___Working_file[[#This Row],[Sales Price]]*Nikes_Sales_Dataset___Working_file[[#This Row],[Units Sold Filled]] -> 8577.75 | Q49: 45456 | R49: =IF(ISBLANK(Nikes_Sales_Dataset___Working_file[[#This Row],[Order_Date]]),"Unknown Date",Nikes_Sales_Dataset___Working_file[[#This Row],[Order_Date]]) -> 45456 | S49: =IF(ISNUMBER(Nikes_Sales_Dataset___Working_file[[#This Row],[Cleaned Order Date]]),TEXT(Nikes_Sales_Dataset___Working_file[[#This Row],[Cleaned Order Date]],"mmm"),"Unknown") -> Jun | T49: =IF(ISNUMBER(Nikes_Sales_Dataset___Working_file[[#This Row],[Cleaned Order Date]]),TEXT(Nikes_Sales_Dataset___Working_file[[#This Row],[Cleaned Order Date]],"yyyy"),"Unknown") -> 2024 | U49: Retail | V49: Bangalore | W49: Bangalore | X49: 2888.68
A50: 2048 | B50: =Nikes_Sales_Dataset___Working_file[[#This Row],[Order_ID]]&"_"&TEXT(Nikes_Sales_Dataset___Working_file[[#This Row],[Cleaned Order Date]],"yyyymmdd") -> 2048_20241027 | C50: Women | D50: Basketball | E50: Air Jordan | F50: XL | G50: XL | I50: =IF(ISBLANK(Nikes_Sales_Dataset___Working_file[[#This Row],[Units_Sold]]),IF(Nikes_Sales_Dataset___Working_file[[#This Row],[Profit]]<0,0,1),Nikes_Sales_Dataset___Working_file[[#This Row],[Units_Sold]]) -> 1 | K50: =IF(ISBLANK(Nikes_Sales_Dataset___Working_file[[#This Row],[MRP]]),MEDIAN(Nikes_Sales_Dataset___Working_file[[#All],[MRP]]),Nikes_Sales_Dataset___Working_file[[#This Row],[MRP]]) -> 6110.03 | M50: =IF(ISBLANK(Nikes_Sales_Dataset___Working_file[[#This Row],[Discount_Applied]]),0,Nikes_Sales_Dataset___Working_file[[#This Row],[Discount_Applied]]) -> 0 | N50: =Nikes_Sales_Dataset___Working_file[[#This Row],[MRP Final]]*(1-Nikes_Sales_Dataset___Working_file[[#This Row],[Cleaned Discount]]) -> 6110.03 | O50: 0 | P50: =Nikes_Sales_Dataset___Working_file[[#This Row],[Sales Price]]*Nikes_Sales_Dataset___Working_file[[#This Row],[Units Sold Filled]] -> 6110.03 | Q50: 45592 | R50: =IF(ISBLANK(Nikes_Sales_Dataset___Working_file[[#This Row],[Order_Date]]),"Unknown Date",Nikes_Sales_Dataset___Working_file[[#This Row],[Order_Date]]) -> 45592 | S50: =IF(ISNUMBER(Nikes_Sales_Dataset___Working_file[[#This Row],[Cleaned Order Date]]),TEXT(Nikes_Sales_Dataset___Working_file[[#This Row],[Cleaned Order Date]],"mmm"),"Unknown") -> Oct | T50: =IF(ISNUMBER(Nikes_Sales_Dataset___Working_file[[#This Row],[Cleaned Order Date]]),TEXT(Nikes_Sales_Dataset___Working_file[[#This Row],[Cleaned Order Date]],"yyyy"),"Unknown") -> 2024 | U50: Online | V50: Bangalore | W50: Bangalore | X50: 2875.86
A51: 2049 | B51: =Nikes_Sales_Dataset___Working_file[[#This Row],[Order_ID]]&"_"&TEXT(Nikes_Sales_Dataset___Working_file[[#This Row],[Cleaned Order Date]],"yyyymmdd") -> 2049_Unknown Date | C51: Kids | D51: Soccer | E51: Tiempo Legend | F51: L | G51: L | H51: 1 | I51: =IF(ISBLANK(Nikes_Sales_Dataset___Working_file[[#This Row],[Units_Sold]]),IF(Nikes_Sales_Dataset___Working_file[[#This Row],[Profit]]<0,0,1),Nikes_Sales_Dataset___Working_file[[#This Row],[Units_Sold]]) -> 1 | J51: 7767.2 | K51: =IF(ISBLANK(Nikes_Sales_Dataset___Working_file[[#This Row],[MRP]]),MEDIAN(Nikes_Sales_Dataset___Working_file[[#All],[MRP]]),Nikes_Sales_Dataset___Working_file[[#This Row],[MRP]]) -> 7767.2 | M51: =IF(ISBLANK(Nikes_Sales_Dataset___Working_file[[#This Row],[Discount_Applied]]),0,Nikes_Sales_Dataset___Working_file[[#This Row],[Discount_Applied]]) -> 0 | N51: =Nikes_Sales_Dataset___Working_file[[#This Row],[MRP Final]]*(1-Nikes_Sales_Dataset___Working_file[[#This Row],[Cleaned Discount]]) -> 7767.2 | O51: 0 | P51: =Nikes_Sales_Dataset___Working_file[[#This Row],[Sales Price]]*Nikes_Sales_Dataset___Working_file[[#This Row],[Units Sold Filled]] -> 7767.2 | R51: =IF(ISBLANK(Nikes_Sales_Dataset___Working_file[[#This Row],[Order_Date]]),"Unknown Date",Nikes_Sales_Dataset___Working_file[[#This Row],[Order_Date]]) -> Unknown Date | S51: =IF(ISNUMBER(Nikes_Sales_Dataset___Working_file[[#This Row],[Cleaned Order Date]]),TEXT(Nikes_Sales_Dataset___Working_file[[#This Row],[Cleaned Order Date]],"mmm"),"Unknown") -> Unknown | T51: =IF(ISNUMBER(Nikes_Sales_Dataset___Working_file[[#This Row],[Cleaned Order Date]]),TEXT(Nikes_Sales_Dataset___Working_file[[#This Row],[Cleaned Order Date]],"yyyy"),"Unknown") -> Unknown | U51: Retail | V51: Pune | W51: Pune | X51: 311.48
A52: 2050 | B52: =Nikes_Sales_Dataset___Working_file[[#This Row],[Order_ID]]&"_"&TEXT(Nikes_Sales_Dataset___Working_file[[#This Row],[Cleaned Order Date]],"yyyymmdd") -> 2050_Unknown Date | C52: Men | D52: Running | E52: Air Zoom | F52: L | G52: L | H52: 1 | I52: =IF(ISBLANK(Nikes_Sales_Dataset___Working_file[[#This Row],[Units_Sold]]),IF(Nikes_Sales_Dataset___Working_file[[#This Row],[Profit]]<0,0,1),Nikes_Sales_Dataset___Working_file[[#This Row],[Units_Sold]]) -> 1 | K52: =IF(ISBLANK(Nikes_Sales_Dataset___Working_file[[#This Row],[MRP]]),MEDIAN(Nikes_Sales_Dataset___Working_file[[#All],[MRP]]),Nikes_Sales_Dataset___Working_file[[#This Row],[MRP]]) -> 6110.03 | L52: 0.57 | M52: =IF(ISBLANK(Nikes_Sales_Dataset___Working_file[[#This Row],[Discount_Applied]]),0,Nikes_Sales_Dataset___Working_file[[#This Row],[Discount_Applied]]) -> 0.57 | N52: =Nikes_Sales_Dataset___Working_file[[#This Row],[MRP Final]]*(1-Nikes_Sales_Dataset___Working_file[[#This Row],[Cleaned Discount]]) -> 2627.3129 | O52: 0 | P52: =Nikes_Sales_Dataset___Working_file[[#This Row],[Sales Price]]*Nikes_Sales_Dataset___Working_file[[#This Row],[Units Sold Filled]] -> 2627.3129 | R52: =IF(ISBLANK(Nikes_Sales_Dataset___Working_file[[#This Row],[Order_Date]]),"Unknown Date",Nikes_Sales_Dataset___Working_file[[#This Row],[Order_Date]]) -> Unknown Date | S52: =IF(ISNUMBER(Nikes_Sales_Dataset___Working_file[[#This Row],[Cleaned Order Date]]),TEXT(Nikes_Sales_Dataset___Working_file[[#This Row],[Cleaned Order Date]],"mmm"),"Unknown") -> Unknown | T52: =IF(ISNUMBER(Nikes_Sales_Dataset___Working_file[[#This Row],[Cleaned Order Date]]),TEXT(Nikes_Sales_Dataset___Working_file[[#This Row],[Cleaned Order Date]],"yyyy"),"Unknown") -> Unknown | U52: Retail | V52: Kolkata | W52: Kolkata | X52: 682.12
A53: 2051 | B53: =Nikes_Sales_Dataset___Working_file[[#This Row],[Order_ID]]&"_"&TEXT(Nikes_Sales_Dataset___Working_file[[#This Row],[Cleaned Order Date]],"yyyymmdd") -> 2051_20240105 | C53: Women | D53: Basketball | E53: Air Jordan | F53: XL | G53: XL | I53: =IF(ISBLANK(Nikes_Sales_Dataset___Working_file[[#This Row],[Units_Sold]]),IF(Nikes_Sales_Dataset___Working_file[[#This Row],[Profit]]<0,0,1),Nikes_Sales_Dataset___Working_file[[#This Row],[Units_Sold]]) -> 1 | K53: =IF(ISBLANK(Nikes_Sales_Dataset___Working_file[[#This Row],[MRP]]),MEDIAN(Nikes_Sales_Dataset___Working_file[[#All],[MRP]]),Nikes_Sales_Dataset___Working_file[[#This Row],[MRP]]) -> 6110.03 | L53: 0.37 | M53: =IF(ISBLANK(Nikes_Sales_Dataset___Working_file[[#This Row],[Discount_Applied]]),0,Nikes_Sales_Dataset___Working_file[[#This Row],[Discount_Applied]]) -> 0.37 | N53: =Nikes_Sales_Dataset___Working_file[[#This Row],[MRP Final]]*(1-Nikes_Sales_Dataset___Working_file[[#This Row],[Cleaned Discount]]) -> 3849.3189 | O53: 0 | P53: =Nikes_Sales_Dataset___Working_file[[#This Row],[Sales Price]]*Nikes_Sales_Dataset___Working_file[[#This Row],[Units Sold Filled]] -> 3849.3189 | Q53: 45296 | R53: =IF(ISBLANK(Nikes_Sales_Dataset___Working_file[[#This Row],[Order_Date]]),"Unknown Date",Nikes_Sales_Dataset___Working_file[[#This Row],[Order_Date]]) -> 45296 | S53: =IF(ISNUMBER(Nikes_Sales_Dataset___Working_file[[#This Row],[Cleaned Order Date]]),TEXT(Nikes_Sales_Dataset___Working_file[[#This Row],[Cleaned Order Date]],"mmm"),"Unknown") -> Jan | T53: =IF(ISNUMBER(Nikes_Sales_Dataset___Working_file[[#This Row],[Cleaned Order Date]]),TEXT(Nikes_Sales_Dataset___Working_file[[#This Row],[Cleaned Order Date]],"yyyy"),"Unknown") -> 2024 | U53: Retail | V53: Delhi | W53: Delhi | X53: 3135.98
A54: 2052 | B54: =Nikes_Sales_Dataset___Working_file[[#This Row],[Order_ID]]&"_"&TEXT(Nikes_Sales_Dataset___Working_file[[#This Row],[Cleaned Order Date]],"yyyymmdd") -> 2052_20241008 | C54: Men | D54: Training | E54: Flex Trainer | F54: 10 | G54: L | H54: 3 | I54: =IF(ISBLANK(Nikes_Sales_Dataset___Working_file[[#This Row],[Units_Sold]]),IF(Nikes_Sales_Dataset___Working_file[[#This Row],[Profit]]<0,0,1),Nikes_Sales_Dataset___Working_file[[#This Row],[Units_Sold]]) -> 3 | J54: 9155.96 | K54: =IF(ISBLANK(Nikes_Sales_Dataset___Working_file[[#This Row],[MRP]]),MEDIAN(Nikes_Sales_Dataset___Working_file[[#All],[MRP]]),Nikes_Sales_Dataset___Working_file[[#This Row],[MRP]]) -> 9155.96 | M54: =IF(ISBLANK(Nikes_Sales_Dataset___Working_file[[#This Row],[Discount_Applied]]),0,Nikes_Sales_Dataset___Working_file[[#This Row],[Discount_Applied]]) -> 0 | N54: =Nikes_Sales_Dataset___Working_file[[#This Row],[MRP Final]]*(1-Nikes_Sales_Dataset___Working_file[[#This Row],[Cleaned Discount]]) -> 9155.96 | O54: 0 | P54: =Nikes_Sales_Dataset___Working_file[[#This Row],[Sales Price]]*Nikes_Sales_Dataset___Working_file[[#This Row],[Units Sold Filled]] -> 27467.88 | Q54: 45573 | R54: =IF(ISBLANK(Nikes_Sales_Dataset___Working_file[[#This Row],[Order_Date]]),"Unknown Date",Nikes_Sales_Dataset___Working_file[[#This Row],[Order_Date]]) -> 45573 | S54: =IF(ISNUMBER(Nikes_Sales_Dataset___Working_file[[#This Row],[Cleaned Order Date]]),TEXT(Nikes_Sales_Dataset___Working_file[[#This Row],[Cleaned Order Date]],"mmm"),"Unknown") -> Oct | T54: =IF(ISNUMBER(Nikes_Sales_Dataset___Working_file[[#This Row],[Cleaned Order Date]]),TEXT(Nikes_Sales_Dataset___Working_file[[#This Row],[Cleaned Order Date]],"yyyy"),"Unknown") -> 2024 | U54: Retail | V54: Pune | W54: Pune | X54: 2184.8
A55: 2053 | B55: =Nikes_Sales_Dataset___Working_file[[#This Row],[Order_ID]]&"_"&TEXT(Nikes_Sales_Dataset___Working_file[[#This Row],[Cleaned Order Date]],"yyyymmdd") -> 2053_20241002 | C55: Men | D55: Lifestyle | E55: Air Force 1 | F55: XL | G55: XL | H55: 3 | I55: =IF(ISBLANK(Nikes_Sales_Dataset___Working_file[[#This Row],[Units_Sold]]),IF(Nikes_Sales_Dataset___Working_file[[#This Row],[Profit]]<0,0,1),Nikes_Sales_Dataset___Working_file[[#This Row],[Units_Sold]]) -> 3 | J55: 6009.58 | K55: =IF(ISBLANK(Nikes_Sales_Dataset___Working_file[[#This Row],[MRP]]),MEDIAN(Nikes_Sales_Dataset___Working_file[[#All],[MRP]]),Nikes_Sales_Dataset___Working_file[[#This Row],[MRP]]) -> 6009.58 | M55: =IF(ISBLANK(Nikes_Sales_Dataset___Working_file[[#This Row],[Discount_Applied]]),0,Nikes_Sales_Dataset___Working_file[[#This Row],[Discount_Applied]]) -> 0 | N55: =Nikes_Sales_Dataset___Working_file[[#This Row],[MRP Final]]*(1-Nikes_Sales_Dataset___Working_file[[#This Row],[Cleaned Discount]]) -> 6009.58 | O55: 0 | P55: =Nikes_Sales_Dataset___Working_file[[#This Row],[Sales Price]]*Nikes_Sales_Dataset___Working_file[[#This Row],[Units Sold Filled]] -> 18028.74 | Q55: 45567 | R55: =IF(ISBLANK(Nikes_Sales_Dataset___Working_file[[#This Row],[Order_Date]]),"Unknown Date",Nikes_Sales_Dataset___Working_file[[#This Row],[Order_Date]]) -> 45567 | S55: =IF(ISNUMBER(Nikes_Sales_Dataset___Working_file[[#This Row],[Cleaned Order Date]]),TEXT(Nikes_Sales_Dataset___Working_file[[#This Row],[Cleaned Order Date]],"mmm"),"Unknown") -> Oct | T55: =IF(ISNUMBER(Nikes_Sales_Dataset___Working_file[[#This Row],[Cleaned Order Date]]),TEXT(Nikes_Sales_Dataset___Working_file[[#This Row],[Cleaned Order Date]],"yyyy"),"Unknown") -> 2024 | U55: Online | V55: Delhi | W55: Delhi | X55: 3384.92
A56: 2054 | B56: =Nikes_Sales_Dataset___Working_file[[#This Row],[Order_ID]]&"_"&TEXT(Nikes_Sales_Dataset___Working_file[[#This Row],[Cleaned Order Date]],"yyyymmdd") -> 2054_20250623 | C56: Women | D56: Training | E56: Flex Trainer | F56: 11 | G56: L | H56: -1 | I56: =IF(ISBLANK(Nikes_Sales_Dataset___Working_file[[#This Row],[Units_Sold]]),IF(Nikes_Sales_Dataset___Working_file[[#This Row],[Profit]]<0,0,1),Nikes_Sales_Dataset___Working_file[[#This Row],[Units_Sold]]) -> -1 | K56: =IF(ISBLANK(Nikes_Sales_Dataset___Working_file[[#This Row],[MRP]]),MEDIAN(Nikes_Sales_Dataset___Working_file[[#All],[MRP]]),Nikes_Sales_Dataset___Working_file[[#This Row],[MRP]]) -> 6110.03 | M56: =IF(ISBLANK(Nikes_Sales_Dataset___Working_file[[#This Row],[Discount_Applied]]),0,Nikes_Sales_Dataset___Working_file[[#This Row],[Discount_Applied]]) -> 0 | N56: =Nikes_Sales_Dataset___Working_file[[#This Row],[MRP Final]]*(1-Nikes_Sales_Dataset___Working_file[[#This Row],[Cleaned Discount]]) -> 6110.03 | O56: 0 | P56: =Nikes_Sales_Dataset___Working_file[[#This Row],[Sales Price]]*Nikes_Sales_Dataset___Working_file[[#This Row],[Units Sold Filled]] -> -6110.03 | Q56: 45831 | R56: =IF(ISBLANK(Nikes_Sales_Dataset___Working_file[[#This Row],[Order_Date]]),"Unknown Date",Nikes_Sales_Dataset___Working_file[[#This Row],[Order_Date]]) -> 45831 | S56: =IF(ISNUMBER(Nikes_Sales_Dataset___Working_file[[#This Row],[Cleaned Order Date]]),TEXT(Nikes_Sales_Dataset___Working_file[[#This Row],[Cleaned Order Date]],"mmm"),"Unknown") -> Jun | T56: =IF(ISNUMBER(Nikes_Sales_Dataset___Working_file[[#This Row],[Cleaned Order Date]]),TEXT(Nikes_Sales_Dataset___Working_file[[#This Row],[Cleaned Order Date]],"yyyy"),"Unknown") -> 2025 | U56: Online | V56: Mumbai | W56: Mumbai | X56: -549.76
A57: 2055 | B57: =Nikes_Sales_Dataset___Working_file[[#This Row],[Order_ID]]&"_"&TEXT(Nikes_Sales_Dataset___Working_file[[#This Row],[Cleaned Order Date]],"yyyymmdd") -> 2055_20241026 | C57: Men | D57: Basketball | E57: Kyrie Flytrap | F57: L | G57: L | I57: =IF(ISBLANK(Nikes_Sales_Dataset___Working_file[[#This Row],[Units_Sold]]),IF(Nikes_Sales_Dataset___Working_file[[#This Row],[Profit]]<0,0,1),Nikes_Sales_Dataset___Working_file[[#This Row],[Units_Sold]]) -> 0 | K57: =IF(ISBLANK(Nikes_Sales_Dataset___Working_file[[#This Row],[MRP]]),MEDIAN(Nikes_Sales_Dataset___Working_file[[#All],[MRP]]),Nikes_Sales_Dataset___Working_file[[#This Row],[MRP]]) -> 6110.03 | M57: =IF(ISBLANK(Nikes_Sales_Dataset___Working_file[[#This Row],[Discount_Applied]]),0,Nikes_Sales_Dataset___Working_file[[#This Row],[Discount_Applied]]) -> 0 | N57: =Nikes_Sales_Dataset___Working_file[[#This Row],[MRP Final]]*(1-Nikes_Sales_Dataset___Working_file[[#This Row],[Cleaned Discount]]) -> 6110.03 | O57: 0 | P57: =Nikes_Sales_Dataset___Working_file[[#This Row],[Sales Price]]*Nikes_Sales_Dataset___Working_file[[#This Row],[Units Sold Filled]] -> 0 | Q57: 45591 | R57: =IF(ISBLANK(Nikes_Sales_Dataset___Working_file[[#This Row],[Order_Date]]),"Unknown Date",Nikes_Sales_Dataset___Working_file[[#This Row],[Order_Date]]) -> 45591 | S57: =IF(ISNUMBER(Nikes_Sales_Dataset___Working_file[[#This Row],[Cleaned Order Date]]),TEXT(Nikes_Sales_Dataset___Working_file[[#This Row],[Cleaned Order Date]],"mmm"),"Unknown") -> Oct | T57: =IF(ISNUMBER(Nikes_Sales_Dataset___Working_file[[#This Row],[Cleaned Order Date]]),TEXT(Nikes_Sales_Dataset___Working_file[[#This Row],[Cleaned Order Date]],"yyyy"),"Unknown") -> 2024 | U57: Online | V57: hyderbad | W57: Hyderabad | X57: -1078.76
A58: 2056 | B58: =Nikes_Sales_Dataset___Working_file[[#This Row],[Order_ID]]&"_"&TEXT(Nikes_Sales_Dataset___Working_file[[#This Row],[Cleaned Order Date]],"yyyymmdd") -> 2056_20240531 | C58: Men | D58: Running | E58: React Infinity | F58: L | G58: L | H58: 3 | I58: =IF(ISBLANK(Nikes_Sales_Dataset___Working_file[[#This Row],[Units_Sold]]),IF(Nikes_Sales_Dataset___Working_file[[#This Row],[Profit]]<0,0,1),Nikes_Sales_Dataset___Working_file[[#This Row],[Units_Sold]]) -> 3 | K58: =IF(ISBLANK(Nikes_Sales_Dataset___Working_file[[#This Row],[MRP]]),MEDIAN(Nikes_Sales_Dataset___Working_file[[#All],[MRP]]),Nikes_Sales_Dataset___Working_file[[#This Row],[MRP]]) -> 6110.03 | M58: =IF(ISBLANK(Nikes_Sales_Dataset___Working_file[[#This Row],[Discount_Applied]]),0,Nikes_Sales_Dataset___Working_file[[#This Row],[Discount_Applied]]) -> 0 | N58: =Nikes_Sales_Dataset___Working_file[[#This Row],[MRP Final]]*(1-Nikes_Sales_Dataset___Working_file[[#This Row],[Cleaned Discount]]) -> 6110.03 | O58: 0 | P58: =Nikes_Sales_Dataset___Working_file[[#This Row],[Sales Price]]*Nikes_Sales_Dataset___Working_file[[#This Row],[Units Sold Filled]] -> 18330.09 | Q58: 45443 | R58: =IF(ISBLANK(Nikes_Sales_Dataset___Working_file[[#This Row],[Order_Date]]),"Unknown Date",Nikes_Sales_Dataset___Working_file[[#This Row],[Order_Date]]) -> 45443 | S58: =IF(ISNUMBER(Nikes_Sales_Dataset___Working_file[[#This Row],[Cleaned Order Date]]),TEXT(Nikes_Sales_Dataset___Working_file[[#This Row],[Cleaned Order Date]],"mmm"),"Unknown") -> May | T58: =IF(ISNUMBER(Nikes_Sales_Dataset___Working_file[[#This Row],[Cleaned Order Date]]),TEXT(Nikes_Sales_Dataset___Working_file[[#This Row],[Cleaned Order Date]],"yyyy"),"Unknown") -> 2024 | U58: Retail | V58: Bangalore | W58: Bangalore | X58: -244.44
A59: 2048 | B59: =Nikes_Sales_Dataset___Working_file[[#This Row],[Order_ID]]&"_"&TEXT(Nikes_Sales_Dataset___Working_file[[#This Row],[Cleaned Order Date]],"yyyymmdd") -> 2048_20240914 | C59: Men | D59: Lifestyle | E59: Waffle One | F59: M | G59: M | H59: 3 | I59: =IF(ISBLANK(Nikes_Sales_Dataset___Working_file[[#This Row],[Units_Sold]]),IF(Nikes_Sales_Dataset___Working_file[[#This Row],[Profit]]<0,0,1),Nikes_Sales_Dataset___Working_file[[#This Row],[Units_Sold]]) -> 3 | J59: 6216.29 | K59: =IF(ISBLANK(Nikes_Sales_Dataset___Working_file[[#This Row],[MRP]]),MEDIAN(Nikes_Sales_Dataset___Working_file[[#All],[MRP]]),Nikes_Sales_Dataset___Working_file[[#This Row],[MRP]]) -> 6216.29 | L59: 0.94 | M59: =IF(ISBLANK(Nikes_Sales_Dataset___Working_file[[#This Row],[Discount_Applied]]),0,Nikes_Sales_Dataset___Working_file[[#This Row],[Discount_Applied]]) -> 0.94 | N59: =Nikes_Sales_Dataset___Working_file[[#This Row],[MRP Final]]*(1-Nikes_Sales_Dataset___Working_file[[#This Row],[Cleaned Discount]]) -> 372.9774 | O59: 1118.93 | P59: =Nikes_Sales_Dataset___Working_file[[#This Row],[Sales Price]]*Nikes_Sales_Dataset___Working_file[[#This Row],[Units Sold Filled]] -> 1118.9322 | Q59: 45549 | R59: =IF(ISBLANK(Nikes_Sales_Dataset___Working_file[[#This Row],[Order_Date]]),"Unknown Date",Nikes_Sales_Dataset___Working_file[[#This Row],[Order_Date]]) -> 45549 | S59: =IF(ISNUMBER(Nikes_Sales_Dataset___Working_file[[#This Row],[Cleaned Order Date]]),TEXT(Nikes_Sales_Dataset___Working_file[[#This Row],[Cleaned Order Date]],"mmm"),"Unknown") -> Sep | T59: =IF(ISNUMBER(Nikes_Sales_Dataset___Working_file[[#This Row],[Cleaned Order Date]]),TEXT(Nikes_Sales_Dataset___Working_file[[#This Row],[Cleaned Order Date]],"yyyy"),"Unknown") -> 2024 | U59: Online | V59: Mumbai | W59: Mumbai | X59: -642.02
A60: 2058 | B60: =Nikes_Sales_Dataset___Working_file[[#This Row],[Order_ID]]&"_"&TEXT(Nikes_Sales_Dataset___Working_file[[#This Row],[Cleaned Order Date]],"yyyymmdd") -> 2058_Unknown Date | C60: Women | D60: Training | E60: Flex Trainer | F60: 11 | G60: L | I60: =IF(ISBLANK(Nikes_Sales_Dataset___Working_file[[#This Row],[Units_Sold]]),IF(Nikes_Sales_Dataset___Working_file[[#This Row],[Profit]]<0,0,1),Nikes_Sales_Dataset___Working_file[[#This Row],[Units_Sold]]) -> 1 | J60: 4985.92 | K60: =IF(ISBLANK(Nikes_Sales_Dataset___Working_file[[#This Row],[MRP]]),MEDIAN(Nikes_Sales_Dataset___Working_file[[#All],[MRP]]),Nikes_Sales_Dataset___Working_file[[#This Row],[MRP]]) -> 4985.92 | M60: =IF(ISBLANK(Nikes_Sales_Dataset___Working_file[[#This Row],[Discount_Applied]]),0,Nikes_Sales_Dataset___Working_file[[#This Row],[Discount_Applied]]) -> 0 | N60: =Nikes_Sales_Dataset___Working_file[[#This Row],[MRP Final]]*(1-Nikes_Sales_Dataset___Working_file[[#This Row],[Cleaned Discount]]) -> 4985.92 | O60: 0 | P60: =Nikes_Sales_Dataset___Working_file[[#This Row],[Sales Price]]*Nikes_Sales_Dataset___Working_file[[#This Row],[Units Sold Filled]] -> 4985.92 | R60: =IF(ISBLANK(Nikes_Sales_Dataset___Working_file[[#This Row],[Order_Date]]),"Unknown Date",Nikes_Sales_Dataset___Working_file[[#This Row],[Order_Date]]) -> Unknown Date | S60: =IF(ISNUMBER(Nikes_Sales_Dataset___Working_file[[#This Row],[Cleaned Order Date]]),TEXT(Nikes_Sales_Dataset___Working_file[[#This Row],[Cleaned Order Date]],"mmm"),"Unknown") -> Unknown | T60: =IF(ISNUMBER(Nikes_Sales_Dataset___Working_file[[#This Row],[Cleaned Order Date]]),TEXT(Nikes_Sales_Dataset___Working_file[[#This Row],[Cleaned Order Date]],"yyyy"),"Unknown") -> Unknown | U60: Online | V60: Kolkata | W60: Kolkata | X60: 361.54
A61: 2059 | B61: =Nikes_Sales_Dataset___Working_file[[#This Row],[Order_ID]]&"_"&TEXT(Nikes_Sales_Dataset___Working_file[[#This Row],[Cleaned Order Date]],"yyyymmdd") -> 2059_20231227 | C61: Kids | D61: Soccer | E61: Phantom GT | G61: M | H61: -1 | I61: =IF(ISBLANK(Nikes_Sales_Dataset___Working_file[[#This Row],[Units_Sold]]),IF(Nikes_Sales_Dataset___Working_file[[#This Row],[Profit]]<0,0,1),Nikes_Sales_Dataset___Working_file[[#This Row],[Units_Sold]]) -> -1 | J61: 9507.54 | K61: =IF(ISBLANK(Nikes_Sales_Dataset___Working_file[[#This Row],[MRP]]),MEDIAN(Nikes_Sales_Dataset___Working_file[[#All],[MRP]]),Nikes_Sales_Dataset___Working_file[[#This Row],[MRP]]) -> 9507.54 | M61: =IF(ISBLANK(Nikes_Sales_Dataset___Working_file[[#This Row],[Discount_Applied]]),0,Nikes_Sales_Dataset___Working_file[[#This Row],[Discount_Applied]]) -> 0 | N61: =Nikes_Sales_Dataset___Working_file[[#This Row],[MRP Final]]*(1-Nikes_Sales_Dataset___Working_file[[#This Row],[Cleaned Discount]]) -> 9507.54 | O61: 0 | P61: =Nikes_Sales_Dataset___Working_file[[#This Row],[Sales Price]]*Nikes_Sales_Dataset___Working_file[[#This Row],[Units Sold Filled]] -> -9507.54 | Q61: 45287 | R61: =IF(ISBLANK(Nikes_Sales_Dataset___Working_file[[#This Row],[Order_Date]]),"Unknown Date",Nikes_Sales_Dataset___Working_file[[#This Row],[Order_Date]]) -> 45287 | S61: =IF(ISNUMBER(Nikes_Sales_Dataset___Working_file[[#This Row],[Cleaned Order Date]]),TEXT(Nikes_Sales_Dataset___Working_file[[#This Row],[Cleaned Order Date]],"mmm"),"Unknown") -> Dec | T61: =IF(ISNUMBER(Nikes_Sales_Dataset___Working_file[[#This Row],[Cleaned Order Date]]),TEXT(Nikes_Sales_Dataset___Working_file[[#This Row],[Cleaned Order Date]],"yyyy"),"Unknown") -> 2023 | U61: Retail | V61: Delhi | W61: Delhi | X61: 291.28
A62: 2060 | B62: =Nikes_Sales_Dataset___Working_file[[#This Row],[Order_ID]]&"_"&TEXT(Nikes_Sales_Dataset___Working_file[[#This Row],[Cleaned Order Date]],"yyyymmdd") -> 2060_20240711 | C62: Men | D62: Lifestyle | E62: Waffle One | F62: L | G62: L | H62: 2 | I62: =IF(ISBLANK(Nikes_Sales_Dataset___Working_file[[#This Row],[Units_Sold]]),IF(Nikes_Sales_Dataset___Working_file[[#This Row],[Profit]]<0,0,1),Nikes_Sales_Dataset___Working_file[[#This Row],[Units_Sold]]) -> 2 | J62: 7979.26 | K62: =IF(ISBLANK(Nikes_Sales_Dataset___Working_file[[#This Row],[MRP]]),MEDIAN(Nikes_Sales_Dataset___Working_file[[#All],[MRP]]),Nikes_Sales_Dataset___Working_file[[#This Row],[MRP]]) -> 7979.26 | M62: =IF(ISBLANK(Nikes_Sales_Dataset___Working_file[[#This Row],[Discount_Applied]]),0,Nikes_Sales_Dataset___Working_file[[#This Row],[Discount_Applied]]) -> 0 | N62: =Nikes_Sales_Dataset___Working_file[[#This Row],[MRP Final]]*(1-Nikes_Sales_Dataset___Working_file[[#This Row],[Cleaned Discount]]) -> 7979.26 | O62: 0 | P62: =Nikes_Sales_Dataset___Working_file[[#This Row],[Sales Price]]*Nikes_Sales_Dataset___Working_file[[#This Row],[Units Sold Filled]] -> 15958.52 | Q62: 45484 | R62: =IF(ISBLANK(Nikes_Sales_Dataset___Working_file[[#This Row],[Order_Date]]),"Unknown Date",Nikes_Sales_Dataset___Working_file[[#This Row],[Order_Date]]) -> 45484 | S62: =IF(ISNUMBER(Nikes_Sales_Dataset___Working_file[[#This Row],[Cleaned Order Date]]),TEXT(Nikes_Sales_Dataset___Working_file[[#This Row],[Cleaned Order Date]],"mmm"),"Unknown") -> Jul | T62: =IF(ISNUMBER(Nikes_Sales_Dataset___Working_file[[#This Row],[Cleaned Order Date]]),TEXT(Nikes_Sales_Dataset___Working_file[[#This Row],[Cleaned Order Date]],"yyyy"),"Unknown") -> 2024 | U62: Online | V62: bengaluru | W62: Bangalore | X62: 2821.59
A63: 2061 | B63: =Nikes_Sales_Dataset___Working_file[[#This Row],[Order_ID]]&"_"&TEXT(Nikes_Sales_Dataset___Working_file[[#This Row],[Cleaned Order Date]],"yyyymmdd") -> 2061_20240910 | C63: Women | D63: Basketball | E63: LeBron 20 | F63: L | G63: L | I63: =IF(ISBLANK(Nikes_Sales_Dataset___Working_file[[#This Row],[Units_Sold]]),IF(Nikes_Sales_Dataset___Working_file[[#This Row],[Profit]]<0,0,1),Nikes_Sales_Dataset___Working_file[[#This Row],[Units_Sold]]) -> 0 | K63: =IF(ISBLANK(Nikes_Sales_Dataset___Working_file[[#This Row],[MRP]]),MEDIAN(Nikes_Sales_Dataset___Working_file[[#All],[MRP]]),Nikes_Sales_Dataset___Working_file[[#This Row],[MRP]]) -> 6110.03 | M63: =IF(ISBLANK(Nikes_Sales_Dataset___Working_file[[#This Row],[Discount_Applied]]),0,Nikes_Sales_Dataset___Working_file[[#This Row],[Discount_Applied]]) -> 0 | N63: =Nikes_Sales_Dataset___Working_file[[#This Row],[MRP Final]]*(1-Nikes_Sales_Dataset___Working_file[[#This Row],[Cleaned Discount]]) -> 6110.03 | O63: 0 | P63: =Nikes_Sales_Dataset___Working_file[[#This Row],[Sales Price]]*Nikes_Sales_Dataset___Working_file[[#This Row],[Units Sold Filled]] -> 0 | Q63: 45545 | R63: =IF(ISBLANK(Nikes_Sales_Dataset___Working_file[[#This Row],[Order_Date]]),"Unknown Date",Nikes_Sales_Dataset___Working_file[[#This Row],[Order_Date]]) -> 45545 | S63: =IF(ISNUMBER(Nikes_Sales_Dataset___Working_file[[#This Row],[Cleaned Order Date]]),TEXT(Nikes_Sales_Dataset___Working_file[[#This Row],[Cleaned Order Date]],"mmm"),"Unknown") -> Sep | T63: =IF(ISNUMBER(Nikes_Sales_Dataset___Working_file[[#This Row],[Cleaned Order Date]]),TEXT(Nikes_Sales_Dataset___Working_file[[#This Row],[Cleaned Order Date]],"yyyy"),"Unknown") -> 2024 | U63: Online | V63: Mumbai | W63: Mumbai | X63: -501.68
A64: 2062 | B64: =Nikes_Sales_Dataset___Working_file[[#This Row],[Order_ID]]&"_"&TEXT(Nikes_Sales_Dataset___Working_file[[#This Row],[Cleaned Order Date]],"yyyymmdd") -> 2062_20250606 | C64: Men | D64: Basketball | E64: Air Jordan | G64: M | H64: 2 | I64: =IF(ISBLANK(Nikes_Sales_Dataset___Working_file[[#This Row],[Units_Sold]]),IF(Nikes_Sales_Dataset___Working_file[[#This Row],[Profit]]<0,0,1),Nikes_Sales_Dataset___Working_file[[#This Row],[Units_Sold]]) -> 2 | K64: =IF(ISBLANK(Nikes_Sales_Dataset___Working_file[[#This Row],[MRP]]),MEDIAN(Nikes_Sales_Dataset___Working_file[[#All],[MRP]]),Nikes_Sales_Dataset___Working_file[[#This Row],[MRP]]) -> 6110.03 | M64: =IF(ISBLANK(Nikes_Sales_Dataset___Working_file[[#This Row],[Discount_Applied]]),0,Nikes_Sales_Dataset___Working_file[[#This Row],[Discount_Applied]]) -> 0 | N64: =Nikes_Sales_Dataset___Working_file[[#This Row],[MRP Final]]*(1-Nikes_Sales_Dataset___Working_file[[#This Row],[Cleaned Discount]]) -> 6110.03 | O64: 0 | P64: =Nikes_Sales_Dataset___Working_file[[#This Row],[Sales Price]]*Nikes_Sales_Dataset___Working_file[[#This Row],[Units Sold Filled]] -> 12220.06 | Q64: 45814 | R64: =IF(ISBLANK(Nikes_Sales_Dataset___Working_file[[#This Row],[Order_Date]]),"Unknown Date",Nikes_Sales_Dataset___Working_file[[#This Row],[Order_Date]]) -> 45814 | S64: =IF(ISNUMBER(Nikes_Sales_Dataset___Working_file[[#This Row],[Cleaned Order Date]]),TEXT(Nikes_Sales_Dataset___Working_file[[#This Row],[Cleaned Order Date]],"mmm"),"Unknown") -> Jun | T64: =IF(ISNUMBER(Nikes_Sales_Dataset___Working_file[[#This Row],[Cleaned Order Date]]),TEXT(Nikes_Sales_Dataset___Working_file[[#This Row],[Cleaned Order Date]],"yyyy"),"Unknown") -> 2025 | U64: Online | V64: Bangalore | W64: Bangalore | X64: 1823.91
A65: 2063 | B65: =Nikes_Sales_Dataset___Working_file[[#This Row],[Order_ID]]&"_"&TEXT(Nikes_Sales_Dataset___Working_file[[#This Row],[Cleaned Order Date]],"yyyymmdd") -> 2063_20240906 | C65: Women | D65: Basketball | E65: Air Jordan | F65: M | G65: M | H65: 1 | I65: =IF(ISBLANK(Nikes_Sales_Dataset___Working_file[[#This Row],[Units_Sold]]),IF(Nikes_Sales_Dataset___Working_file[[#This Row],[Profit]]<0,0,1),Nikes_Sales_Dataset___Working_file[[#This Row],[Units_Sold]]) -> 1 | J65: 9751 | K65: =IF(ISBLANK(Nikes_Sales_Dataset___Working_file[[#This Row],[MRP]]),MEDIAN(Nikes_Sales_Dataset___Working_file[[#All],[MRP]]),Nikes_Sales_Dataset___Working_file[[#This Row],[MRP]]) -> 9751 | L65: 0.16 | M65: =IF(ISBLANK(Nikes_Sales_Dataset___Working_file[[#This Row],[Discount_Applied]]),0,Nikes_Sales_Dataset___Working_file[[#This Row],[Discount_Applied]]) -> 0.16 | N65: =Nikes_Sales_Dataset___Working_file[[#This Row],[MRP Final]]*(1-Nikes_Sales_Dataset___Working_file[[#This Row],[Cleaned Discount]]) -> 8190.84 | O65: 8190.84 | P65: =Nikes_Sales_Dataset___Working_file[[#This Row],[Sales Price]]*Nikes_Sales_Dataset___Working_file[[#This Row],[Units Sold Filled]] -> 8190.84 | Q65: 45541 | R65: =IF(ISBLANK(Nikes_Sales_Dataset___Working_file[[#This Row],[Order_Date]]),"Unknown Date",Nikes_Sales_Dataset___Working_file[[#This Row],[Order_Date]]) -> 45541 | S65: =IF(ISNUMBER(Nikes_Sales_Dataset___Working_file[[#This Row],[Cleaned Order Date]]),TEXT(Nikes_Sales_Dataset___Working_file[[#This Row],[Cleaned Order Date]],"mmm"),"Unknown") -> Sep | T65: =IF(ISNUMBER(Nikes_Sales_Dataset___Working_file[[#This Row],[Cleaned Order Date]]),TEXT(Nikes_Sales_Dataset___Working_file[[#This Row],[Cleaned Order Date]],"yyyy"),"Unknown") -> 2024 | U65: Retail | V65: Pune | W65: Pune | X65: 1130.31
A66: 2064 | B66: =Nikes_Sales_Dataset___Working_file[[#This Row],[Order_ID]]&"_"&TEXT(Nikes_Sales_Dataset___Working_file[[#This Row],[Cleaned Order Date]],"yyyymmdd") -> 2064_20250302 | C66: Kids | D66: Running | E66: React Infinity | F66: L | G66: L | H66: 2 | I66: =IF(ISBLANK(Nikes_Sales_Dataset___Working_file[[#This Row],[Units_Sold]]),IF(Nikes_Sales_Dataset___Working_file[[#This Row],[Profit]]<0,0,1),Nikes_Sales_Dataset___Working_file[[#This Row],[Units_Sold]]) -> 2 | J66: 7557.71 | K66: =IF(ISBLANK(Nikes_Sales_Dataset___Working_file[[#This Row],[MRP]]),MEDIAN(Nikes_Sales_Dataset___Working_file[[#All],[MRP]]),Nikes_Sales_Dataset___Working_file[[#This Row],[MRP]]) -> 7557.71 | M66: =IF(ISBLANK(Nikes_Sales_Dataset___Working_file[[#This Row],[Discount_Applied]]),0,Nikes_Sales_Dataset___Working_file[[#This Row],[Discount_Applied]]) -> 0 | N66: =Nikes_Sales_Dataset___Working_file[[#This Row],[MRP Final]]*(1-Nikes_Sales_Dataset___Working_file[[#This Row],[Cleaned Discount]]) -> 7557.71 | O66: 0 | P66: =Nikes_Sales_Dataset___Working_file[[#This Row],[Sales Price]]*Nikes_Sales_Dataset___Working_file[[#This Row],[Units Sold Filled]] -> 15115.42 | Q66: 45718 | R66: =IF(ISBLANK(Nikes_Sales_Dataset___Working_file[[#This Row],[Order_Date]]),"Unknown Date",Nikes_Sales_Dataset___Working_file[[#This Row],[Order_Date]]) -> 45718 | S66: =IF(ISNUMBER(Nikes_Sales_Dataset___Working_file[[#This Row],[Cleaned Order Date]]),TEXT(Nikes_Sales_Dataset___Working_file[[#This Row],[Cleaned Order Date]],"mmm"),"Unknown") -> Mar | T66: =IF(ISNUMBER(Nikes_Sales_Dataset___Working_file[[#This Row],[Cleaned Order Date]]),TEXT(Nikes_Sales_Dataset___Working_file[[#This Row],[Cleaned Order Date]],"yyyy"),"Unknown") -> 2025 | U66: Online | V66: Bangalore | W66: Bangalore | X66: 3277.44
A67: 2065 | B67: =Nikes_Sales_Dataset___Working_file[[#This Row],[Order_ID]]&"_"&TEXT(Nikes_Sales_Dataset___Working_file[[#This Row],[Cleaned Order Date]],"yyyymmdd") -> 2065_20240211 | C67: Women | D67: Lifestyle | E67: Waffle One | F67: 10 | G67: L | I67: =IF(ISBLANK(Nikes_Sales_Dataset___Working_file[[#This Row],[Units_Sold]]),IF(Nikes_Sales_Dataset___Working_file[[#This Row],[Profit]]<0,0,1),Nikes_Sales_Dataset___Working_file[[#This Row],[Units_Sold]]) -> 1 | K67: =IF(ISBLANK(Nikes_Sales_Dataset___Working_file[[#This Row],[MRP]]),MEDIAN(Nikes_Sales_Dataset___Working_file[[#All],[MRP]]),Nikes_Sales_Dataset___Working_file[[#This Row],[MRP]]) -> 6110.03 | L67: 0.78 | M67: =IF(ISBLANK(Nikes_Sales_Dataset___Working_file[[#This Row],[Discount_Applied]]),0,Nikes_Sales_Dataset___Working_file[[#This Row],[Discount_Applied]]) -> 0.78 | N67: =Nikes_Sales_Dataset___Working_file[[#This Row],[MRP Final]]*(1-Nikes_Sales_Dataset___Working_file[[#This Row],[Cleaned Discount]]) -> 1344.2066 | O67: 0 | P67: =Nikes_Sales_Dataset___Working_file[[#This Row],[Sales Price]]*Nikes_Sales_Dataset___Working_file[[#This Row],[Units Sold Filled]] -> 1344.2066 | Q67: 45333 | R67: =IF(ISBLANK(Nikes_Sales_Dataset___Working_file[[#This Row],[Order_Date]]),"Unknown Date",Nikes_Sales_Dataset___Working_file[[#This Row],[Order_Date]]) -> 45333 | S67: =IF(ISNUMBER(Nikes_Sales_Dataset___Working_file[[#This Row],[Cleaned Order Date]]),TEXT(Nikes_Sales_Dataset___Working_file[[#This Row],[Cleaned Order Date]],"mmm"),"Unknown") -> Feb | T67: =IF(ISNUMBER(Nikes_Sales_Dataset___Working_file[[#This Row],[Cleaned Order Date]]),TEXT(Nikes_Sales_Dataset___Working_file[[#This Row],[Cleaned Order Date]],"yyyy"),"Unknown") -> 2024 | U67: Retail | V67: Hyd | W67: Hyderabad | X67: 21.58
A68: 2066 | B68: =Nikes_Sales_Dataset___Working_file[[#This Row],[Order_ID]]&"_"&TEXT(Nikes_Sales_Dataset___Working_file[[#This Row],[Cleaned Order Date]],"yyyymmdd") -> 2066_20241210 | C68: Men | D68: Soccer | E68: Phantom GT | F68: XL | G68: XL | H68: -1 | I68: =IF(ISBLANK(Nikes_Sales_Dataset___Working_file[[#This Row],[Units_Sold]]),IF(Nikes_Sales_Dataset___Working_file[[#This Row],[Profit]]<0,0,1),Nikes_Sales_Dataset___Working_file[[#This Row],[Units_Sold]]) -> -1 | J68: 5259.05 | K68: =IF(ISBLANK(Nikes_Sales_Dataset___Working_file[[#This Row],[MRP]]),MEDIAN(Nikes_Sales_Dataset___Working_file[[#All],[MRP]]),Nikes_Sales_Dataset___Working_file[[#This Row],[MRP]]) -> 5259.05 | M68: =IF(ISBLANK(Nikes_Sales_Dataset___Working_file[[#This Row],[Discount_Applied]]),0,Nikes_Sales_Dataset___Working_file[[#This Row],[Discount_Applied]]) -> 0 | N68: =Nikes_Sales_Dataset___Working_file[[#This Row],[MRP Final]]*(1-Nikes_Sales_Dataset___Working_file[[#This Row],[Cleaned Discount]]) -> 5259.05 | O68: 0 | P68: =Nikes_Sales_Dataset___Working_file[[#This Row],[Sales Price]]*Nikes_Sales_Dataset___Working_file[[#This Row],[Units Sold Filled]] -> -5259.05 | Q68: 45636 | R68: =IF(ISBLANK(Nikes_Sales_Dataset___Working_file[[#This Row],[Order_Date]]),"Unknown Date",Nikes_Sales_Dataset___Working_file[[#This Row],[Order_Date]]) -> 45636 | S68: =IF(ISNUMBER(Nikes_Sales_Dataset___Working_file[[#This Row],[Cleaned Order Date]]),TEXT(Nikes_Sales_Dataset___Working_file[[#This Row],[Cleaned Order Date]],"mmm"),"Unknown") -> Dec | T68: =IF(ISNUMBER(Nikes_Sales_Dataset___Working_file[[#This Row],[Cleaned Order Date]]),TEXT(Nikes_Sales_Dataset___Working_file[[#This Row],[Cleaned Order Date]],"yyyy"),"Unknown") -> 2024 | U68: Online | V68: Mumbai | W68: Mumbai | X68: 1022.82
A69: 2067 | B69: =Nikes_Sales_Dataset___Working_file[[#This Row],[Order_ID]]&"_"&TEXT(Nikes_Sales_Dataset___Working_file[[#This Row],[Cleaned Order Date]],"yyyymmdd") -> 2067_20250506 | C69: Kids | D69: Basketball | E69: LeBron 20 | F69: L | G69: L | H69: 4 | I69: =IF(ISBLANK(Nikes_Sales_Dataset___Working_file[[#This Row],[Units_Sold]]),IF(Nikes_Sales_Dataset___Working_file[[#This Row],[Profit]]<0,0,1),Nikes_Sales_Dataset___Working_file[[#This Row],[Units_Sold]]) -> 4 | J69: 3588.38 | K69: =IF(ISBLANK(Nikes_Sales_Dataset___Working_file[[#This Row],[MRP]]),MEDIAN(Nikes_Sales_Dataset___Working_file[[#All],[MRP]]),Nikes_Sales_Dataset___Working_file[[#This Row],[MRP]]) -> 3588.38 | M69: =IF(ISBLANK(Nikes_Sales_Dataset___Working_file[[#This Row],[Discount_Applied]]),0,Nikes_Sales_Dataset___Working_file[[#This Row],[Discount_Applied]]) -> 0 | N69: =Nikes_Sales_Dataset___Working_file[[#This Row],[MRP Final]]*(1-Nikes_Sales_Dataset___Working_file[[#This Row],[Cleaned Discount]]) -> 3588.38 | O69: 0 | P69: =Nikes_Sales_Dataset___Working_file[[#This Row],[Sales Price]]*Nikes_Sales_Dataset___Working_file[[#This Row],[Units Sold Filled]] -> 14353.52 | Q69: 45783 | R69: =IF(ISBLANK(Nikes_Sales_Dataset___Working_file[[#This Row],[Order_Date]]),"Unknown Date",Nikes_Sales_Dataset___Working_file[[#This Row],[Order_Date]]) -> 45783 | S69: =IF(ISNUMBER(Nikes_Sales_Dataset___Working_file[[#This Row],[Cleaned Order Date]]),TEXT(Nikes_Sales_Dataset___Working_file[[#This Row],[Cleaned Order Date]],"mmm"),"Unknown") -> May | T69: =IF(ISNUMBER(Nikes_Sales_Dataset___Working_file[[#This Row],[Cleaned Order Date]]),TEXT(Nikes_Sales_Dataset___Working_file[[#This Row],[Cleaned Order Date]],"yyyy"),"Unknown") -> 2025 | U69: Online | V69: Kolkata | W69: Kolkata | X69: 161.5
A70: 2068 | B70: =Nikes_Sales_Dataset___Working_file[[#This Row],[Order_ID]]&"_"&TEXT(Nikes_Sales_Dataset___Working_file[[#This Row],[Cleaned Order Date]],"yyyymmdd") -> 2068_20241205 | C70: Men | D70: Running | E70: Free RN | G70: M | H70: 4 | I70: =IF(ISBLANK(Nikes_Sales_Dataset___Working_file[[#This Row],[Units_Sold]]),IF(Nikes_Sales_Dataset___Working_file[[#This Row],[Profit]]<0,0,1),Nikes_Sales_Dataset___Working_file[[#This Row],[Units_Sold]]) -> 4 | J70: 2553.29 | K70: =IF(ISBLANK(Nikes_Sales_Dataset___Working_file[[#This Row],[MRP]]),MEDIAN(Nikes_Sales_Dataset___Working_file[[#All],[MRP]]),Nikes_Sales_Dataset___Working_file[[#This Row],[MRP]]) -> 2553.29 | M70: =IF(ISBLANK(Nikes_Sales_Dataset___Working_file[[#This Row],[Discount_Applied]]),0,Nikes_Sales_Dataset___Working_file[[#This Row],[Discount_Applied]]) -> 0 | N70: =Nikes_Sales_Dataset___Working_file[[#This Row],[MRP Final]]*(1-Nikes_Sales_Dataset___Working_file[[#This Row],[Cleaned Discount]]) -> 2553.29 | O70: 0 | P70: =Nikes_Sales_Dataset___Working_file[[#This Row],[Sales Price]]*Nikes_Sales_Dataset___Working_file[[#This Row],[Units Sold Filled]] -> 10213.16 | Q70: 45631 | R70: =IF(ISBLANK(Nikes_Sales_Dataset___Working_file[[#This Row],[Order_Date]]),"Unknown Date",Nikes_Sales_Dataset___Working_file[[#This Row],[Order_Date]]) -> 45631 | S70: =IF(ISNUMBER(Nikes_Sales_Dataset___Working_file[[#This Row],[Cleaned Order Date]]),TEXT(Nikes_Sales_Dataset___Working_file[[#This Row],[Cleaned Order Date]],"mmm"),"Unknown") -> Dec | T70: =IF(ISNUMBER(Nikes_Sales_Dataset___Working_file[[#This Row],[Cleaned Order Date]]),TEXT(Nikes_Sales_Dataset___Working_file[[#This Row],[Cleaned Order Date]],"yyyy"),"Unknown") -> 2024 | U70: Retail | V70: Mumbai | W70: Mumbai | X70: 984.9
A71: 2069 | B71: =Nikes_Sales_Dataset___Working_file[[#This Row],[Order_ID]]&"_"&TEXT(Nikes_Sales_Dataset___Working_file[[#This Row],[Cleaned Order Date]],"yyyymmdd") -> 2069_20250714 | C71: Women | D71: Training | E71: SuperRep Go | G71: M | I71: =IF(ISBLANK(Nikes_Sales_Dataset___Working_file[[#This Row],[Units_Sold]]),IF(Nikes_Sales_Dataset___Working_file[[#This Row],[Profit]]<0,0,1),Nikes_Sales_Dataset___Working_file[[#This Row],[Units_Sold]]) -> 1 | J71: 7502.24 | K71: =IF(ISBLANK(Nikes_Sales_Dataset___Working_file[[#This Row],[MRP]]),MEDIAN(Nikes_Sales_Dataset___Working_file[[#All],[MRP]]),Nikes_Sales_Dataset___Working_file[[#This Row],[MRP]]) -> 7502.24 | M71: =IF(ISBLANK(Nikes_Sales_Dataset___Working_file[[#This Row],[Discount_Applied]]),0,Nikes_Sales_Dataset___Working_file[[#This Row],[Discount_Applied]]) -> 0 | N71: =Nikes_Sales_Dataset___Working_file[[#This Row],[MRP Final]]*(1-Nikes_Sales_Dataset___Working_file[[#This Row],[Cleaned Discount]]) -> 7502.24 | O71: 0 | P71: =Nikes_Sales_Dataset___Working_file[[#This Row],[Sales Price]]*Nikes_Sales_Dataset___Working_file[[#This Row],[Units Sold Filled]] -> 7502.24 | Q71: 45852 | R71: =IF(ISBLANK(Nikes_Sales_Dataset___Working_file[[#This Row],[Order_Date]]),"Unknown Date",Nikes_Sales_Dataset___Working_file[[#This Row],[Order_Date]]) -> 45852 | S71: =IF(ISNUMBER(Nikes_Sales_Dataset___Working_file[[#This Row],[Cleaned Order Date]]),TEXT(Nikes_Sales_Dataset___Working_file[[#This Row],[Cleaned Order Date]],"mmm"),"Unknown") -> Jul | T71: =IF(ISNUMBER(Nikes_Sales_Dataset___Working_file[[#This Row],[Cleaned Order Date]]),TEXT(Nikes_Sales_Dataset___Working_file[[#This Row],[Cleaned Order Date]],"yyyy"),"Unknown") -> 2025 | U71: Online | V71: Pune | W71: Pune | X71: 3554.58
A72: 2070 | B72: =Nikes_Sales_Dataset___Working_file[[#This Row],[Order_ID]]&"_"&TEXT(Nikes_Sales_Dataset___Working_file[[#This Row],[Cleaned Order Date]],"yyyymmdd") -> 2070_Unknown Date | C72: Kids | D72: Running | E72: React Infinity | F72: L | G72: L | I72: =IF(ISBLANK(Nikes_Sales_Dataset___Working_file[[#This Row],[Units_Sold]]),IF(Nikes_Sales_Dataset___Working_file[[#This Row],[Profit]]<0,0,1),Nikes_Sales_Dataset___Working_file[[#This Row],[Units_Sold]]) -> 1 | K72: =IF(ISBLANK(Nikes_Sales_Dataset___Working_file[[#This Row],[MRP]]),MEDIAN(Nikes_Sales_Dataset___Working_file[[#All],[MRP]]),Nikes_Sales_Dataset___Working_file[[#This Row],[MRP]]) -> 6110.03 | M72: =IF(ISBLANK(Nikes_Sales_Dataset___Working_file[[#This Row],[Discount_Applied]]),0,Nikes_Sales_Dataset___Working_file[[#This Row],[Discount_Applied]]) -> 0 | N72: =Nikes_Sales_Dataset___Working_file[[#This Row],[MRP Final]]*(1-Nikes_Sales_Dataset___Working_file[[#This Row],[Cleaned Discount]]) -> 6110.03 | O72: 0 | P72: =Nikes_Sales_Dataset___Working_file[[#This Row],[Sales Price]]*Nikes_Sales_Dataset___Working_file[[#This Row],[Units Sold Filled]] -> 6110.03 | R72: =IF(ISBLANK(Nikes_Sales_Dataset___Working_file[[#This Row],[Order_Date]]),"Unknown Date",Nikes_Sales_Dataset___Working_file[[#This Row],[Order_Date]]) -> Unknown Date | S72: =IF(ISNUMBER(Nikes_Sales_Dataset___Working_file[[#This Row],[Cleaned Order Date]]),TEXT(Nikes_Sales_Dataset___Working_file[[#This Row],[Cleaned Order Date]],"mmm"),"Unknown") -> Unknown | T72: =IF(ISNUMBER(Nikes_Sales_Dataset___Working_file[[#This Row],[Cleaned Order Date]]),TEXT(Nikes_Sales_Dataset___Working_file[[#This Row],[Cleaned Order Date]],"yyyy"),"Unknown") -> Unknown | U72: Retail | V72: Mumbai | W72: Mumbai | X72: 1112.43
A73: 2071 | B73: =Nikes_Sales_Dataset___Working_file[[#This Row],[Order_ID]]&"_"&TEXT(Nikes_Sales_Dataset___Working_file[[#This Row],[Cleaned Order Date]],"yyyymmdd") -> 2071_20250112 | C73: Kids | D73: Lifestyle | E73: Blazer Mid | F73: M | G73: M | H73: 3 | I73: =IF(ISBLANK(Nikes_Sales_Dataset___Working_file[[#This Row],[Units_Sold]]),IF(Nikes_Sales_Dataset___Working_file[[#This Row],[Profit]]<0,0,1),Nikes_Sales_Dataset___Working_file[[#This Row],[Units_Sold]]) -> 3 | J73: 7849.81 | K73: =IF(ISBLANK(Nikes_Sales_Dataset___Working_file[[#This Row],[MRP]]),MEDIAN(Nikes_Sales_Dataset___Working_file[[#All],[MRP]]),Nikes_Sales_Dataset___Working_file[[#This Row],[MRP]]) -> 7849.81 | L73: 0.49 | M73: =IF(ISBLANK(Nikes_Sales_Dataset___Working_file[[#This Row],[Discount_Applied]]),0,Nikes_Sales_Dataset___Working_file[[#This Row],[Discount_Applied]]) -> 0.49 | N73: =Nikes_Sales_Dataset___Working_file[[#This Row],[MRP Final]]*(1-Nikes_Sales_Dataset___Working_file[[#This Row],[Cleaned Discount]]) -> 4003.4031 | O73: 12010.21 | P73: =Nikes_Sales_Dataset___Working_file[[#This Row],[Sales Price]]*Nikes_Sales_Dataset___Working_file[[#This Row],[Units Sold Filled]] -> 12010.209 | Q73: 45669 | R73: =IF(ISBLANK(Nikes_Sales_Dataset___Working_file[[#This Row],[Order_Date]]),"Unknown Date",Nikes_Sales_Dataset___Working_file[[#This Row],[Order_Date]]) -> 45669 | S73: =IF(ISNUMBER(Nikes_Sales_Dataset___Working_file[[#This Row],[Cleaned Order Date]]),TEXT(Nikes_Sales_Dataset___Working_file[[#This Row],[Cleaned Order Date]],"mmm"),"Unknown") -> Jan | T73: =IF(ISNUMBER(Nikes_Sales_Dataset___Working_file[[#This Row],[Cleaned Order Date]]),TEXT(Nikes_Sales_Dataset___Working_file[[#This Row],[Cleaned Order Date]],"yyyy"),"Unknown") -> 2025 | U73: Retail | V73: Pune | W73: Pune | X73: -882.96
A74: 2072 | B74: =Nikes_Sales_Dataset___Working_file[[#This Row],[Order_ID]]&"_"&TEXT(Nikes_Sales_Dataset___Working_file[[#This Row],[Cleaned Order Date]],"yyyymmdd") -> 2072_Unknown Date | C74: Men | D74: Training | E74: Flex Trainer | G74: M | H74: 3 | I74: =IF(ISBLANK(Nikes_Sales_Dataset___Working_file[[#This Row],[Units_Sold]]),IF(Nikes_Sales_Dataset___Working_file[[#This Row],[Profit]]<0,0,1),Nikes_Sales_Dataset___Working_file[[#This Row],[Units_Sold]]) -> 3 | K74: =IF(ISBLANK(Nikes_Sales_Dataset___Working_file[[#This Row],[MRP]]),MEDIAN(Nikes_Sales_Dataset___Working_file[[#All],[MRP]]),Nikes_Sales_Dataset___Working_file[[#This Row],[MRP]]) -> 6110.03 | M74: =IF(ISBLANK(Nikes_Sales_Dataset___Working_file[[#This Row],[Discount_Applied]]),0,Nikes_Sales_Dataset___Working_file[[#This Row],[Discount_Applied]]) -> 0 | N74: =Nikes_Sales_Dataset___Working_file[[#This Row],[MRP Final]]*(1-Nikes_Sales_Dataset___Working_file[[#This Row],[Cleaned Discount]]) -> 6110.03 | O74: 0 | P74: =Nikes_Sales_Dataset___Working_file[[#This Row],[Sales Price]]*Nikes_Sales_Dataset___Working_file[[#This Row],[Units Sold Filled]] -> 18330.09 | R74: =IF(ISBLANK(Nikes_Sales_Dataset___Working_file[[#This Row],[Order_Date]]),"Unknown Date",Nikes_Sales_Dataset___Working_file[[#This Row],[Order_Date]]) -> Unknown Date | S74: =IF(ISNUMBER(Nikes_Sales_Dataset___Working_file[[#This Row],[Cleaned Order Date]]),TEXT(Nikes_Sales_Dataset___Working_file[[#This Row],[Cleaned Order Date]],"mmm"),"Unknown") -> Unknown | T74: =IF(ISNUMBER(Nikes_Sales_Dataset___Working_file[[#This Row],[Cleaned Order Date]]),TEXT(Nikes_Sales_Dataset___Working_file[[#This Row],[Cleaned Order Date]],"yyyy"),"Unknown") -> Unknown | U74: Retail | V74: Pune | W74: Pune | X74: 3639.2
A75: 2073 | B75: =Nikes_Sales_Dataset___Working_file[[#This Row],[Order_ID]]&"_"&TEXT(Nikes_Sales_Dataset___Working_file[[#This Row],[Cleaned Order Date]],"yyyymmdd") -> 2073_20241103 | C75: Women | D75: Lifestyle | E75: Blazer Mid | F75: 12 | G75: XL | H75: 4 | I75: =IF(ISBLANK(Nikes_Sales_Dataset___Working_file[[#This Row],[Units_Sold]]),IF(Nikes_Sales_Dataset___Working_file[[#This Row],[Profit]]<0,0,1),Nikes_Sales_Dataset___Working_file[[#This Row],[Units_Sold]]) -> 4 | K75: =IF(ISBLANK(Nikes_Sales_Dataset___Working_file[[#This Row],[MRP]]),MEDIAN(Nikes_Sales_Dataset___Working_file[[#All],[MRP]]),Nikes_Sales_Dataset___Working_file[[#This Row],[MRP]]) -> 6110.03 | L75: 0.85 | M75: =IF(ISBLANK(Nikes_Sales_Dataset___Working_file[[#This Row],[Discount_Applied]]),0,Nikes_Sales_Dataset___Working_file[[#This Row],[Discount_Applied]]) -> 0.85 | N75: =Nikes_Sales_Dataset___Working_file[[#This Row],[MRP Final]]*(1-Nikes_Sales_Dataset___Working_file[[#This Row],[Cleaned Discount]]) -> 916.5045 | O75: 0 | P75: =Nikes_Sales_Dataset___Working_file[[#This Row],[Sales Price]]*Nikes_Sales_Dataset___Working_file[[#This Row],[Units Sold Filled]] -> 3666.018 | Q75: 45599 | R75: =IF(ISBLANK(Nikes_Sales_Dataset___Working_file[[#This Row],[Order_Date]]),"Unknown Date",Nikes_Sales_Dataset___Working_file[[#This Row],[Order_Date]]) -> 45599 | S75: =IF(ISNUMBER(Nikes_Sales_Dataset___Working_file[[#This Row],[Cleaned Order Date]]),TEXT(Nikes_Sales_Dataset___Working_file[[#This Row],[Cleaned Order Date]],"mmm"),"Unknown") -> Nov | T75: =IF(ISNUMBER(Nikes_Sales_Dataset___Working_file[[#This Row],[Cleaned Order Date]]),TEXT(Nikes_Sales_Dataset___Working_file[[#This Row],[Cleaned Order Date]],"yyyy"),"Unknown") -> 2024 | U75: Online | V75: Hyd | W75: Hyderabad | X75: 443.86
A76: 2074 | B76: =Nikes_Sales_Dataset___Working_file[[#This Row],[Order_ID]]&"_"&TEXT(Nikes_Sales_Dataset___Working_file[[#This Row],[Cleaned Order Date]],"yyyymmdd") -> 2074_Unknown Date | C76: Men | D76: Training | E76: Flex Trainer | F76: L | G76: L | H76: -1 | I76: =IF(ISBLANK(Nikes_Sales_Dataset___Working_file[[#This Row],[Units_Sold]]),IF(Nikes_Sales_Dataset___Working_file[[#This Row],[Profit]]<0,0,1),Nikes_Sales_Dataset___Working_file[[#This Row],[Units_Sold]]) -> -1 | K76: =IF(ISBLANK(Nikes_Sales_Dataset___Working_file[[#This Row],[MRP]]),MEDIAN(Nikes_Sales_Dataset___Working_file[[#All],[MRP]]),Nikes_Sales_Dataset___Working_file[[#This Row],[MRP]]) -> 6110.03 | L76: 0.57 | M76: =IF(ISBLANK(Nikes_Sales_Dataset___Working_file[[#This Row],[Discount_Applied]]),0,Nikes_Sales_Dataset___Working_file[[#This Row],[Discount_Applied]]) -> 0.57 | N76: =Nikes_Sales_Dataset___Working_file[[#This Row],[MRP Final]]*(1-Nikes_Sales_Dataset___Working_file[[#This Row],[Cleaned Discount]]) -> 2627.3129 | O76: 0 | P76: =Nikes_Sales_Dataset___Working_file[[#This Row],[Sales Price]]*Nikes_Sales_Dataset___Working_file[[#This Row],[Units Sold Filled]] -> -2627.3129 | R76: =IF(ISBLANK(Nikes_Sales_Dataset___Working_file[[#This Row],[Order_Date]]),"Unknown Date",Nikes_Sales_Dataset___Working_file[[#This Row],[Order_Date]]) -> Unknown Date | S76: =IF(ISNUMBER(Nikes_Sales_Dataset___Working_file[[#This Row],[Cleaned Order Date]]),TEXT(Nikes_Sales_Dataset___Working_file[[#This Row],[Cleaned Order Date]],"mmm"),"Unknown") -> Unknown | T76: =IF(ISNUMBER(Nikes_Sales_Dataset___Working_file[[#This Row],[Cleaned Order Date]]),TEXT(Nikes_Sales_Dataset___Working_file[[#This Row],[Cleaned Order Date]],"yyyy"),"Unknown") -> Unknown | U76: Online | V76: Kolkata | W76: Kolkata | X76: 1958.47
A77: 2075 | B77: =Nikes_Sales_Dataset___Working_file[[#This Row],[Order_ID]]&"_"&TEXT(Nikes_Sales_Dataset___Working_file[[#This Row],[Cleaned Order Date]],"yyyymmdd") -> 2075_20250714 | C77: Kids | D77: Basketball | E77: Air Jordan | F77: L | G77: L | H77: 4 | I77: =IF(ISBLANK(Nikes_Sales_Dataset___Working_file[[#This Row],[Units_Sold]]),IF(Nikes_Sales_Dataset___Working_file[[#This Row],[Profit]]<0,0,1),Nikes_Sales_Dataset___Working_file[[#This Row],[Units_Sold]]) -> 4 | J77: 4251.74 | K77: =IF(ISBLANK(Nikes_Sales_Dataset___Working_file[[#This Row],[MRP]]),MEDIAN(Nikes_Sales_Dataset___Working_file[[#All],[MRP]]),Nikes_Sales_Dataset___Working_file[[#This Row],[MRP]]) -> 4251.74 | M77: =IF(ISBLANK(Nikes_Sales_Dataset___Working_file[[#This Row],[Discount_Applied]]),0,Nikes_Sales_Dataset___Working_file[[#This Row],[Discount_Applied]]) -> 0 | N77: =Nikes_Sales_Dataset___Working_file[[#This Row],[MRP Final]]*(1-Nikes_Sales_Dataset___Working_file[[#This Row],[Cleaned Discount]]) -> 4251.74 | O77: 0 | P77: =Nikes_Sales_Dataset___Working_file[[#This Row],[Sales Price]]*Nikes_Sales_Dataset___Working_file[[#This Row],[Units Sold Filled]] -> 17006.96 | Q77: 45852 | R77: =IF(ISBLANK(Nikes_Sales_Dataset___Working_file[[#This Row],[Order_Date]]),"Unknown Date",Nikes_Sales_Dataset___Working_file[[#This Row],[Order_Date]]) -> 45852 | S77: =IF(ISNUMBER(Nikes_Sales_Dataset___Working_file[[#This Row],[Cleaned Order Date]]),TEXT(Nikes_Sales_Dataset___Working_file[[#This Row],[Cleaned Order Date]],"mmm"),"Unknown") -> Jul | T77: =IF(ISNUMBER(Nikes_Sales_Dataset___Working_file[[#This Row],[Cleaned Order Date]]),TEXT(Nikes_Sales_Dataset___Working_file[[#This Row],[Cleaned Order Date]],"yyyy"),"Unknown") -> 2025 | U77: Online | V77: Pune | W77: Pune | X77: 2345.35
A78: 2076 | B78: =Nikes_Sales_Dataset___Working_file[[#This Row],[Order_ID]]&"_"&TEXT(Nikes_Sales_Dataset___Working_file[[#This Row],[Cleaned Order Date]],"yyyymmdd") -> 2076_20241013 | C78: Women | D78: Training | E78: ZoomX Invincible | F78: 11 | G78: L | I78: =IF(ISBLANK(Nikes_Sales_Dataset___Working_file[[#This Row],[Units_Sold]]),IF(Nikes_Sales_Dataset___Working_file[[#This Row],[Profit]]<0,0,1),Nikes_Sales_Dataset___Working_file[[#This Row],[Units_Sold]]) -> 1 | K78: =IF(ISBLANK(Nikes_Sales_Dataset___Working_file[[#This Row],[MRP]]),MEDIAN(Nikes_Sales_Dataset___Working_file[[#All],[MRP]]),Nikes_Sales_Dataset___Working_file[[#This Row],[MRP]]) -> 6110.03 | M78: =IF(ISBLANK(Nikes_Sales_Dataset___Working_file[[#This Row],[Discount_Applied]]),0,Nikes_Sales_Dataset___Working_file[[#This Row],[Discount_Applied]]) -> 0 | N78: =Nikes_Sales_Dataset___Working_file[[#This Row],[MRP Final]]*(1-Nikes_Sales_Dataset___Working_file[[#This Row],[Cleaned Discount]]) -> 6110.03 | O78: 0 | P78: =Nikes_Sales_Dataset___Working_file[[#This Row],[Sales Price]]*Nikes_Sales_Dataset___Working_file[[#This Row],[Units Sold Filled]] -> 6110.03 | Q78: 45578 | R78: =IF(ISBLANK(Nikes_Sales_Dataset___Working_file[[#This Row],[Order_Date]]),"Unknown Date",Nikes_Sales_Dataset___Working_file[[#This Row],[Order_Date]]) -> 45578 | S78: =IF(ISNUMBER(Nikes_Sales_Dataset___Working_file[[#This Row],[Cleaned Order Date]]),TEXT(Nikes_Sales_Dataset___Working_file[[#This Row],[Cleaned Order Date]],"mmm"),"Unknown") -> Oct | T78: =IF(ISNUMBER(Nikes_Sales_Dataset___Working_file[[#This Row],[Cleaned Order Date]]),TEXT(Nikes_Sales_Dataset___Working_file[[#This Row],[Cleaned Order Date]],"yyyy"),"Unknown") -> 2024 | U78: Retail | V78: bengaluru | W78: Bangalore | X78: 2011.25
A79: 2077 | B79: =Nikes_Sales_Dataset___Working_file[[#This Row],[Order_ID]]&"_"&TEXT(Nikes_Sales_Dataset___Working_file[[#This Row],[Cleaned Order Date]],"yyyymmdd") -> 2077_20231121 | C79: Men | D79: Training | E79: ZoomX Invincible | F79: L | G79: L | I79: =IF(ISBLANK(Nikes_Sales_Dataset___Working_file[[#This Row],[Units_Sold]]),IF(Nikes_Sales_Dataset___Working_file[[#This Row],[Profit]]<0,0,1),Nikes_Sales_Dataset___Working_file[[#This Row],[Units_Sold]]) -> 1 | K79: =IF(ISBLANK(Nikes_Sales_Dataset___Working_file[[#This Row],[MRP]]),MEDIAN(Nikes_Sales_Dataset___Working_file[[#All],[MRP]]),Nikes_Sales_Dataset___Working_file[[#This Row],[MRP]]) -> 6110.03 | M79: =IF(ISBLANK(Nikes_Sales_Dataset___Working_file[[#This Row],[Discount_Applied]]),0,Nikes_Sales_Dataset___Working_file[[#This Row],[Discount_Applied]]) -> 0 | N79: =Nikes_Sales_Dataset___Working_file[[#This Row],[MRP Final]]*(1-Nikes_Sales_Dataset___Working_file[[#This Row],[Cleaned Discount]]) -> 6110.03 | O79: 0 | P79: =Nikes_Sales_Dataset___Working_file[[#This Row],[Sales Price]]*Nikes_Sales_Dataset___Working_file[[#This Row],[Units Sold Filled]] -> 6110.03 | Q79: 45251 | R79: =IF(ISBLANK(Nikes_Sales_Dataset___Working_file[[#This Row],[Order_Date]]),"Unknown Date",Nikes_Sales_Dataset___Working_file[[#This Row],[Order_Date]]) -> 45251 | S79: =IF(ISNUMBER(Nikes_Sales_Dataset___Working_file[[#This Row],[Cleaned Order Date]]),TEXT(Nikes_Sales_Dataset___Working_file[[#This Row],[Cleaned Order Date]],"mmm"),"Unknown") -> Nov | T79: =IF(ISNUMBER(Nikes_Sales_Dataset___Working_file[[#This Row],[Cleaned Order Date]]),TEXT(Nikes_Sales_Dataset___Working_file[[#This Row],[Cleaned Order Date]],"yyyy"),"Unknown") -> 2023 | U79: Online | V79: Pune | W79: Pune | X79: 3332.66
A80: 2078 | B80: =Nikes_Sales_Dataset___Working_file[[#This Row],[Order_ID]]&"_"&TEXT(Nikes_Sales_Dataset___Working_file[[#This Row],[Cleaned Order Date]],"yyyymmdd") -> 2078_Unknown Date | C80: Women | D80: Basketball | E80: LeBron 20 | G80: M | H80: 0 | I80: =IF(ISBLANK(Nikes_Sales_Dataset___Working_file[[#This Row],[Units_Sold]]),IF(Nikes_Sales_Dataset___Working_file[[#This Row],[Profit]]<0,0,1),Nikes_Sales_Dataset___Working_file[[#This Row],[Units_Sold]]) -> 0 | J80: 6970.47 | K80: =IF(ISBLANK(Nikes_Sales_Dataset___Working_file[[#This Row],[MRP]]),MEDIAN(Nikes_Sales_Dataset___Working_file[[#All],[MRP]]),Nikes_Sales_Dataset___Working_file[[#This Row],[MRP]]) -> 6970.47 | M80: =IF(ISBLANK(Nikes_Sales_Dataset___Working_file[[#This Row],[Discount_Applied]]),0,Nikes_Sales_Dataset___Working_file[[#This Row],[Discount_Applied]]) -> 0 | N80: =Nikes_Sales_Dataset___Working_file[[#This Row],[MRP Final]]*(1-Nikes_Sales_Dataset___Working_file[[#This Row],[Cleaned Discount]]) -> 6970.47 | O80: 0 | P80: =Nikes_Sales_Dataset___Working_file[[#This Row],[Sales Price]]*Nikes_Sales_Dataset___Working_file[[#This Row],[Units Sold Filled]] -> 0 | R80: =IF(ISBLANK(Nikes_Sales_Dataset___Working_file[[#This Row],[Order_Date]]),"Unknown Date",Nikes_Sales_Dataset___Working_file[[#This Row],[Order_Date]]) -> Unknown Date | S80: =IF(ISNUMBER(Nikes_Sales_Dataset___Working_file[[#This Row],[Cleaned Order Date]]),TEXT(Nikes_Sales_Dataset___Working_file[[#This Row],[Cleaned Order Date]],"mmm"),"Unknown") -> Unknown | T80: =IF(ISNUMBER(Nikes_Sales_Dataset___Working_file[[#This Row],[Cleaned Order Date]]),TEXT(Nikes_Sales_Dataset___Working_file[[#This Row],[Cleaned Order Date]],"yyyy"),"Unknown") -> Unknown | U80: Online | V80: Mumbai | W80: Mumbai | X80: 262.79
A81: 2079 | B81: =Nikes_Sales_Dataset___Working_file[[#This Row],[Order_ID]]&"_"&TEXT(Nikes_Sales_Dataset___Working_file[[#This Row],[Cleaned Order Date]],"yyyymmdd") -> 2079_20250119 | C81: Men | D81: Running | E81: Pegasus Turbo | F81: XL | G81: XL | H81: -1 | I81: =IF(ISBLANK(Nikes_Sales_Dataset___Working_file[[#This Row],[Units_Sold]]),IF(Nikes_Sales_Dataset___Working_file[[#This Row],[Profit]]<0,0,1),Nikes_Sales_Dataset___Working_file[[#This Row],[Units_Sold]]) -> -1 | J81: 4322.06 | K81: =IF(ISBLANK(Nikes_Sales_Dataset___Working_file[[#This Row],[MRP]]),MEDIAN(Nikes_Sales_Dataset___Working_file[[#All],[MRP]]),Nikes_Sales_Dataset___Working_file[[#This Row],[MRP]]) -> 4322.06 | M81: =IF(ISBLANK(Nikes_Sales_Dataset___Working_file[[#This Row],[Discount_Applied]]),0,Nikes_Sales_Dataset___Working_file[[#This Row],[Discount_Applied]]) -> 0 | N81: =Nikes_Sales_Dataset___Working_file[[#This Row],[MRP Final]]*(1-Nikes_Sales_Dataset___Working_file[[#This Row],[Cleaned Discount]]) -> 4322.06 | O81: 0 | P81: =Nikes_Sales_Dataset___Working_file[[#This Row],[Sales Price]]*Nikes_Sales_Dataset___Working_file[[#This Row],[Units Sold Filled]] -> -4322.06 | Q81: 45676 | R81: =IF(ISBLANK(Nikes_Sales_Dataset___Working_file[[#This Row],[Order_Date]]),"Unknown Date",Nikes_Sales_Dataset___Working_file[[#This Row],[Order_Date]]) -> 45676 | S81: =IF(ISNUMBER(Nikes_Sales_Dataset___Working_file[[#This Row],[Cleaned Order Date]]),TEXT(Nikes_Sales_Dataset___Working_file[[#This Row],[Cleaned Order Date]],"mmm"),"Unknown") -> Jan | T81: =IF(ISNUMBER(Nikes_Sales_Dataset___Working_file[[#This Row],[Cleaned Order Date]]),TEXT(Nikes_Sales_Dataset___Working_file[[#This Row],[Cleaned Order Date]],"yyyy"),"Unknown") -> 2025 | U81: Online | V81: bengaluru | W81: Bangalore | X81: 279.78
A82: 2080 | B82: =Nikes_Sales_Dataset___Working_file[[#This Row],[Order_ID]]&"_"&TEXT(Nikes_Sales_Dataset___Working_file[[#This Row],[Cleaned Order Date]],"yyyymmdd") -> 2080_20250331 | C82: Men | D82: Lifestyle | E82: Blazer Mid | F82: L | G82: L | I82: =IF(ISBLANK(Nikes_Sales_Dataset___Working_file[[#This Row],[Units_Sold]]),IF(Nikes_Sales_Dataset___Working_file[[#This Row],[Profit]]<0,0,1),Nikes_Sales_Dataset___Working_file[[#This Row],[Units_Sold]]) -> 0 | K82: =IF(ISBLANK(Nikes_Sales_Dataset___Working_file[[#This Row],[MRP]]),MEDIAN(Nikes_Sales_Dataset___Working_file[[#All],[MRP]]),Nikes_Sales_Dataset___Working_file[[#This Row],[MRP]]) -> 6110.03 | M82: =IF(ISBLANK(Nikes_Sales_Dataset___Working_file[[#This Row],[Discount_Applied]]),0,Nikes_Sales_Dataset___Working_file[[#This Row],[Discount_Applied]]) -> 0 | N82: =Nikes_Sales_Dataset___Working_file[[#This Row],[MRP Final]]*(1-Nikes_Sales_Dataset___Working_file[[#This Row],[Cleaned Discount]]) -> 6110.03 | O82: 0 | P82: =Nikes_Sales_Dataset___Working_file[[#This Row],[Sales Price]]*Nikes_Sales_Dataset___Working_file[[#This Row],[Units Sold Filled]] -> 0 | Q82: 45747 | R82: =IF(ISBLANK(Nikes_Sales_Dataset___Working_file[[#This Row],[Order_Date]]),"Unknown Date",Nikes_Sales_Dataset___Working_file[[#This Row],[Order_Date]]) -> 45747 | S82: =IF(ISNUMBER(Nikes_Sales_Dataset___Working_file[[#This Row],[Cleaned Order Date]]),TEXT(Nikes_Sales_Dataset___Working_file[[#This Row],[Cleaned Order Date]],"mmm"),"Unknown") -> Mar | T82: =IF(ISNUMBER(Nikes_Sales_Dataset___Working_file[[#This Row],[Cleaned Order Date]]),TEXT(Nikes_Sales_Dataset___Working_file[[#This Row],[Cleaned Order Date]],"yyyy"),"Unknown") -> 2025 | U82: Online | V82: Bangalore | W82: Bangalore | X82: -1005.89
A83: 2081 | B83: =Nikes_Sales_Dataset___Working_file[[#This Row],[Order_ID]]&"_"&TEXT(Nikes_Sales_Dataset___Working_file[[#This Row],[Cleaned Order Date]],"yyyymmdd") -> 2081_Unknown Date | C83: Men | D83: Training | E83: ZoomX Invincible | F83: L | G83: L | I83: =IF(ISBLANK(Nikes_Sales_Dataset___Working_file[[#This Row],[Units_Sold]]),IF(Nikes_Sales_Dataset___Working_file[[#This Row],[Profit]]<0,0,1),Nikes_Sales_Dataset___Working_file[[#This Row],[Units_Sold]]) -> 1 | K83: =IF(ISBLANK(Nikes_Sales_Dataset___Working_file[[#This Row],[MRP]]),MEDIAN(Nikes_Sales_Dataset___Working_file[[#All],[MRP]]),Nikes_Sales_Dataset___Working_file[[#This Row],[MRP]]) -> 6110.03 | M83: =IF(ISBLANK(Nikes_Sales_Dataset___Working_file[[#This Row],[Discount_Applied]]),0,Nikes_Sales_Dataset___Working_file[[#This Row],[Discount_Applied]]) -> 0 | N83: =Nikes_Sales_Dataset___Working_file[[#This Row],[MRP Final]]*(1-Nikes_Sales_Dataset___Working_file[[#This Row],[Cleaned Discount]]) -> 6110.03 | O83: 0 | P83: =Nikes_Sales_Dataset___Working_file[[#This Row],[Sales Price]]*Nikes_Sales_Dataset___Working_file[[#This Row],[Units Sold Filled]] -> 6110.03 | R83: =IF(ISBLANK(Nikes_Sales_Dataset___Working_file[[#This Row],[Order_Date]]),"Unknown Date",Nikes_Sales_Dataset___Working_file[[#This Row],[Order_Date]]) -> Unknown Date | S83: =IF(ISNUMBER(Nikes_Sales_Dataset___Working_file[[#This Row],[Cleaned Order Date]]),TEXT(Nikes_Sales_Dataset___Working_file[[#This Row],[Cleaned Order Date]],"mmm"),"Unknown") -> Unknown | T83: =IF(ISNUMBER(Nikes_Sales_Dataset___Working_file[[#This Row],[Cleaned Order Date]]),TEXT(Nikes_Sales_Dataset___Working_file[[#This Row],[Cleaned Order Date]],"yyyy"),"Unknown") -> Unknown | U83: Online | V83: Mumbai | W83: Mumbai | X83: 2810.49
A84: 2028 | B84: =Nikes_Sales_Dataset___Working_file[[#This Row],[Order_ID]]&"_"&TEXT(Nikes_Sales_Dataset___Working_file[[#This Row],[Cleaned Order Date]],"yyyymmdd") -> 2028_20240214 | C84: Men | D84: Running | E84: Free RN | G84: M | H84: -1 | I84: =IF(ISBLANK(Nikes_Sales_Dataset___Working_file[[#This Row],[Units_Sold]]),IF(Nikes_Sales_Dataset___Working_file[[#This Row],[Profit]]<0,0,1),Nikes_Sales_Dataset___Working_file[[#This Row],[Units_Sold]]) -> -1 | K84: =IF(ISBLANK(Nikes_Sales_Dataset___Working_file[[#This Row],[MRP]]),MEDIAN(Nikes_Sales_Dataset___Working_file[[#All],[MRP]]),Nikes_Sales_Dataset___Working_file[[#This Row],[MRP]]) -> 6110.03 | L84: 0.21 | M84: =IF(ISBLANK(Nikes_Sales_Dataset___Working_file[[#This Row],[Discount_Applied]]),0,Nikes_Sales_Dataset___Working_file[[#This Row],[Discount_Applied]]) -> 0.21 | N84: =Nikes_Sales_Dataset___Working_file[[#This Row],[MRP Final]]*(1-Nikes_Sales_Dataset___Working_file[[#This Row],[Cleaned Discount]]) -> 4826.9237 | O84: 0 | P84: =Nikes_Sales_Dataset___Working_file[[#This Row],[Sales Price]]*Nikes_Sales_Dataset___Working_file[[#This Row],[Units Sold Filled]] -> -4826.9237 | Q84: 45336 | R84: =IF(ISBLANK(Nikes_Sales_Dataset___Working_file[[#This Row],[Order_Date]]),"Unknown Date",Nikes_Sales_Dataset___Working_file[[#This Row],[Order_Date]]) -> 45336 | S84: =IF(ISNUMBER(Nikes_Sales_Dataset___Working_file[[#This Row],[Cleaned Order Date]]),TEXT(Nikes_Sales_Dataset___Working_file[[#This Row],[Cleaned Order Date]],"mmm"),"Unknown") -> Feb | T84: =IF(ISNUMBER(Nikes_Sales_Dataset___Working_file[[#This Row],[Cleaned Order Date]]),TEXT(Nikes_Sales_Dataset___Working_file[[#This Row],[Cleaned Order Date]],"yyyy"),"Unknown") -> 2024 | U84: Online | V84: Hyderabad | W84: Hyderabad | X84: 3303.01
A85: 2083 | B85: =Nikes_Sales_Dataset___Working_file[[#This Row],[Order_ID]]&"_"&TEXT(Nikes_Sales_Dataset___Working_file[[#This Row],[Cleaned Order Date]],"yyyymmdd") -> 2083_20241014 | C85: Men | D85: Running | E85: Free RN | G85: M | I85: =IF(ISBLANK(Nikes_Sales_Dataset___Working_file[[#This Row],[Units_Sold]]),IF(Nikes_Sales_Dataset___Working_file[[#This Row],[Profit]]<0,0,1),Nikes_Sales_Dataset___Working_file[[#This Row],[Units_Sold]]) -> 0 | J85: 9291.74 | K85: =IF(ISBLANK(Nikes_Sales_Dataset___Working_file[[#This Row],[MRP]]),MEDIAN(Nikes_Sales_Dataset___Working_file[[#All],[MRP]]),Nikes_Sales_Dataset___Working_file[[#This Row],[MRP]]) -> 9291.74 | M85: =IF(ISBLANK(Nikes_Sales_Dataset___Working_file[[#This Row],[Discount_Applied]]),0,Nikes_Sales_Dataset___Working_file[[#This Row],[Discount_Applied]]) -> 0 | N85: =Nikes_Sales_Dataset___Working_file[[#This Row],[MRP Final]]*(1-Nikes_Sales_Dataset___Working_file[[#This Row],[Cleaned Discount]]) -> 9291.74 | O85: 0 | P85: =Nikes_Sales_Dataset___Working_file[[#This Row],[Sales Price]]*Nikes_Sales_Dataset___Working_file[[#This Row],[Units Sold Filled]] -> 0 | Q85: 45579 | R85: =IF(ISBLANK(Nikes_Sales_Dataset___Working_file[[#This Row],[Order_Date]]),"Unknown Date",Nikes_Sales_Dataset___Working_file[[#This Row],[Order_Date]]) -> 45579 | S85: =IF(ISNUMBER(Nikes_Sales_Dataset___Working_file[[#This Row],[Cleaned Order Date]]),TEXT(Nikes_Sales_Dataset___Working_file[[#This Row],[Cleaned Order Date]],"mmm"),"Unknown") -> Oct | T85: =IF(ISNUMBER(Nikes_Sales_Dataset___Working_file[[#This Row],[Cleaned Order Date]]),TEXT(Nikes_Sales_Dataset___Working_file[[#This Row],[Cleaned Order Date]],"yyyy"),"Unknown") -> 2024 | U85: Retail | V85: Delhi | W85: Delhi | X85: -981.21
A86: 2084 | B86: =Nikes_Sales_Dataset___Working_file[[#This Row],[Order_ID]]&"_"&TEXT(Nikes_Sales_Dataset___Working_file[[#This Row],[Cleaned Order Date]],"yyyymmdd") -> 2084_20231224 | C86: Men | D86: Training | E86: Metcon 7 | F86: M | G86: M | H86: 2 | I86: =IF(ISBLANK(Nikes_Sales_Dataset___Working_file[[#This Row],[Units_Sold]]),IF(Nikes_Sales_Dataset___Working_file[[#This Row],[Profit]]<0,0,1),Nikes_Sales_Dataset___Working_file[[#This Row],[Units_Sold]]) -> 2 | K86: =IF(ISBLANK(Nikes_Sales_Dataset___Working_file[[#This Row],[MRP]]),MEDIAN(Nikes_Sales_Dataset___Working_file[[#All],[MRP]]),Nikes_Sales_Dataset___Working_file[[#This Row],[MRP]]) -> 6110.03 | M86: =IF(ISBLANK(Nikes_Sales_Dataset___Working_file[[#This Row],[Discount_Applied]]),0,Nikes_Sales_Dataset___Working_file[[#This Row],[Discount_Applied]]) -> 0 | N86: =Nikes_Sales_Dataset___Working_file[[#This Row],[MRP Final]]*(1-Nikes_Sales_Dataset___Working_file[[#This Row],[Cleaned Discount]]) -> 6110.03 | O86: 0 | P86: =Nikes_Sales_Dataset___Working_file[[#This Row],[Sales Price]]*Nikes_Sales_Dataset___Working_file[[#This Row],[Units Sold Filled]] -> 12220.06 | Q86: 45284 | R86: =IF(ISBLANK(Nikes_Sales_Dataset___Working_file[[#This Row],[Order_Date]]),"Unknown Date",Nikes_Sales_Dataset___Working_file[[#This Row],[Order_Date]]) -> 45284 | S86: =IF(ISNUMBER(Nikes_Sales_Dataset___Working_file[[#This Row],[Cleaned Order Date]]),TEXT(Nikes_Sales_Dataset___Working_file[[#This Row],[Cleaned Order Date]],"mmm"),"Unknown") -> Dec | T86: =IF(ISNUMBER(Nikes_Sales_Dataset___Working_file[[#This Row],[Cleaned Order Date]]),TEXT(Nikes_Sales_Dataset___Working_file[[#This Row],[Cleaned Order Date]],"yyyy"),"Unknown") -> 2023 | U86: Online | V86: Mumbai | W86: Mumbai | X86: 408.39
A87: 2085 | B87: =Nikes_Sales_Dataset___Working_file[[#This Row],[Order_ID]]&"_"&TEXT(Nikes_Sales_Dataset___Working_file[[#This Row],[Cleaned Order Date]],"yyyymmdd") -> 2085_20241217 | C87: Men | D87: Basketball | E87: Kyrie Flytrap | G87: M | I87: =IF(ISBLANK(Nikes_Sales_Dataset___Working_file[[#This Row],[Units_Sold]]),IF(Nikes_Sales_Dataset___Working_file[[#This Row],[Profit]]<0,0,1),Nikes_Sales_Dataset___Working_file[[#This Row],[Units_Sold]]) -> 1 | J87: 7561.85 | K87: =IF(ISBLANK(Nikes_Sales_Dataset___Working_file[[#This Row],[MRP]]),MEDIAN(Nikes_Sales_Dataset___Working_file[[#All],[MRP]]),Nikes_Sales_Dataset___Working_file[[#This Row],[MRP]]) -> 7561.85 | M87: =IF(ISBLANK(Nikes_Sales_Dataset___Working_file[[#This Row],[Discount_Applied]]),0,Nikes_Sales_Dataset___Working_file[[#This Row],[Discount_Applied]]) -> 0 | N87: =Nikes_Sales_Dataset___Working_file[[#This Row],[MRP Final]]*(1-Nikes_Sales_Dataset___Working_file[[#This Row],[Cleaned Discount]]) -> 7561.85 | O87: 0 | P87: =Nikes_Sales_Dataset___Working_file[[#This Row],[Sales Price]]*Nikes_Sales_Dataset___Working_file[[#This Row],[Units Sold Filled]] -> 7561.85 | Q87: 45643 | R87: =IF(ISBLANK(Nikes_Sales_Dataset___Working_file[[#This Row],[Order_Date]]),"Unknown Date",Nikes_Sales_Dataset___Working_file[[#This Row],[Order_Date]]) -> 45643 | S87: =IF(ISNUMBER(Nikes_Sales_Dataset___Working_file[[#This Row],[Cleaned Order Date]]),TEXT(Nikes_Sales_Dataset___Working_file[[#This Row],[Cleaned Order Date]],"mmm"),"Unknown") -> Dec | T87: =IF(ISNUMBER(Nikes_Sales_Dataset___Working_file[[#This Row],[Cleaned Order Date]]),TEXT(Nikes_Sales_Dataset___Working_file[[#This Row],[Cleaned Order Date]],"yyyy"),"Unknown") -> 2024 | U87: Retail | V87: Kolkata | W87: Kolkata | X87: 98.72
A88: 2086 | B88: =Nikes_Sales_Dataset___Working_file[[#This Row],[Order_ID]]&"_"&TEXT(Nikes_Sales_Dataset___Working_file[[#This Row],[Cleaned Order Date]],"yyyymmdd") -> 2086_20241011 | C88: Men | D88: Soccer | E88: Mercurial Superfly | F88: L | G88: L | H88: 0 | I88: =IF(ISBLANK(Nikes_Sales_Dataset___Working_file[[#This Row],[Units_Sold]]),IF(Nikes_Sales_Dataset___Working_file[[#This Row],[Profit]]<0,0,1),Nikes_Sales_Dataset___Working_file[[#This Row],[Units_Sold]]) -> 0 | K88: =IF(ISBLANK(Nikes_Sales_Dataset___Working_file[[#This Row],[MRP]]),MEDIAN(Nikes_Sales_Dataset___Working_file[[#All],[MRP]]),Nikes_Sales_Dataset___Working_file[[#This Row],[MRP]]) -> 6110.03 | L88: 0.45 | M88: =IF(ISBLANK(Nikes_Sales_Dataset___Working_file[[#This Row],[Discount_Applied]]),0,Nikes_Sales_Dataset___Working_file[[#This Row],[Discount_Applied]]) -> 0.45 | N88: =Nikes_Sales_Dataset___Working_file[[#This Row],[MRP Final]]*(1-Nikes_Sales_Dataset___Working_file[[#This Row],[Cleaned Discount]]) -> 3360.5165 | O88: 0 | P88: =Nikes_Sales_Dataset___Working_file[[#This Row],[Sales Price]]*Nikes_Sales_Dataset___Working_file[[#This Row],[Units Sold Filled]] -> 0 | Q88: 45576 | R88: =IF(ISBLANK(Nikes_Sales_Dataset___Working_file[[#This Row],[Order_Date]]),"Unknown Date",Nikes_Sales_Dataset___Working_file[[#This Row],[Order_Date]]) -> 45576 | S88: =IF(ISNUMBER(Nikes_Sales_Dataset___Working_file[[#This Row],[Cleaned Order Date]]),TEXT(Nikes_Sales_Dataset___Working_file[[#This Row],[Cleaned Order Date]],"mmm"),"Unknown") -> Oct | T88: =IF(ISNUMBER(Nikes_Sales_Dataset___Working_file[[#This Row],[Cleaned Order Date]]),TEXT(Nikes_Sales_Dataset___Working_file[[#This Row],[Cleaned Order Date]],"yyyy"),"Unknown") -> 2024 | U88: Online | V88: Kolkata | W88: Kolkata | X88: 1742.66
A89: 2087 | B89: =Nikes_Sales_Dataset___Working_file[[#This Row],[Order_ID]]&"_"&TEXT(Nikes_Sales_Dataset___Working_file[[#This Row],[Cleaned Order Date]],"yyyymmdd") -> 2087_20241101 | C89: Kids | D89: Basketball | E89: Zoom Freak | G89: M | I89: =IF(ISBLANK(Nikes_Sales_Dataset___Working_file[[#This Row],[Units_Sold]]),IF(Nikes_Sales_Dataset___Working_file[[#This Row],[Profit]]<0,0,1),Nikes_Sales_Dataset___Working_file[[#This Row],[Units_Sold]]) -> 1 | J89: 4656.28 | K89: =IF(ISBLANK(Nikes_Sales_Dataset___Working_file[[#This Row],[MRP]]),MEDIAN(Nikes_Sales_Dataset___Working_file[[#All],[MRP]]),Nikes_Sales_Dataset___Working_file[[#This Row],[MRP]]) -> 4656.28 | M89: =IF(ISBLANK(Nikes_Sales_Dataset___Working_file[[#This Row],[Discount_Applied]]),0,Nikes_Sales_Dataset___Working_file[[#This Row],[Discount_Applied]]) -> 0 | N89: =Nikes_Sales_Dataset___Working_file[[#This Row],[MRP Final]]*(1-Nikes_Sales_Dataset___Working_file[[#This Row],[Cleaned Discount]]) -> 4656.28 | O89: 0 | P89: =Nikes_Sales_Dataset___Working_file[[#This Row],[Sales Price]]*Nikes_Sales_Dataset___Working_file[[#This Row],[Units Sold Filled]] -> 4656.28 | Q89: 45597 | R89: =IF(ISBLANK(Nikes_Sales_Dataset___Working_file[[#This Row],[Order_Date]]),"Unknown Date",Nikes_Sales_Dataset___Working_file[[#This Row],[Order_Date]]) -> 45597 | S89: =IF(ISNUMBER(Nikes_Sales_Dataset___Working_file[[#This Row],[Cleaned Order Date]]),TEXT(Nikes_Sales_Dataset___Working_file[[#This Row],[Cleaned Order Date]],"mmm"),"Unknown") -> Nov | T89: =IF(ISNUMBER(Nikes_Sales_Dataset___Working_file[[#This Row],[Cleaned Order Date]]),TEXT(Nikes_Sales_Dataset___Working_file[[#This Row],[Cleaned Order Date]],"yyyy"),"Unknown") -> 2024 | U89: Online | V89: Kolkata | W89: Kolkata | X89: 3777.5
A90: 2088 | B90: =Nikes_Sales_Dataset___Working_file[[#This Row],[Order_ID]]&"_"&TEXT(Nikes_Sales_Dataset___Working_file[[#This Row],[Cleaned Order Date]],"yyyymmdd") -> 2088_20250426 | C90: Women | D90: Running | E90: Free RN | F90: XL | G90: XL | H90: 4 | I90: =IF(ISBLANK(Nikes_Sales_Dataset___Working_file[[#This Row],[Units_Sold]]),IF(Nikes_Sales_Dataset___Working_file[[#This Row],[Profit]]<0,0,1),Nikes_Sales_Dataset___Working_file[[#This Row],[Units_Sold]]) -> 4 | K90: =IF(ISBLANK(Nikes_Sales_Dataset___Working_file[[#This Row],[MRP]]),MEDIAN(Nikes_Sales_Dataset___Working_file[[#All],[MRP]]),Nikes_Sales_Dataset___Working_file[[#This Row],[MRP]]) -> 6110.03 | M90: =IF(ISBLANK(Nikes_Sales_Dataset___Working_file[[#This Row],[Discount_Applied]]),0,Nikes_Sales_Dataset___Working_file[[#This Row],[Discount_Applied]]) -> 0 | N90: =Nikes_Sales_Dataset___Working_file[[#This Row],[MRP Final]]*(1-Nikes_Sales_Dataset___Working_file[[#This Row],[Cleaned Discount]]) -> 6110.03 | O90: 0 | P90: =Nikes_Sales_Dataset___Working_file[[#This Row],[Sales Price]]*Nikes_Sales_Dataset___Working_file[[#This Row],[Units Sold Filled]] -> 24440.12 | Q90: 45773 | R90: =IF(ISBLANK(Nikes_Sales_Dataset___Working_file[[#This Row],[Order_Date]]),"Unknown Date",Nikes_Sales_Dataset___Working_file[[#This Row],[Order_Date]]) -> 45773 | S90: =IF(ISNUMBER(Nikes_Sales_Dataset___Working_file[[#This Row],[Cleaned Order Date]]),TEXT(Nikes_Sales_Dataset___Working_file[[#This Row],[Cleaned Order Date]],"mmm"),"Unknown") -> Apr | T90: =IF(ISNUMBER(Nikes_Sales_Dataset___Working_file[[#This Row],[Cleaned Order Date]]),TEXT(Nikes_Sales_Dataset___Working_file[[#This Row],[Cleaned Order Date]],"yyyy"),"Unknown") -> 2025 | U90: Online | V90: Bangalore | W90: Bangalore | X90: 2702.93
A91: 2089 | B91: =Nikes_Sales_Dataset___Working_file[[#This Row],[Order_ID]]&"_"&TEXT(Nikes_Sales_Dataset___Working_file[[#This Row],[Cleaned Order Date]],"yyyymmdd") -> 2089_20241202 | C91: Women | D91: Training | E91: Flex Trainer | F91: L | G91: L | H91: 2 | I91: =IF(ISBLANK(Nikes_Sales_Dataset___Working_file[[#This Row],[Units_Sold]]),IF(Nikes_Sales_Dataset___Working_file[[#This Row],[Profit]]<0,0,1),Nikes_Sales_Dataset___Working_file[[#This Row],[Units_Sold]]) -> 2 | J91: 6874.77 | K91: =IF(ISBLANK(Nikes_Sales_Dataset___Working_file[[#This Row],[MRP]]),MEDIAN(Nikes_Sales_Dataset___Working_file[[#All],[MRP]]),Nikes_Sales_Dataset___Working_file[[#This Row],[MRP]]) -> 6874.77 | L91: 0.6 | M91: =IF(ISBLANK(Nikes_Sales_Dataset___Working_file[[#This Row],[Discount_Applied]]),0,Nikes_Sales_Dataset___Working_file[[#This Row],[Discount_Applied]]) -> 0.6 | N91: =Nikes_Sales_Dataset___Working_file[[#This Row],[MRP Final]]*(1-Nikes_Sales_Dataset___Working_file[[#This Row],[Cleaned Discount]]) -> 2749.908 | O91: 5499.82 | P91: =Nikes_Sales_Dataset___Working_file[[#This Row],[Sales Price]]*Nikes_Sales_Dataset___Working_file[[#This Row],[Units Sold Filled]] -> 5499.816 | Q91: 45628 | R91: =IF(ISBLANK(Nikes_Sales_Dataset___Working_file[[#This Row],[Order_Date]]),"Unknown Date",Nikes_Sales_Dataset___Working_file[[#This Row],[Order_Date]]) -> 45628 | S91: =IF(ISNUMBER(Nikes_Sales_Dataset___Working_file[[#This Row],[Cleaned Order Date]]),TEXT(Nikes_Sales_Dataset___Working_file[[#This Row],[Cleaned Order Date]],"mmm"),"Unknown") -> Dec | T91: =IF(ISNUMBER(Nikes_Sales_Dataset___Working_file[[#This Row],[Cleaned Order Date]]),TEXT(Nikes_Sales_Dataset___Working_file[[#This Row],[Cleaned Order Date]],"yyyy"),"Unknown") -> 2024 | U91: Online | V91: Mumbai | W91: Mumbai | X91: -1076.66
A92: 2090 | B92: =Nikes_Sales_Dataset___Working_file[[#This Row],[Order_ID]]&"_"&TEXT(Nikes_Sales_Dataset___Working_file[[#This Row],[Cleaned Order Date]],"yyyymmdd") -> 2090_Unknown Date | C92: Kids | D92: Lifestyle | E92: Dunk Low | F92: 8 | G92: M | I92: =IF(ISBLANK(Nikes_Sales_Dataset___Working_file[[#This Row],[Units_Sold]]),IF(Nikes_Sales_Dataset___Working_file[[#This Row],[Profit]]<0,0,1),Nikes_Sales_Dataset___Working_file[[#This Row],[Units_Sold]]) -> 1 | K92: =IF(ISBLANK(Nikes_Sales_Dataset___Working_file[[#This Row],[MRP]]),MEDIAN(Nikes_Sales_Dataset___Working_file[[#All],[MRP]]),Nikes_Sales_Dataset___Working_file[[#This Row],[MRP]]) -> 6110.03 | M92: =IF(ISBLANK(Nikes_Sales_Dataset___Working_file[[#This Row],[Discount_Applied]]),0,Nikes_Sales_Dataset___Working_file[[#This Row],[Discount_Applied]]) -> 0 | N92: =Nikes_Sales_Dataset___Working_file[[#This Row],[MRP Final]]*(1-Nikes_Sales_Dataset___Working_file[[#This Row],[Cleaned Discount]]) -> 6110.03 | O92: 0 | P92: =Nikes_Sales_Dataset___Working_file[[#This Row],[Sales Price]]*Nikes_Sales_Dataset___Working_file[[#This Row],[Units Sold Filled]] -> 6110.03 | R92: =IF(ISBLANK(Nikes_Sales_Dataset___Working_file[[#This Row],[Order_Date]]),"Unknown Date",Nikes_Sales_Dataset___Working_file[[#This Row],[Order_Date]]) -> Unknown Date | S92: =IF(ISNUMBER(Nikes_Sales_Dataset___Working_file[[#This Row],[Cleaned Order Date]]),TEXT(Nikes_Sales_Dataset___Working_file[[#This Row],[Cleaned Order Date]],"mmm"),"Unknown") -> Unknown | T92: =IF(ISNUMBER(Nikes_Sales_Dataset___Working_file[[#This Row],[Cleaned Order Date]]),TEXT(Nikes_Sales_Dataset___Working_file[[#This Row],[Cleaned Order Date]],"yyyy"),"Unknown") -> Unknown | U92: Retail | V92: Bangalore | W92: Bangalore | X92: 163.15
A93: 2091 | B93: =Nikes_Sales_Dataset___Working_file[[#This Row],[Order_ID]]&"_"&TEXT(Nikes_Sales_Dataset___Working_file[[#This Row],[Cleaned Order Date]],"yyyymmdd") -> 2091_Unknown Date | C93: Kids | D93: Running | E93: Air Zoom | F93: 11 | G93: L | I93: =IF(ISBLANK(Nikes_Sales_Dataset___Working_file[[#This Row],[Units_Sold]]),IF(Nikes_Sales_Dataset___Working_file[[#This Row],[Profit]]<0,0,1),Nikes_Sales_Dataset___Working_file[[#This Row],[Units_Sold]]) -> 1 | J93: 9246.88 | K93: =IF(ISBLANK(Nikes_Sales_Dataset___Working_file[[#This Row],[MRP]]),MEDIAN(Nikes_Sales_Dataset___Working_file[[#All],[MRP]]),Nikes_Sales_Dataset___Working_file[[#This Row],[MRP]]) -> 9246.88 | M93: =IF(ISBLANK(Nikes_Sales_Dataset___Working_file[[#This Row],[Discount_Applied]]),0,Nikes_Sales_Dataset___Working_file[[#This Row],[Discount_Applied]]) -> 0 | N93: =Nikes_Sales_Dataset___Working_file[[#This Row],[MRP Final]]*(1-Nikes_Sales_Dataset___Working_file[[#This Row],[Cleaned Discount]]) -> 9246.88 | O93: 0 | P93: =Nikes_Sales_Dataset___Working_file[[#This Row],[Sales Price]]*Nikes_Sales_Dataset___Working_file[[#This Row],[Units Sold Filled]] -> 9246.88 | R93: =IF(ISBLANK(Nikes_Sales_Dataset___Working_file[[#This Row],[Order_Date]]),"Unknown Date",Nikes_Sales_Dataset___Working_file[[#This Row],[Order_Date]]) -> Unknown Date | S93: =IF(ISNUMBER(Nikes_Sales_Dataset___Working_file[[#This Row],[Cleaned Order Date]]),TEXT(Nikes_Sales_Dataset___Working_file[[#This Row],[Cleaned Order Date]],"mmm"),"Unknown") -> Unknown | T93: =IF(ISNUMBER(Nikes_Sales_Dataset___Working_file[[#This Row],[Cleaned Order Date]]),TEXT(Nikes_Sales_Dataset___Working_file[[#This Row],[Cleaned Order Date]],"yyyy"),"Unknown") -> Unknown | U93: Retail | V93: Mumbai | W93: Mumbai | X93: 1917.55
A94: 2092 | B94: =Nikes_Sales_Dataset___Working_file[[#This Row],[Order_ID]]&"_"&TEXT(Nikes_Sales_Dataset___Working_file[[#This Row],[Cleaned Order Date]],"yyyymmdd") -> 2092_Unknown Date | C94: Kids | D94: Basketball | E94: Zoom Freak | F94: XL | G94: XL | H94: 2 | I94: =IF(ISBLANK(Nikes_Sales_Dataset___Working_file[[#This Row],[Units_Sold]]),IF(Nikes_Sales_Dataset___Working_file[[#This Row],[Profit]]<0,0,1),Nikes_Sales_Dataset___Working_file[[#This Row],[Units_Sold]]) -> 2 | K94: =IF(ISBLANK(Nikes_Sales_Dataset___Working_file[[#This Row],[MRP]]),MEDIAN(Nikes_Sales_Dataset___Working_file[[#All],[MRP]]),Nikes_Sales_Dataset___Working_file[[#This Row],[MRP]]) -> 6110.03 | L94: 1.13 | M94: =IF(ISBLANK(Nikes_Sales_Dataset___Working_file[[#This Row],[Discount_Applied]]),0,Nikes_Sales_Dataset___Working_file[[#This Row],[Discount_Applied]]) -> 1.13 | N94: =Nikes_Sales_Dataset___Working_file[[#This Row],[MRP Final]]*(1-Nikes_Sales_Dataset___Working_file[[#This Row],[Cleaned Discount]]) -> -794.3039 | O94: 0 | P94: =Nikes_Sales_Dataset___Working_file[[#This Row],[Sales Price]]*Nikes_Sales_Dataset___Working_file[[#This Row],[Units Sold Filled]] -> -1588.6078 | R94: =IF(ISBLANK(Nikes_Sales_Dataset___Working_file[[#This Row],[Order_Date]]),"Unknown Date",Nikes_Sales_Dataset___Working_file[[#This Row],[Order_Date]]) -> Unknown Date | S94: =IF(ISNUMBER(Nikes_Sales_Dataset___Working_file[[#This Row],[Cleaned Order Date]]),TEXT(Nikes_Sales_Dataset___Working_file[[#This Row],[Cleaned Order Date]],"mmm"),"Unknown") -> Unknown | T94: =IF(ISNUMBER(Nikes_Sales_Dataset___Working_file[[#This Row],[Cleaned Order Date]]),TEXT(Nikes_Sales_Dataset___Working_file[[#This Row],[Cleaned Order Date]],"yyyy"),"Unknown") -> Unknown | U94: Online | V94: Delhi | W94: Delhi | X94: 207.2
A95: 2093 | B95: =Nikes_Sales_Dataset___Working_file[[#This Row],[Order_ID]]&"_"&TEXT(Nikes_Sales_Dataset___Working_file[[#This Row],[Cleaned Order Date]],"yyyymmdd") -> 2093_Unknown Date | C95: Men | D95: Running | E95: Free RN | F95: XL | G95: XL | H95: 0 | I95: =IF(ISBLANK(Nikes_Sales_Dataset___Working_file[[#This Row],[Units_Sold]]),IF(Nikes_Sales_Dataset___Working_file[[#This Row],[Profit]]<0,0,1),Nikes_Sales_Dataset___Working_file[[#This Row],[Units_Sold]]) -> 0 | K95: =IF(ISBLANK(Nikes_Sales_Dataset___Working_file[[#This Row],[MRP]]),MEDIAN(Nikes_Sales_Dataset___Working_file[[#All],[MRP]]),Nikes_Sales_Dataset___Working_file[[#This Row],[MRP]]) -> 6110.03 | L95: 0.29 | M95: =IF(ISBLANK(Nikes_Sales_Dataset___Working_file[[#This Row],[Discount_Applied]]),0,Nikes_Sales_Dataset___Working_file[[#This Row],[Discount_Applied]]) -> 0.29 | N95: =Nikes_Sales_Dataset___Working_file[[#This Row],[MRP Final]]*(1-Nikes_Sales_Dataset___Working_file[[#This Row],[Cleaned Discount]]) -> 4338.1213 | O95: 0 | P95: =Nikes_Sales_Dataset___Working_file[[#This Row],[Sales Price]]*Nikes_Sales_Dataset___Working_file[[#This Row],[Units Sold Filled]] -> 0 | R95: =IF(ISBLANK(Nikes_Sales_Dataset___Working_file[[#This Row],[Order_Date]]),"Unknown Date",Nikes_Sales_Dataset___Working_file[[#This Row],[Order_Date]]) -> Unknown Date | S95: =IF(ISNUMBER(Nikes_Sales_Dataset___Working_file[[#This Row],[Cleaned Order Date]]),TEXT(Nikes_Sales_Dataset___Working_file[[#This Row],[Cleaned Order Date]],"mmm"),"Unknown") -> Unknown | T95: =IF(ISNUMBER(Nikes_Sales_Dataset___Working_file[[#This Row],[Cleaned Order Date]]),TEXT(Nikes_Sales_Dataset___Working_file[[#This Row],[Cleaned Order Date]],"yyyy"),"Unknown") -> Unknown | U95: Online | V95: Kolkata | W95: Kolkata | X95: -146.73
A96: 2094 | B96: =Nikes_Sales_Dataset___Working_file[[#This Row],[Order_ID]]&"_"&TEXT(Nikes_Sales_Dataset___Working_file[[#This Row],[Cleaned Order Date]],"yyyymmdd") -> 2094_20241110 | C96: Kids | D96: Training | E96: Flex Trainer | F96: 10 | G96: L | H96: 1 | I96: =IF(ISBLANK(Nikes_Sales_Dataset___Working_file[[#This Row],[Units_Sold]]),IF(Nikes_Sales_Dataset___Working_file[[#This Row],[Profit]]<0,0,1),Nikes_Sales_Dataset___Working_file[[#This Row],[Units_Sold]]) -> 1 | J96: 4276.36 | K96: =IF(ISBLANK(Nikes_Sales_Dataset___Working_file[[#This Row],[MRP]]),MEDIAN(Nikes_Sales_Dataset___Working_file[[#All],[MRP]]),Nikes_Sales_Dataset___Working_file[[#This Row],[MRP]]) -> 4276.36 | M96: =IF(ISBLANK(Nikes_Sales_Dataset___Working_file[[#This Row],[Discount_Applied]]),0,Nikes_Sales_Dataset___Working_file[[#This Row],[Discount_Applied]]) -> 0 | N96: =Nikes_Sales_Dataset___Working_file[[#This Row],[MRP Final]]*(1-Nikes_Sales_Dataset___Working_file[[#This Row],[Cleaned Discount]]) -> 4276.36 | O96: 0 | P96: =Nikes_Sales_Dataset___Working_file[[#This Row],[Sales Price]]*Nikes_Sales_Dataset___Working_file[[#This Row],[Units Sold Filled]] -> 4276.36 | Q96: 45606 | R96: =IF(ISBLANK(Nikes_Sales_Dataset___Working_file[[#This Row],[Order_Date]]),"Unknown Date",Nikes_Sales_Dataset___Working_file[[#This Row],[Order_Date]]) -> 45606 | S96: =IF(ISNUMBER(Nikes_Sales_Dataset___Working_file[[#This Row],[Cleaned Order Date]]),TEXT(Nikes_Sales_Dataset___Working_file[[#This Row],[Cleaned Order Date]],"mmm"),"Unknown") -> Nov | T96: =IF(ISNUMBER(Nikes_Sales_Dataset___Working_file[[#This Row],[Cleaned Order Date]]),TEXT(Nikes_Sales_Dataset___Working_file[[#This Row],[Cleaned Order Date]],"yyyy"),"Unknown") -> 2024 | U96: Retail | V96: Delhi | W96: Delhi | X96: 2974.58
A97: 2095 | B97: =Nikes_Sales_Dataset___Working_file[[#This Row],[Order_ID]]&"_"&TEXT(Nikes_Sales_Dataset___Working_file[[#This Row],[Cleaned Order Date]],"yyyymmdd") -> 2095_20241016 | C97: Men | D97: Lifestyle | E97: Waffle One | F97: M | G97: M | I97: =IF(ISBLANK(Nikes_Sales_Dataset___Working_file[[#This Row],[Units_Sold]]),IF(Nikes_Sales_Dataset___Working_file[[#This Row],[Profit]]<0,0,1),Nikes_Sales_Dataset___Working_file[[#This Row],[Units_Sold]]) -> 1 | K97: =IF(ISBLANK(Nikes_Sales_Dataset___Working_file[[#This Row],[MRP]]),MEDIAN(Nikes_Sales_Dataset___Working_file[[#All],[MRP]]),Nikes_Sales_Dataset___Working_file[[#This Row],[MRP]]) -> 6110.03 | M97: =IF(ISBLANK(Nikes_Sales_Dataset___Working_file[[#This Row],[Discount_Applied]]),0,Nikes_Sales_Dataset___Working_file[[#This Row],[Discount_Applied]]) -> 0 | N97: =Nikes_Sales_Dataset___Working_file[[#This Row],[MRP Final]]*(1-Nikes_Sales_Dataset___Working_file[[#This Row],[Cleaned Discount]]) -> 6110.03 | O97: 0 | P97: =Nikes_Sales_Dataset___Working_file[[#This Row],[Sales Price]]*Nikes_Sales_Dataset___Working_file[[#This Row],[Units Sold Filled]] -> 6110.03 | Q97: 45581 | R97: =IF(ISBLANK(Nikes_Sales_Dataset___Working_file[[#This Row],[Order_Date]]),"Unknown Date",Nikes_Sales_Dataset___Working_file[[#This Row],[Order_Date]]) -> 45581 | S97: =IF(ISNUMBER(Nikes_Sales_Dataset___Working_file[[#This Row],[Cleaned Order Date]]),TEXT(Nikes_Sales_Dataset___Working_file[[#This Row],[Cleaned Order Date]],"mmm"),"Unknown") -> Oct | T97: =IF(ISNUMBER(Nikes_Sales_Dataset___Working_file[[#This Row],[Cleaned Order Date]]),TEXT(Nikes_Sales_Dataset___Working_file[[#This Row],[Cleaned Order Date]],"yyyy"),"Unknown") -> 2024 | U97: Online | V97: Delhi | W97: Delhi | X97: 880.57
A98: 2096 | B98: =Nikes_Sales_Dataset___Working_file[[#This Row],[Order_ID]]&"_"&TEXT(Nikes_Sales_Dataset___Working_file[[#This Row],[Cleaned Order Date]],"yyyymmdd") -> 2096_20241224 | C98: Men | D98: Running | E98: Pegasus Turbo | F98: XL | G98: XL | H98: 2 | I98: =IF(ISBLANK(Nikes_Sales_Dataset___Working_file[[#This Row],[Units_Sold]]),IF(Nikes_Sales_Dataset___Working_file[[#This Row],[Profit]]<0,0,1),Nikes_Sales_Dataset___Working_file[[#This Row],[Units_Sold]]) -> 2 | K98: =IF(ISBLANK(Nikes_Sales_Dataset___Working_file[[#This Row],[MRP]]),MEDIAN(Nikes_Sales_Dataset___Working_file[[#All],[MRP]]),Nikes_Sales_Dataset___Working_file[[#This Row],[MRP]]) -> 6110.03 | M98: =IF(ISBLANK(Nikes_Sales_Dataset___Working_file[[#This Row],[Discount_Applied]]),0,Nikes_Sales_Dataset___Working_file[[#This Row],[Discount_Applied]]) -> 0 | N98: =Nikes_Sales_Dataset___Working_file[[#This Row],[MRP Final]]*(1-Nikes_Sales_Dataset___Working_file[[#This Row],[Cleaned Discount]]) -> 6110.03 | O98: 0 | P98: =Nikes_Sales_Dataset___Working_file[[#This Row],[Sales Price]]*Nikes_Sales_Dataset___Working_file[[#This Row],[Units Sold Filled]] -> 12220.06 | Q98: 45650 | R98: =IF(ISBLANK(Nikes_Sales_Dataset___Working_file[[#This Row],[Order_Date]]),"Unknown Date",Nikes_Sales_Dataset___Working_file[[#This Row],[Order_Date]]) -> 45650 | S98: =IF(ISNUMBER(Nikes_Sales_Dataset___Working_file[[#This Row],[Cleaned Order Date]]),TEXT(Nikes_Sales_Dataset___Working_file[[#This Row],[Cleaned Order Date]],"mmm"),"Unknown") -> Dec | T98: =IF(ISNUMBER(Nikes_Sales_Dataset___Working_file[[#This Row],[Cleaned Order Date]]),TEXT(Nikes_Sales_Dataset___Working_file[[#This Row],[Cleaned Order Date]],"yyyy"),"Unknown") -> 2024 | U98: Online | V98: Kolkata | W98: Kolkata | X98: 288.66
A99: 2097 | B99: =Nikes_Sales_Dataset___Working_file[[#This Row],[Order_ID]]&"_"&TEXT(Nikes_Sales_Dataset___Working_file[[#This Row],[Cleaned Order Date]],"yyyymmdd") -> 2097_Unknown Date | C99: Women | D99: Training | E99: ZoomX Invincible | F99: XL | G99: XL | I99: =IF(ISBLANK(Nikes_Sales_Dataset___Working_file[[#This Row],[Units_Sold]]),IF(Nikes_Sales_Dataset___Working_file[[#This Row],[Profit]]<0,0,1),Nikes_Sales_Dataset___Working_file[[#This Row],[Units_Sold]]) -> 1 | J99: 7978.89 | K99: =IF(ISBLANK(Nikes_Sales_Dataset___Working_file[[#This Row],[MRP]]),MEDIAN(Nikes_Sales_Dataset___Working_file[[#All],[MRP]]),Nikes_Sales_Dataset___Working_file[[#This Row],[MRP]]) -> 7978.89 | M99: =IF(ISBLANK(Nikes_Sales_Dataset___Working_file[[#This Row],[Discount_Applied]]),0,Nikes_Sales_Dataset___Working_file[[#This Row],[Discount_Applied]]) -> 0 | N99: =Nikes_Sales_Dataset___Working_file[[#This Row],[MRP Final]]*(1-Nikes_Sales_Dataset___Working_file[[#This Row],[Cleaned Discount]]) -> 7978.89 | O99: 0 | P99: =Nikes_Sales_Dataset___Working_file[[#This Row],[Sales Price]]*Nikes_Sales_Dataset___Working_file[[#This Row],[Units Sold Filled]] -> 7978.89 | R99: =IF(ISBLANK(Nikes_Sales_Dataset___Working_file[[#This Row],[Order_Date]]),"Unknown Date",Nikes_Sales_Dataset___Working_file[[#This Row],[Order_Date]]) -> Unknown Date | S99: =IF(ISNUMBER(Nikes_Sales_Dataset___Working_file[[#This Row],[Cleaned Order Date]]),TEXT(Nikes_Sales_Dataset___Working_file[[#This Row],[Cleaned Order Date]],"mmm"),"Unknown") -> Unknown | T99: =IF(ISNUMBER(Nikes_Sales_Dataset___Working_file[[#This Row],[Cleaned Order Date]]),TEXT(Nikes_Sales_Dataset___Working_file[[#This Row],[Cleaned Order Date]],"yyyy"),"Unknown") -> Unknown | U99: Online | V99: Bangalore | W99: Bangalore | X99: 769.05
A100: 2098 | B100: =Nikes_Sales_Dataset___Working_file[[#This Row],[Order_ID]]&"_"&TEXT(Nikes_Sales_Dataset___Working_file[[#This Row],[Cleaned Order Date]],"yyyymmdd") -> 2098_20240124 | C100: Men | D100: Training | E100: ZoomX Invincible | F100: L | G100: L | I100: =IF(ISBLANK(Nikes_Sales_Dataset___Working_file[[#This Row],[Units_Sold]]),IF(Nikes_Sales_Dataset___Working_file[[#This Row],[Profit]]<0,0,1),Nikes_Sales_Dataset___Working_file[[#This Row],[Units_Sold]]) -> 1 | J100: 5690.69 | K100: =IF(ISBLANK(Nikes_Sales_Dataset___Working_file[[#This Row],[MRP]]),MEDIAN(Nikes_Sales_Dataset___Working_file[[#All],[MRP]]),Nikes_Sales_Dataset___Working_file[[#This Row],[MRP]]) -> 5690.69 | L100: 0.69 | M100: =IF(ISBLANK(Nikes_Sales_Dataset___Working_file[[#This Row],[Discount_Applied]]),0,Nikes_Sales_Dataset___Working_file[[#This Row],[Discount_Applied]]) -> 0.69 | N100: =Nikes_Sales_Dataset___Working_file[[#This Row],[MRP Final]]*(1-Nikes_Sales_Dataset___Working_file[[#This Row],[Cleaned Discount]]) -> 1764.1139 | O100: 0 | P100: =Nikes_Sales_Dataset___Working_file[[#This Row],[Sales Price]]*Nikes_Sales_Dataset___Working_file[[#This Row],[Units Sold Filled]] -> 1764.1139 | Q100: 45315 | R100: =IF(ISBLANK(Nikes_Sales_Dataset___Working_file[[#This Row],[Order_Date]]),"Unknown Date",Nikes_Sales_Dataset___Working_file[[#This Row],[Order_Date]]) -> 45315 | S100: =IF(ISNUMBER(Nikes_Sales_Dataset___Working_file[[#This Row],[Cleaned Order Date]]),TEXT(Nikes_Sales_Dataset___Working_file[[#This Row],[Cleaned Order Date]],"mmm"),"Unknown") -> Jan | T100: =IF(ISNUMBER(Nikes_Sales_Dataset___Working_file[[#This Row],[Cleaned Order Date]]),TEXT(Nikes_Sales_Dataset___Working_file[[#This Row],[Cleaned Order Date]],"yyyy"),"Unknown") -> 2024 | U100: Online | V100: hyderbad | W100: Hyderabad | X100: 98.3
...

Sheet Cleaned and Transformed Dataset
A1: Order_ID | B1: Unique Order ID | C1: Gender Category | D1: Product Line | E1: Product Name | F1: Size Filled | G1: Units Sold Filled | H1: MRP Final | I1: Cleaned Discount | J1: Sales Price | K1: Calculated Revenue | L1: Cleaned Order Date | M1: Month | N1: Year | O1: Sales Channel | P1: Region Corrected | Q1: Profit
A2: 2000 | B2: =VLOOKUP('Nikes Sales Dataset - Worked f'!A:A,'Nikes Sales Dataset - Worked f'!A:B,2,FALSE) -> 2000_20240309 | C2: =VLOOKUP('Nikes Sales Dataset - Worked f'!A:A,'Nikes Sales Dataset - Worked f'!A:C,3,FALSE) -> Kids | D2: =VLOOKUP('Nikes Sales Dataset - Worked f'!A:A,'Nikes Sales Dataset - Worked f'!A:D,4,FALSE) -> Training | E2: =VLOOKUP('Nikes Sales Dataset - Worked f'!A:A,'Nikes Sales Dataset - Worked f'!A:E,5,FALSE) -> SuperRep Go | F2: =VLOOKUP('Nikes Sales Dataset - Worked f'!A:A,'Nikes Sales Dataset - Worked f'!A:G,7,FALSE) -> M | G2: =VLOOKUP('Nikes Sales Dataset - Worked f'!A:A,'Nikes Sales Dataset - Worked f'!A:I,9,FALSE) -> 0 | H2: =VLOOKUP('Nikes Sales Dataset - Worked f'!A:A,'Nikes Sales Dataset - Worked f'!A:K,11,FALSE) -> 6110.03 | I2: =_xlfn.XLOOKUP('Cleaned and Transformed Dataset'!A:A,'Nikes Sales Dataset - Worked f'!A:A,'Nikes Sales Dataset - Worked f'!M:M) -> 0.47 | J2: =_xlfn.XLOOKUP(A:A,'Nikes Sales Dataset - Worked f'!A:A,'Nikes Sales Dataset - Worked f'!N:N) -> 3238.3159 | K2: =_xlfn.XLOOKUP(A:A,'Nikes Sales Dataset - Worked f'!A:A,'Nikes Sales Dataset - Worked f'!P:P) -> 0 | L2: =VLOOKUP('Nikes Sales Dataset - Worked f'!A:A,'Nikes Sales Dataset - Worked f'!A:R,18,FALSE) -> 45360 | M2: =_xlfn.XLOOKUP(A:A,'Nikes Sales Dataset - Worked f'!A:A,'Nikes Sales Dataset - Worked f'!S:S) -> Mar | N2: =_xlfn.XLOOKUP(A:A,'Nikes Sales Dataset - Worked f'!A:A,'Nikes Sales Dataset - Worked f'!T:T) -> 2024 | O2: =_xlfn.XLOOKUP(A:A,'Nikes Sales Dataset - Worked f'!A:A,'Nikes Sales Dataset - Worked f'!U:U) -> Online | P2: =_xlfn.XLOOKUP(A:A,'Nikes Sales Dataset - Worked f'!A:A,'Nikes Sales Dataset - Worked f'!W:W) -> Bangalore | Q2: =_xlfn.XLOOKUP(A:A,'Nikes Sales Dataset - Worked f'!A:A,'Nikes Sales Dataset - Worked f'!X:X) -> -770.45
A3: 2001 | B3: =VLOOKUP('Nikes Sales Dataset - Worked f'!A:A,'Nikes Sales Dataset - Worked f'!A:B,2,FALSE) -> 2001_20240709 | C3: =VLOOKUP('Nikes Sales Dataset - Worked f'!A:A,'Nikes Sales Dataset - Worked f'!A:C,3,FALSE) -> Women | D3: =VLOOKUP('Nikes Sales Dataset - Worked f'!A:A,'Nikes Sales Dataset - Worked f'!A:D,4,FALSE) -> Soccer | E3: =VLOOKUP('Nikes Sales Dataset - Worked f'!A:A,'Nikes Sales Dataset - Worked f'!A:E,5,FALSE) -> Tiempo Legend | F3: =VLOOKUP('Nikes Sales Dataset - Worked f'!A:A,'Nikes Sales Dataset - Worked f'!A:G,7,FALSE) -> M | G3: =VLOOKUP('Nikes Sales Dataset - Worked f'!A:A,'Nikes Sales Dataset - Worked f'!A:I,9,FALSE) -> 3 | H3: =VLOOKUP('Nikes Sales Dataset - Worked f'!A:A,'Nikes Sales Dataset - Worked f'!A:K,11,FALSE) -> 4957.93 | I3: =_xlfn.XLOOKUP('Cleaned and Transformed Dataset'!A:A,'Nikes Sales Dataset - Worked f'!A:A,'Nikes Sales Dataset - Worked f'!M:M) -> 0 | J3: =_xlfn.XLOOKUP(A:A,'Nikes Sales Dataset - Worked f'!A:A,'Nikes Sales Dataset - Worked f'!N:N) -> 4957.93 | K3: =_xlfn.XLOOKUP(A:A,'Nikes Sales Dataset - Worked f'!A:A,'Nikes Sales Dataset - Worked f'!P:P) -> 14873.79 | L3: =VLOOKUP('Nikes Sales Dataset - Worked f'!A:A,'Nikes Sales Dataset - Worked f'!A:R,18,FALSE) -> 45482 | M3: =_xlfn.XLOOKUP(A:A,'Nikes Sales Dataset - Worked f'!A:A,'Nikes Sales Dataset - Worked f'!S:S) -> Jul | N3: =_xlfn.XLOOKUP(A:A,'Nikes Sales Dataset - Worked f'!A:A,'Nikes Sales Dataset - Worked f'!T:T) -> 2024 | O3: =_xlfn.XLOOKUP(A:A,'Nikes Sales Dataset - Worked f'!A:A,'Nikes Sales Dataset - Worked f'!U:U) -> Retail | P3: =_xlfn.XLOOKUP(A:A,'Nikes Sales Dataset - Worked f'!A:A,'Nikes Sales Dataset - Worked f'!W:W) -> Hyderabad | Q3: =_xlfn.XLOOKUP(A:A,'Nikes Sales Dataset - Worked f'!A:A,'Nikes Sales Dataset - Worked f'!X:X) -> -112.53
A4: 2002 | B4: =VLOOKUP('Nikes Sales Dataset - Worked f'!A:A,'Nikes Sales Dataset - Worked f'!A:B,2,FALSE) -> 2002_Unknown Date | C4: =VLOOKUP('Nikes Sales Dataset - Worked f'!A:A,'Nikes Sales Dataset - Worked f'!A:C,3,FALSE) -> Women | D4: =VLOOKUP('Nikes Sales Dataset - Worked f'!A:A,'Nikes Sales Dataset - Worked f'!A:D,4,FALSE) -> Soccer | E4: =VLOOKUP('Nikes Sales Dataset - Worked f'!A:A,'Nikes Sales Dataset - Worked f'!A:E,5,FALSE) -> Premier III | F4: =VLOOKUP('Nikes Sales Dataset - Worked f'!A:A,'Nikes Sales Dataset - Worked f'!A:G,7,FALSE) -> M | G4: =VLOOKUP('Nikes Sales Dataset - Worked f'!A:A,'Nikes Sales Dataset - Worked f'!A:I,9,FALSE) -> 4 | H4: =VLOOKUP('Nikes Sales Dataset - Worked f'!A:A,'Nikes Sales Dataset - Worked f'!A:K,11,FALSE) -> 6110.03 | I4: =_xlfn.XLOOKUP('Cleaned and Transformed Dataset'!A:A,'Nikes Sales Dataset - Worked f'!A:A,'Nikes Sales Dataset - Worked f'!M:M) -> 0 | J4: =_xlfn.XLOOKUP(A:A,'Nikes Sales Dataset - Worked f'!A:A,'Nikes Sales Dataset - Worked f'!N:N) -> 6110.03 | K4: =_xlfn.XLOOKUP(A:A,'Nikes Sales Dataset - Worked f'!A:A,'Nikes Sales Dataset - Worked f'!P:P) -> 24440.12 | L4: =VLOOKUP('Nikes Sales Dataset - Worked f'!A:A,'Nikes Sales Dataset - Worked f'!A:R,18,FALSE) -> Unknown Date | M4: =_xlfn.XLOOKUP(A:A,'Nikes Sales Dataset - Worked f'!A:A,'Nikes Sales Dataset - Worked f'!S:S) -> Unknown | N4: =_xlfn.XLOOKUP(A:A,'Nikes Sales Dataset - Worked f'!A:A,'Nikes Sales Dataset - Worked f'!T:T) -> Unknown | O4: =_xlfn.XLOOKUP(A:A,'Nikes Sales Dataset - Worked f'!A:A,'Nikes Sales Dataset - Worked f'!U:U) -> Retail | P4: =_xlfn.XLOOKUP(A:A,'Nikes Sales Dataset - Worked f'!A:A,'Nikes Sales Dataset - Worked f'!W:W) -> Mumbai | Q4: =_xlfn.XLOOKUP(A:A,'Nikes Sales Dataset - Worked f'!A:A,'Nikes Sales Dataset - Worked f'!X:X) -> 3337.34
A5: 2003 | B5: =VLOOKUP('Nikes Sales Dataset - Worked f'!A:A,'Nikes Sales Dataset - Worked f'!A:B,2,FALSE) -> 2003_20241004 | C5: =VLOOKUP('Nikes Sales Dataset - Worked f'!A:A,'Nikes Sales Dataset - Worked f'!A:C,3,FALSE) -> Kids | D5: =VLOOKUP('Nikes Sales Dataset - Worked f'!A:A,'Nikes Sales Dataset - Worked f'!A:D,4,FALSE) -> Lifestyle | E5: =VLOOKUP('Nikes Sales Dataset - Worked f'!A:A,'Nikes Sales Dataset - Worked f'!A:E,5,FALSE) -> Blazer Mid | F5: =VLOOKUP('Nikes Sales Dataset - Worked f'!A:A,'Nikes Sales Dataset - Worked f'!A:G,7,FALSE) -> L | G5: =VLOOKUP('Nikes Sales Dataset - Worked f'!A:A,'Nikes Sales Dataset - Worked f'!A:I,9,FALSE) -> 1 | H5: =VLOOKUP('Nikes Sales Dataset - Worked f'!A:A,'Nikes Sales Dataset - Worked f'!A:K,11,FALSE) -> 9673.57 | I5: =_xlfn.XLOOKUP('Cleaned and Transformed Dataset'!A:A,'Nikes Sales Dataset - Worked f'!A:A,'Nikes Sales Dataset - Worked f'!M:M) -> 0 | J5: =_xlfn.XLOOKUP(A:A,'Nikes Sales Dataset - Worked f'!A:A,'Nikes Sales Dataset - Worked f'!N:N) -> 9673.57 | K5: =_xlfn.XLOOKUP(A:A,'Nikes Sales Dataset - Worked f'!A:A,'Nikes Sales Dataset - Worked f'!P:P) -> 9673.57 | L5: =VLOOKUP('Nikes Sales Dataset - Worked f'!A:A,'Nikes Sales Dataset - Worked f'!A:R,18,FALSE) -> 45569 | M5: =_xlfn.XLOOKUP(A:A,'Nikes Sales Dataset - Worked f'!A:A,'Nikes Sales Dataset - Worked f'!S:S) -> Oct | N5: =_xlfn.XLOOKUP(A:A,'Nikes Sales Dataset - Worked f'!A:A,'Nikes Sales Dataset - Worked f'!T:T) -> 2024 | O5: =_xlfn.XLOOKUP(A:A,'Nikes Sales Dataset - Worked f'!A:A,'Nikes Sales Dataset - Worked f'!U:U) -> Online | P5: =_xlfn.XLOOKUP(A:A,'Nikes Sales Dataset - Worked f'!A:A,'Nikes Sales Dataset - Worked f'!W:W) -> Pune | Q5: =_xlfn.XLOOKUP(A:A,'Nikes Sales Dataset - Worked f'!A:A,'Nikes Sales Dataset - Worked f'!X:X) -> 3376.85
A6: 2004 | B6: =VLOOKUP('Nikes Sales Dataset - Worked f'!A:A,'Nikes Sales Dataset - Worked f'!A:B,2,FALSE) -> 2004_20240912 | C6: =VLOOKUP('Nikes Sales Dataset - Worked f'!A:A,'Nikes Sales Dataset - Worked f'!A:C,3,FALSE) -> Kids | D6: =VLOOKUP('Nikes Sales Dataset - Worked f'!A:A,'Nikes Sales Dataset - Worked f'!A:D,4,FALSE) -> Running | E6: =VLOOKUP('Nikes Sales Dataset - Worked f'!A:A,'Nikes Sales Dataset - Worked f'!A:E,5,FALSE) -> React Infinity | F6: =VLOOKUP('Nikes Sales Dataset - Worked f'!A:A,'Nikes Sales Dataset - Worked f'!A:G,7,FALSE) -> XL | G6: =VLOOKUP('Nikes Sales Dataset - Worked f'!A:A,'Nikes Sales Dataset - Worked f'!A:I,9,FALSE) -> 1 | H6: =VLOOKUP('Nikes Sales Dataset - Worked f'!A:A,'Nikes Sales Dataset - Worked f'!A:K,11,FALSE) -> 6110.03 | I6: =_xlfn.XLOOKUP('Cleaned and Transformed Dataset'!A:A,'Nikes Sales Dataset - Worked f'!A:A,'Nikes Sales Dataset - Worked f'!M:M) -> 0 | J6: =_xlfn.XLOOKUP(A:A,'Nikes Sales Dataset - Worked f'!A:A,'Nikes Sales Dataset - Worked f'!N:N) -> 6110.03 | K6: =_xlfn.XLOOKUP(A:A,'Nikes Sales Dataset - Worked f'!A:A,'Nikes Sales Dataset - Worked f'!P:P) -> 6110.03 | L6: =VLOOKUP('Nikes Sales Dataset - Worked f'!A:A,'Nikes Sales Dataset - Worked f'!A:R,18,FALSE) -> 45547 | M6: =_xlfn.XLOOKUP(A:A,'Nikes Sales Dataset - Worked f'!A:A,'Nikes Sales Dataset - Worked f'!S:S) -> Sep | N6: =_xlfn.XLOOKUP(A:A,'Nikes Sales Dataset - Worked f'!A:A,'Nikes Sales Dataset - Worked f'!T:T) -> 2024 | O6: =_xlfn.XLOOKUP(A:A,'Nikes Sales Dataset - Worked f'!A:A,'Nikes Sales Dataset - Worked f'!U:U) -> Retail | P6: =_xlfn.XLOOKUP(A:A,'Nikes Sales Dataset - Worked f'!A:A,'Nikes Sales Dataset - Worked f'!W:W) -> Delhi | Q6: =_xlfn.XLOOKUP(A:A,'Nikes Sales Dataset - Worked f'!A:A,'Nikes Sales Dataset - Worked f'!X:X) -> 187.89
A7: 2005 | B7: =VLOOKUP('Nikes Sales Dataset - Worked f'!A:A,'Nikes Sales Dataset - Worked f'!A:B,2,FALSE) -> 2005_Unknown Date | C7: =VLOOKUP('Nikes Sales Dataset - Worked f'!A:A,'Nikes Sales Dataset - Worked f'!A:C,3,FALSE) -> Women | D7: =VLOOKUP('Nikes Sales Dataset - Worked f'!A:A,'Nikes Sales Dataset - Worked f'!A:D,4,FALSE) -> Training | E7: =VLOOKUP('Nikes Sales Dataset - Worked f'!A:A,'Nikes Sales Dataset - Worked f'!A:E,5,FALSE) -> Flex Trainer | F7: =VLOOKUP('Nikes Sales Dataset - Worked f'!A:A,'Nikes Sales Dataset - Worked f'!A:G,7,FALSE) -> M | G7: =VLOOKUP('Nikes Sales Dataset - Worked f'!A:A,'Nikes Sales Dataset - Worked f'!A:I,9,FALSE) -> 1 | H7: =VLOOKUP('Nikes Sales Dataset - Worked f'!A:A,'Nikes Sales Dataset - Worked f'!A:K,11,FALSE) -> 7363.96 | I7: =_xlfn.XLOOKUP('Cleaned and Transformed Dataset'!A:A,'Nikes Sales Dataset - Worked f'!A:A,'Nikes Sales Dataset - Worked f'!M:M) -> 0 | J7: =_xlfn.XLOOKUP(A:A,'Nikes Sales Dataset - Worked f'!A:A,'Nikes Sales Dataset - Worked f'!N:N) -> 7363.96 | K7: =_xlfn.XLOOKUP(A:A,'Nikes Sales Dataset - Worked f'!A:A,'Nikes Sales Dataset - Worked f'!P:P) -> 7363.96 | L7: =VLOOKUP('Nikes Sales Dataset - Worked f'!A:A,'Nikes Sales Dataset - Worked f'!A:R,18,FALSE) -> Unknown Date | M7: =_xlfn.XLOOKUP(A:A,'Nikes Sales Dataset - Worked f'!A:A,'Nikes Sales Dataset - Worked f'!S:S) -> Unknown | N7: =_xlfn.XLOOKUP(A:A,'Nikes Sales Dataset - Worked f'!A:A,'Nikes Sales Dataset - Worked f'!T:T) -> Unknown | O7: =_xlfn.XLOOKUP(A:A,'Nikes Sales Dataset - Worked f'!A:A,'Nikes Sales Dataset - Worked f'!U:U) -> Retail | P7: =_xlfn.XLOOKUP(A:A,'Nikes Sales Dataset - Worked f'!A:A,'Nikes Sales Dataset - Worked f'!W:W) -> Delhi | Q7: =_xlfn.XLOOKUP(A:A,'Nikes Sales Dataset - Worked f'!A:A,'Nikes Sales Dataset - Worked f'!X:X) -> 1415.98
A8: 2006 | B8: =VLOOKUP('Nikes Sales Dataset - Worked f'!A:A,'Nikes Sales Dataset - Worked f'!A:B,2,FALSE) -> 2006_20250604 | C8: =VLOOKUP('Nikes Sales Dataset - Worked f'!A:A,'Nikes Sales Dataset - Worked f'!A:C,3,FALSE) -> Men | D8: =VLOOKUP('Nikes Sales Dataset - Worked f'!A:A,'Nikes Sales Dataset - Worked f'!A:D,4,FALSE) -> Training | E8: =VLOOKUP('Nikes Sales Dataset - Worked f'!A:A,'Nikes Sales Dataset - Worked f'!A:E,5,FALSE) -> SuperRep Go | F8: =VLOOKUP('Nikes Sales Dataset - Worked f'!A:A,'Nikes Sales Dataset - Worked f'!A:G,7,FALSE) -> M | G8: =VLOOKUP('Nikes Sales Dataset - Worked f'!A:A,'Nikes Sales Dataset - Worked f'!A:I,9,FALSE) -> 1 | H8: =VLOOKUP('Nikes Sales Dataset - Worked f'!A:A,'Nikes Sales Dataset - Worked f'!A:K,11,FALSE) -> 6819.78 | I8: =_xlfn.XLOOKUP('Cleaned and Transformed Dataset'!A:A,'Nikes Sales Dataset - Worked f'!A:A,'Nikes Sales Dataset - Worked f'!M:M) -> 0 | J8: =_xlfn.XLOOKUP(A:A,'Nikes Sales Dataset - Worked f'!A:A,'Nikes Sales Dataset - Worked f'!N:N) -> 6819.78 | K8: =_xlfn.XLOOKUP(A:A,'Nikes Sales Dataset - Worked f'!A:A,'Nikes Sales Dataset - Worked f'!P:P) -> 6819.78 | L8: =VLOOKUP('Nikes Sales Dataset - Worked f'!A:A,'Nikes Sales Dataset - Worked f'!A:R,18,FALSE) -> 45812 | M8: =_xlfn.XLOOKUP(A:A,'Nikes Sales Dataset - Worked f'!A:A,'Nikes Sales Dataset - Worked f'!S:S) -> Jun | N8: =_xlfn.XLOOKUP(A:A,'Nikes Sales Dataset - Worked f'!A:A,'Nikes Sales Dataset - Worked f'!T:T) -> 2025 | O8: =_xlfn.XLOOKUP(A:A,'Nikes Sales Dataset - Worked f'!A:A,'Nikes Sales Dataset - Worked f'!U:U) -> Online | P8: =_xlfn.XLOOKUP(A:A,'Nikes Sales Dataset - Worked f'!A:A,'Nikes Sales Dataset - Worked f'!W:W) -> Bangalore | Q8: =_xlfn.XLOOKUP(A:A,'Nikes Sales Dataset - Worked f'!A:A,'Nikes Sales Dataset - Worked f'!X:X) -> 1802.09
A9: 2007 | B9: =VLOOKUP('Nikes Sales Dataset - Worked f'!A:A,'Nikes Sales Dataset - Worked f'!A:B,2,FALSE) -> 2007_Unknown Date | C9: =VLOOKUP('Nikes Sales Dataset - Worked f'!A:A,'Nikes Sales Dataset - Worked f'!A:C,3,FALSE) -> Kids | D9: =VLOOKUP('Nikes Sales Dataset - Worked f'!A:A,'Nikes Sales Dataset - Worked f'!A:D,4,FALSE) -> Training | E9: =VLOOKUP('Nikes Sales Dataset - Worked f'!A:A,'Nikes Sales Dataset - Worked f'!A:E,5,FALSE) -> SuperRep Go | F9: =VLOOKUP('Nikes Sales Dataset - Worked f'!A:A,'Nikes Sales Dataset - Worked f'!A:G,7,FALSE) -> M | G9: =VLOOKUP('Nikes Sales Dataset - Worked f'!A:A,'Nikes Sales Dataset - Worked f'!A:I,9,FALSE) -> 1 | H9: =VLOOKUP('Nikes Sales Dataset - Worked f'!A:A,'Nikes Sales Dataset - Worked f'!A:K,11,FALSE) -> 6110.03 | I9: =_xlfn.XLOOKUP('Cleaned and Transformed Dataset'!A:A,'Nikes Sales Dataset - Worked f'!A:A,'Nikes Sales Dataset - Worked f'!M:M) -> 0.32 | J9: =_xlfn.XLOOKUP(A:A,'Nikes Sales Dataset - Worked f'!A:A,'Nikes Sales Dataset - Worked f'!N:N) -> 4154.8204 | K9: =_xlfn.XLOOKUP(A:A,'Nikes Sales Dataset - Worked f'!A:A,'Nikes Sales Dataset - Worked f'!P:P) -> 4154.8204 | L9: =VLOOKUP('Nikes Sales Dataset - Worked f'!A:A,'Nikes Sales Dataset - Worked f'!A:R,18,FALSE) -> Unknown Date | M9: =_xlfn.XLOOKUP(A:A,'Nikes Sales Dataset - Worked f'!A:A,'Nikes Sales Dataset - Worked f'!S:S) -> Unknown | N9: =_xlfn.XLOOKUP(A:A,'Nikes Sales Dataset - Worked f'!A:A,'Nikes Sales Dataset - Worked f'!T:T) -> Unknown | O9: =_xlfn.XLOOKUP(A:A,'Nikes Sales Dataset - Worked f'!A:A,'Nikes Sales Dataset - Worked f'!U:U) -> Retail | P9: =_xlfn.XLOOKUP(A:A,'Nikes Sales Dataset - Worked f'!A:A,'Nikes Sales Dataset - Worked f'!W:W) -> Bangalore | Q9: =_xlfn.XLOOKUP(A:A,'Nikes Sales Dataset - Worked f'!A:A,'Nikes Sales Dataset - Worked f'!X:X) -> 2928.36
A10: 2008 | B10: =VLOOKUP('Nikes Sales Dataset - Worked f'!A:A,'Nikes Sales Dataset - Worked f'!A:B,2,FALSE) -> 2008_20241011 | C10: =VLOOKUP('Nikes Sales Dataset - Worked f'!A:A,'Nikes Sales Dataset - Worked f'!A:C,3,FALSE) -> Women | D10: =VLOOKUP('Nikes Sales Dataset - Worked f'!A:A,'Nikes Sales Dataset - Worked f'!A:D,4,FALSE) -> Soccer | E10: =VLOOKUP('Nikes Sales Dataset - Worked f'!A:A,'Nikes Sales Dataset - Worked f'!A:E,5,FALSE) -> Premier III | F10: =VLOOKUP('Nikes Sales Dataset - Worked f'!A:A,'Nikes Sales Dataset - Worked f'!A:G,7,FALSE) -> L | G10: =VLOOKUP('Nikes Sales Dataset - Worked f'!A:A,'Nikes Sales Dataset - Worked f'!A:I,9,FALSE) -> -1 | H10: =VLOOKUP('Nikes Sales Dataset - Worked f'!A:A,'Nikes Sales Dataset - Worked f'!A:K,11,FALSE) -> 6110.03 | I10: =_xlfn.XLOOKUP('Cleaned and Transformed Dataset'!A:A,'Nikes Sales Dataset - Worked f'!A:A,'Nikes Sales Dataset - Worked f'!M:M) -> 0 | J10: =_xlfn.XLOOKUP(A:A,'Nikes Sales Dataset - Worked f'!A:A,'Nikes Sales Dataset - Worked f'!N:N) -> 6110.03 | K10: =_xlfn.XLOOKUP(A:A,'Nikes Sales Dataset - Worked f'!A:A,'Nikes Sales Dataset - Worked f'!P:P) -> -6110.03 | L10: =VLOOKUP('Nikes Sales Dataset - Worked f'!A:A,'Nikes Sales Dataset - Worked f'!A:R,18,FALSE) -> 45576 | M10: =_xlfn.XLOOKUP(A:A,'Nikes Sales Dataset - Worked f'!A:A,'Nikes Sales Dataset - Worked f'!S:S) -> Oct | N10: =_xlfn.XLOOKUP(A:A,'Nikes Sales Dataset - Worked f'!A:A,'Nikes Sales Dataset - Worked f'!T:T) -> 2024 | O10: =_xlfn.XLOOKUP(A:A,'Nikes Sales Dataset - Worked f'!A:A,'Nikes Sales Dataset - Worked f'!U:U) -> Online | P10: =_xlfn.XLOOKUP(A:A,'Nikes Sales Dataset - Worked f'!A:A,'Nikes Sales Dataset - Worked f'!W:W) -> Hyderabad | Q10: =_xlfn.XLOOKUP(A:A,'Nikes Sales Dataset - Worked f'!A:A,'Nikes Sales Dataset - Worked f'!X:X) -> -731.18
A11: 2009 | B11: =VLOOKUP('Nikes Sales Dataset - Worked f'!A:A,'Nikes Sales Dataset - Worked f'!A:B,2,FALSE) -> 2009_Unknown Date | C11: =VLOOKUP('Nikes Sales Dataset - Worked f'!A:A,'Nikes Sales Dataset - Worked f'!A:C,3,FALSE) -> Men | D11: =VLOOKUP('Nikes Sales Dataset - Worked f'!A:A,'Nikes Sales Dataset - Worked f'!A:D,4,FALSE) -> Soccer | E11: =VLOOKUP('Nikes Sales Dataset - Worked f'!A:A,'Nikes Sales Dataset - Worked f'!A:E,5,FALSE) -> Mercurial Superfly | F11: =VLOOKUP('Nikes Sales Dataset - Worked f'!A:A,'Nikes Sales Dataset - Worked f'!A:G,7,FALSE) -> M | G11: =VLOOKUP('Nikes Sales Dataset - Worked f'!A:A,'Nikes Sales Dataset - Worked f'!A:I,9,FALSE) -> 4 | H11: =VLOOKUP('Nikes Sales Dataset - Worked f'!A:A,'Nikes Sales Dataset - Worked f'!A:K,11,FALSE) -> 6110.03 | I11: =_xlfn.XLOOKUP('Cleaned and Transformed Dataset'!A:A,'Nikes Sales Dataset - Worked f'!A:A,'Nikes Sales Dataset - Worked f'!M:M) -> 0 | J11: =_xlfn.XLOOKUP(A:A,'Nikes Sales Dataset - Worked f'!A:A,'Nikes Sales Dataset - Worked f'!N:N) -> 6110.03 | K11: =_xlfn.XLOOKUP(A:A,'Nikes Sales Dataset - Worked f'!A:A,'Nikes Sales Dataset - Worked f'!P:P) -> 24440.12 | L11: =VLOOKUP('Nikes Sales Dataset - Worked f'!A:A,'Nikes Sales Dataset - Worked f'!A:R,18,FALSE) -> Unknown Date | M11: =_xlfn.XLOOKUP(A:A,'Nikes Sales Dataset - Worked f'!A:A,'Nikes Sales Dataset - Worked f'!S:S) -> Unknown | N11: =_xlfn.XLOOKUP(A:A,'Nikes Sales Dataset - Worked f'!A:A,'Nikes Sales Dataset - Worked f'!T:T) -> Unknown | O11: =_xlfn.XLOOKUP(A:A,'Nikes Sales Dataset - Worked f'!A:A,'Nikes Sales Dataset - Worked f'!U:U) -> Online | P11: =_xlfn.XLOOKUP(A:A,'Nikes Sales Dataset - Worked f'!A:A,'Nikes Sales Dataset - Worked f'!W:W) -> Pune | Q11: =_xlfn.XLOOKUP(A:A,'Nikes Sales Dataset - Worked f'!A:A,'Nikes Sales Dataset - Worked f'!X:X) -> 3929.61
A12: 2010 | B12: =VLOOKUP('Nikes Sales Dataset - Worked f'!A:A,'Nikes Sales Dataset - Worked f'!A:B,2,FALSE) -> 2010_20250116 | C12: =VLOOKUP('Nikes Sales Dataset - Worked f'!A:A,'Nikes Sales Dataset - Worked f'!A:C,3,FALSE) -> Kids | D12: =VLOOKUP('Nikes Sales Dataset - Worked f'!A:A,'Nikes Sales Dataset - Worked f'!A:D,4,FALSE) -> Lifestyle | E12: =VLOOKUP('Nikes Sales Dataset - Worked f'!A:A,'Nikes Sales Dataset - Worked f'!A:E,5,FALSE) -> Waffle One | F12: =VLOOKUP('Nikes Sales Dataset - Worked f'!A:A,'Nikes Sales Dataset - Worked f'!A:G,7,FALSE) -> L | G12: =VLOOKUP('Nikes Sales Dataset - Worked f'!A:A,'Nikes Sales Dataset - Worked f'!A:I,9,FALSE) -> 1 | H12: =VLOOKUP('Nikes Sales Dataset - Worked f'!A:A,'Nikes Sales Dataset - Worked f'!A:K,11,FALSE) -> 7949.83 | I12: =_xlfn.XLOOKUP('Cleaned and Transformed Dataset'!A:A,'Nikes Sales Dataset - Worked f'!A:A,'Nikes Sales Dataset - Worked f'!M:M) -> 0 | J12: =_xlfn.XLOOKUP(A:A,'Nikes Sales Dataset - Worked f'!A:A,'Nikes Sales Dataset - Worked f'!N:N) -> 7949.83 | K12: =_xlfn.XLOOKUP(A:A,'Nikes Sales Dataset - Worked f'!A:A,'Nikes Sales Dataset - Worked f'!P:P) -> 7949.83 | L12: =VLOOKUP('Nikes Sales Dataset - Worked f'!A:A,'Nikes Sales Dataset - Worked f'!A:R,18,FALSE) -> 45673 | M12: =_xlfn.XLOOKUP(A:A,'Nikes Sales Dataset - Worked f'!A:A,'Nikes Sales Dataset - Worked f'!S:S) -> Jan | N12: =_xlfn.XLOOKUP(A:A,'Nikes Sales Dataset - Worked f'!A:A,'Nikes Sales Dataset - Worked f'!T:T) -> 2025 | O12: =_xlfn.XLOOKUP(A:A,'Nikes Sales Dataset - Worked f'!A:A,'Nikes Sales Dataset - Worked f'!U:U) -> Online | P12: =_xlfn.XLOOKUP(A:A,'Nikes Sales Dataset - Worked f'!A:A,'Nikes Sales Dataset - Worked f'!W:W) -> Pune | Q12: =_xlfn.XLOOKUP(A:A,'Nikes Sales Dataset - Worked f'!A:A,'Nikes Sales Dataset - Worked f'!X:X) -> 1965.56
A13: 2011 | B13: =VLOOKUP('Nikes Sales Dataset - Worked f'!A:A,'Nikes Sales Dataset - Worked f'!A:B,2,FALSE) -> 2011_Unknown Date | C13: =VLOOKUP('Nikes Sales Dataset - Worked f'!A:A,'Nikes Sales Dataset - Worked f'!A:C,3,FALSE) -> Women | D13: =VLOOKUP('Nikes Sales Dataset - Worked f'!A:A,'Nikes Sales Dataset - Worked f'!A:D,4,FALSE) -> Training | E13: =VLOOKUP('Nikes Sales Dataset - Worked f'!A:A,'Nikes Sales Dataset - Worked f'!A:E,5,FALSE) -> Flex Trainer | F13: =VLOOKUP('Nikes Sales Dataset - Worked f'!A:A,'Nikes Sales Dataset - Worked f'!A:G,7,FALSE) -> L | G13: =VLOOKUP('Nikes Sales Dataset - Worked f'!A:A,'Nikes Sales Dataset - Worked f'!A:I,9,FALSE) -> -1 | H13: =VLOOKUP('Nikes Sales Dataset - Worked f'!A:A,'Nikes Sales Dataset - Worked f'!A:K,11,FALSE) -> 9586.08 | I13: =_xlfn.XLOOKUP('Cleaned and Transformed Dataset'!A:A,'Nikes Sales Dataset - Worked f'!A:A,'Nikes Sales Dataset - Worked f'!M:M) -> 0 | J13: =_xlfn.XLOOKUP(A:A,'Nikes Sales Dataset - Worked f'!A:A,'Nikes Sales Dataset - Worked f'!N:N) -> 9586.08 | K13: =_xlfn.XLOOKUP(A:A,'Nikes Sales Dataset - Worked f'!A:A,'Nikes Sales Dataset - Worked f'!P:P) -> -9586.08 | L13: =VLOOKUP('Nikes Sales Dataset - Worked f'!A:A,'Nikes Sales Dataset - Worked f'!A:R,18,FALSE) -> Unknown Date | M13: =_xlfn.XLOOKUP(A:A,'Nikes Sales Dataset - Worked f'!A:A,'Nikes Sales Dataset - Worked f'!S:S) -> Unknown | N13: =_xlfn.XLOOKUP(A:A,'Nikes Sales Dataset - Worked f'!A:A,'Nikes Sales Dataset - Worked f'!T:T) -> Unknown | O13: =_xlfn.XLOOKUP(A:A,'Nikes Sales Dataset - Worked f'!A:A,'Nikes Sales Dataset - Worked f'!U:U) -> Retail | P13: =_xlfn.XLOOKUP(A:A,'Nikes Sales Dataset - Worked f'!A:A,'Nikes Sales Dataset - Worked f'!W:W) -> Hyderabad | Q13: =_xlfn.XLOOKUP(A:A,'Nikes Sales Dataset - Worked f'!A:A,'Nikes Sales Dataset - Worked f'!X:X) -> 1667.08
... A2501: 4499 | B2501: =VLOOKUP('Nikes Sales Dataset - Worked f'!A:A,'Nikes Sales Dataset - Worked f'!A:B,2,FALSE) -> 4499_20241123 | C2501: =VLOOKUP('Nikes Sales Dataset - Worked f'!A:A,'Nikes Sales Dataset - Worked f'!A:C,3,FALSE) -> Women | D2501: =VLOOKUP('Nikes Sales Dataset - Worked f'!A:A,'Nikes Sales Dataset - Worked f'!A:D,4,FALSE) -> Running | E2501: =VLOOKUP('Nikes Sales Dataset - Worked f'!A:A,'Nikes Sales Dataset - Worked f'!A:E,5,FALSE) -> Air Zoom | F2501: =VLOOKUP('Nikes Sales Dataset - Worked f'!A:A,'Nikes Sales Dataset - Worked f'!A:G,7,FALSE) -> M | G2501: =VLOOKUP('Nikes Sales Dataset - Worked f'!A:A,'Nikes Sales Dataset - Worked f'!A:I,9,FALSE) -> 1 | H2501: =VLOOKUP('Nikes Sales Dataset - Worked f'!A:A,'Nikes Sales Dataset - Worked f'!A:K,11,FALSE) -> 5550.99 | I2501: =_xlfn.XLOOKUP('Cleaned and Transformed Dataset'!A:A,'Nikes Sales Dataset - Worked f'!A:A,'Nikes Sales Dataset - Worked f'!M:M) -> 0 | J2501: =_xlfn.XLOOKUP(A:A,'Nikes Sales Dataset - Worked f'!A:A,'Nikes Sales Dataset - Worked f'!N:N) -> 5550.99 | K2501: =_xlfn.XLOOKUP(A:A,'Nikes Sales Dataset - Worked f'!A:A,'Nikes Sales Dataset - Worked f'!P:P) -> 5550.99 | L2501: =VLOOKUP('Nikes Sales Dataset - Worked f'!A:A,'Nikes Sales Dataset - Worked f'!A:R,18,FALSE) -> 45619 | M2501: =_xlfn.XLOOKUP(A:A,'Nikes Sales Dataset - Worked f'!A:A,'Nikes Sales Dataset - Worked f'!S:S) -> Nov | N2501: =_xlfn.XLOOKUP(A:A,'Nikes Sales Dataset - Worked f'!A:A,'Nikes Sales Dataset - Worked f'!T:T) -> 2024 | O2501: =_xlfn.XLOOKUP(A:A,'Nikes Sales Dataset - Worked f'!A:A,'Nikes Sales Dataset - Worked f'!U:U) -> Retail | P2501: =_xlfn.XLOOKUP(A:A,'Nikes Sales Dataset - Worked f'!A:A,'Nikes Sales Dataset - Worked f'!W:W) -> Mumbai | Q2501: =_xlfn.XLOOKUP(A:A,'Nikes Sales Dataset - Worked f'!A:A,'Nikes Sales Dataset - Worked f'!X:X) -> 2453.57

Sheet Data analysis-Pivot Tables
A2: 1. Sales with respect to gender category | G2: 2. Profit with respect to gender category
A4: Row Labels | B4: Sum of Sales Price | G4: Row Labels | H4: Sum of Profit
A5: Kids | B5: 4009809 | G5: Kids | H5: 1159573.7
A6: Men | B6: 3962305.7 | G6: Men | H6: 1095421.1
A7: Women | B7: 3958315.1 | G7: Women | H7: 1193031.9
A8: Grand Total | B8: 11930430 | G8: Grand Total | H8: 3448026.6
A10: Findings: The category of kids contribute to high percentage of sales | G10: Findings: The profit generators are category of women
A12: 3. Most selling product category and product brand | J12: 4. Profitable category and Brand
